{
  "limit": 96,
  "offset": 0,
  "results": [
    {
      "tx_id": "0xf80ccf900b08b777809dbbdd9af50ef45dc57611604a8e1866bb010c97c36012",
      "nonce": 4286,
      "fee_rate": "0",
      "sender_address": "SP1R7EKK639BRCMJ3R1KC1RM7M0CF0X4S5ACNYSRE",
      "sponsored": false,
      "post_condition_mode": "deny",
      "post_conditions": [],
      "anchor_mode": "on_chain_only",
      "is_unanchored": false,
      "block_hash": "0xeae541b09caa3d57fa3c5581fa5e8ed995dff8e1fc0b1646d8d249902c656943",
      "parent_block_hash": "0xa80328e36b7b0d127d1c0a129eff649ec2ddb6d551e98a38219490fcf2116e59",
      "block_height": 39610,
      "burn_block_time": 1638174864,
      "burn_block_time_iso": "2021-11-29T08:34:24.000Z",
      "parent_burn_block_time": 1638173957,
      "parent_burn_block_time_iso": "2021-11-29T08:19:17.000Z",
      "canonical": true,
      "tx_index": 0,
      "tx_status": "success",
      "tx_result": {
        "hex": "0x0703",
        "repr": "(ok true)"
      },
      "microblock_hash": "",
      "microblock_sequence": 2147483647,
      "microblock_canonical": true,
      "event_count": 0,
      "events": [],
      "execution_cost_read_count": 0,
      "execution_cost_read_length": 0,
      "execution_cost_runtime": 0,
      "execution_cost_write_count": 0,
      "execution_cost_write_length": 0,
      "tx_type": "coinbase",
      "coinbase_payload": {
        "data": "0x0000000000000000000000000000000000000000000000000000000000000000"
      }
    },
    {
      "tx_id": "0xbe34d1d6423292ba7cdbe6ace39e4a67213c7f7a1b62478a95a8ea9b51136d24",
      "nonce": 307,
      "fee_rate": "93833",
      "sender_address": "SP1FV4FZ8D32S7GKYRPFWK6YHRJE5BZEYKABK72Q3",
      "sponsored": false,
      "post_condition_mode": "deny",
      "post_conditions": [
        {
          "type": "non_fungible",
          "condition_code": "sent",
          "principal": {
            "type_id": "principal_contract",
            "contract_name": "marketplace-v4",
            "address": "SPNWZ5V2TPWGQGVDR6T7B6RQ4XMGZ4PXTEE0VQ0S"
          },
          "asset": {
            "contract_name": "bitcoin-monkeys",
            "asset_name": "bitcoin-monkeys",
            "contract_address": "SP2KAF9RF86PVX3NEE27DFV1CQX0T4WGR41X3S45C"
          },
          "asset_value": {
            "hex": "0x0100000000000000000000000000000826",
            "repr": "u2086"
          }
        }
      ],
      "anchor_mode": "any",
      "is_unanchored": false,
      "block_hash": "0xeae541b09caa3d57fa3c5581fa5e8ed995dff8e1fc0b1646d8d249902c656943",
      "parent_block_hash": "0xa80328e36b7b0d127d1c0a129eff649ec2ddb6d551e98a38219490fcf2116e59",
      "block_height": 39610,
      "burn_block_time": 1638174864,
      "burn_block_time_iso": "2021-11-29T08:34:24.000Z",
      "parent_burn_block_time": 1638173957,
      "parent_burn_block_time_iso": "2021-11-29T08:19:17.000Z",
      "canonical": true,
      "tx_index": 10,
      "tx_status": "success",
      "tx_result": {
        "hex": "0x0703",
        "repr": "(ok true)"
      },
      "microblock_hash": "",
      "microblock_sequence": 2147483647,
      "microblock_canonical": true,
      "event_count": 1,
      "events": [],
      "execution_cost_read_count": 10,
      "execution_cost_read_length": 46379,
      "execution_cost_runtime": 48758000,
      "execution_cost_write_count": 2,
      "execution_cost_write_length": 216,
      "tx_type": "contract_call",
      "contract_call": {
        "contract_id": "SPNWZ5V2TPWGQGVDR6T7B6RQ4XMGZ4PXTEE0VQ0S.marketplace-v4",
        "function_name": "unlist-asset",
        "function_signature": "(define-public (unlist-asset (tradables trait_reference) (tradable-id uint)))",
        "function_args": [
          {
            "hex": "0x0616a6a7a70f41adbe8eae708ed7ec2cbf41a27218200f626974636f696e2d6d6f6e6b657973",
            "repr": "SP2KAF9RF86PVX3NEE27DFV1CQX0T4WGR41X3S45C.bitcoin-monkeys",
            "name": "tradables",
            "type": "trait_reference"
          },
          {
            "hex": "0x0100000000000000000000000000000826",
            "repr": "u2086",
            "name": "tradable-id",
            "type": "uint"
          }
        ]
      }
    },
    {
      "tx_id": "0xe07cd2ad46566a76fceda62cebdf13942fd5f7085f320ffbdb11bedf192b7dcc",
      "nonce": 279,
      "fee_rate": "112773",
      "sender_address": "SPH7P46DMTTFNSHDD33N6G8GFE1MQB2R0QW176B1",
      "sponsored": false,
      "post_condition_mode": "deny",
      "post_conditions": [
        {
          "type": "non_fungible",
          "condition_code": "sent",
          "principal": {
            "type_id": "principal_standard",
            "address": "SPH7P46DMTTFNSHDD33N6G8GFE1MQB2R0QW176B1"
          },
          "asset": {
            "contract_name": "bitcoin-monkeys",
            "asset_name": "bitcoin-monkeys",
            "contract_address": "SP2KAF9RF86PVX3NEE27DFV1CQX0T4WGR41X3S45C"
          },
          "asset_value": {
            "hex": "0x01000000000000000000000000000002a8",
            "repr": "u680"
          }
        }
      ],
      "anchor_mode": "any",
      "is_unanchored": false,
      "block_hash": "0xeae541b09caa3d57fa3c5581fa5e8ed995dff8e1fc0b1646d8d249902c656943",
      "parent_block_hash": "0xa80328e36b7b0d127d1c0a129eff649ec2ddb6d551e98a38219490fcf2116e59",
      "block_height": 39610,
      "burn_block_time": 1638174864,
      "burn_block_time_iso": "2021-11-29T08:34:24.000Z",
      "parent_burn_block_time": 1638173957,
      "parent_burn_block_time_iso": "2021-11-29T08:19:17.000Z",
      "canonical": true,
      "tx_index": 1,
      "tx_status": "success",
      "tx_result": {
        "hex": "0x0703",
        "repr": "(ok true)"
      },
      "microblock_hash": "",
      "microblock_sequence": 2147483647,
      "microblock_canonical": true,
      "event_count": 2,
      "events": [],
      "execution_cost_read_count": 14,
      "execution_cost_read_length": 55258,
      "execution_cost_runtime": 58751000,
      "execution_cost_write_count": 3,
      "execution_cost_write_length": 365,
      "tx_type": "contract_call",
      "contract_call": {
        "contract_id": "SPJW1XE278YMCEYMXB8ZFGJMH8ZVAAEDP2S2PJYG.stacks-art-market-v2",
        "function_name": "list-item",
        "function_signature": "(define-public (list-item (collection trait_reference) (collection-id uint) (item-id uint) (price uint)))",
        "function_args": [
          {
            "hex": "0x0616a6a7a70f41adbe8eae708ed7ec2cbf41a27218200f626974636f696e2d6d6f6e6b657973",
            "repr": "SP2KAF9RF86PVX3NEE27DFV1CQX0T4WGR41X3S45C.bitcoin-monkeys",
            "name": "collection",
            "type": "trait_reference"
          },
          {
            "hex": "0x0100000000000000000000000000000017",
            "repr": "u23",
            "name": "collection-id",
            "type": "uint"
          },
          {
            "hex": "0x01000000000000000000000000000002a8",
            "repr": "u680",
            "name": "item-id",
            "type": "uint"
          },
          {
            "hex": "0x0100000000000000000000000012a80040",
            "repr": "u313000000",
            "name": "price",
            "type": "uint"
          }
        ]
      }
    },
    {
      "tx_id": "0x3df57516d699b90f35e5ee649d8ae7b506d5d7cf16dcf4853dc8649e284aa5d6",
      "nonce": 79,
      "fee_rate": "750000",
      "sender_address": "SP2SPC04MGP0R90X943EKQAFK7QMJPEKMW92N8T39",
      "sponsored": false,
      "post_condition_mode": "allow",
      "post_conditions": [],
      "anchor_mode": "any",
      "is_unanchored": false,
      "block_hash": "0xeae541b09caa3d57fa3c5581fa5e8ed995dff8e1fc0b1646d8d249902c656943",
      "parent_block_hash": "0xa80328e36b7b0d127d1c0a129eff649ec2ddb6d551e98a38219490fcf2116e59",
      "block_height": 39610,
      "burn_block_time": 1638174864,
      "burn_block_time_iso": "2021-11-29T08:34:24.000Z",
      "parent_burn_block_time": 1638173957,
      "parent_burn_block_time_iso": "2021-11-29T08:19:17.000Z",
      "canonical": true,
      "tx_index": 2,
      "tx_status": "success",
      "tx_result": {
        "hex": "0x070b0000000201000000000000000000000000009c98c40100000000000000000000000001312d00",
        "repr": "(ok (list u10262724 u20000000))"
      },
      "microblock_hash": "",
      "microblock_sequence": 2147483647,
      "microblock_canonical": true,
      "event_count": 8,
      "events": [],
      "execution_cost_read_count": 30,
      "execution_cost_read_length": 58745,
      "execution_cost_runtime": 71676000,
      "execution_cost_write_count": 8,
      "execution_cost_write_length": 985,
      "tx_type": "contract_call",
      "contract_call": {
        "contract_id": "SP2C2YFP12AJZB4MABJBAJ55XECVS7E4PMMZ89YZR.arkadiko-swap-v2-1",
        "function_name": "swap-y-for-x",
        "function_signature": "(define-public (swap-y-for-x (token-x-trait trait_reference) (token-y-trait trait_reference) (dy uint) (min-dx uint)))",
        "function_args": [
          {
            "hex": "0x0616982f3ec112a5f5928a5c96a914bd733793b896a511777261707065642d7374782d746f6b656e",
            "repr": "SP2C2YFP12AJZB4MABJBAJ55XECVS7E4PMMZ89YZR.wrapped-stx-token",
            "name": "token-x-trait",
            "type": "trait_reference"
          },
          {
            "hex": "0x0616982f3ec112a5f5928a5c96a914bd733793b896a50e61726b6164696b6f2d746f6b656e",
            "repr": "SP2C2YFP12AJZB4MABJBAJ55XECVS7E4PMMZ89YZR.arkadiko-token",
            "name": "token-y-trait",
            "type": "trait_reference"
          },
          {
            "hex": "0x0100000000000000000000000001312d00",
            "repr": "u20000000",
            "name": "dy",
            "type": "uint"
          },
          {
            "hex": "0x0100000000000000000000000000965537",
            "repr": "u9852215",
            "name": "min-dx",
            "type": "uint"
          }
        ]
      }
    },
    {
      "tx_id": "0x4c0894cc8cd22fe418319d8997a6719b6299713aec37a5505536ecbc93f2958d",
      "nonce": 54,
      "fee_rate": "112507",
      "sender_address": "SP21485G9Y2YQY4DQ5S0QX3SPQ9R6AEF99QA5KR2Q",
      "sponsored": false,
      "post_condition_mode": "deny",
      "post_conditions": [
        {
          "type": "non_fungible",
          "condition_code": "sent",
          "principal": {
            "type_id": "principal_standard",
            "address": "SP21485G9Y2YQY4DQ5S0QX3SPQ9R6AEF99QA5KR2Q"
          },
          "asset": {
            "contract_name": "belles-witches",
            "asset_name": "belles-witches",
            "contract_address": "SPJW1XE278YMCEYMXB8ZFGJMH8ZVAAEDP2S2PJYG"
          },
          "asset_value": {
            "hex": "0x0100000000000000000000000000001230",
            "repr": "u4656"
          }
        }
      ],
      "anchor_mode": "any",
      "is_unanchored": false,
      "block_hash": "0xeae541b09caa3d57fa3c5581fa5e8ed995dff8e1fc0b1646d8d249902c656943",
      "parent_block_hash": "0xa80328e36b7b0d127d1c0a129eff649ec2ddb6d551e98a38219490fcf2116e59",
      "block_height": 39610,
      "burn_block_time": 1638174864,
      "burn_block_time_iso": "2021-11-29T08:34:24.000Z",
      "parent_burn_block_time": 1638173957,
      "parent_burn_block_time_iso": "2021-11-29T08:19:17.000Z",
      "canonical": true,
      "tx_index": 3,
      "tx_status": "success",
      "tx_result": {
        "hex": "0x0703",
        "repr": "(ok true)"
      },
      "microblock_hash": "",
      "microblock_sequence": 2147483647,
      "microblock_canonical": true,
      "event_count": 2,
      "events": [],
      "execution_cost_read_count": 23,
      "execution_cost_read_length": 107358,
      "execution_cost_runtime": 274354000,
      "execution_cost_write_count": 6,
      "execution_cost_write_length": 80754,
      "tx_type": "contract_call",
      "contract_call": {
        "contract_id": "SPJW1XE278YMCEYMXB8ZFGJMH8ZVAAEDP2S2PJYG.stacks-art-market-v2",
        "function_name": "list-item",
        "function_signature": "(define-public (list-item (collection trait_reference) (collection-id uint) (item-id uint) (price uint)))",
        "function_args": [
          {
            "hex": "0x061625c0f5c23a3d463bd4ead1f7c2548a3fb529cdb00e62656c6c65732d77697463686573",
            "repr": "SPJW1XE278YMCEYMXB8ZFGJMH8ZVAAEDP2S2PJYG.belles-witches",
            "name": "collection",
            "type": "trait_reference"
          },
          {
            "hex": "0x0100000000000000000000000000000005",
            "repr": "u5",
            "name": "collection-id",
            "type": "uint"
          },
          {
            "hex": "0x0100000000000000000000000000001230",
            "repr": "u4656",
            "name": "item-id",
            "type": "uint"
          },
          {
            "hex": "0x010000000000000000000000000aba9500",
            "repr": "u180000000",
            "name": "price",
            "type": "uint"
          }
        ]
      }
    },
    {
      "tx_id": "0xf3dcc857fc94ffd441a3a3e2ace30ff116384f54ba362d0b9d060fa289c7833c",
      "nonce": 2754,
      "fee_rate": "2000000",
      "sender_address": "SP335ZC3W6M308ZKTSCCBMR54GWA20RSXCKJPZC59",
      "sponsored": false,
      "post_condition_mode": "deny",
      "post_conditions": [],
      "anchor_mode": "any",
      "is_unanchored": false,
      "block_hash": "0xeae541b09caa3d57fa3c5581fa5e8ed995dff8e1fc0b1646d8d249902c656943",
      "parent_block_hash": "0xa80328e36b7b0d127d1c0a129eff649ec2ddb6d551e98a38219490fcf2116e59",
      "block_height": 39610,
      "burn_block_time": 1638174864,
      "burn_block_time_iso": "2021-11-29T08:34:24.000Z",
      "parent_burn_block_time": 1638173957,
      "parent_burn_block_time_iso": "2021-11-29T08:19:17.000Z",
      "canonical": true,
      "tx_index": 4,
      "tx_status": "success",
      "tx_result": {
        "hex": "0x07010000000000000000000000000df922bc",
        "repr": "(ok u234431164)"
      },
      "microblock_hash": "",
      "microblock_sequence": 2147483647,
      "microblock_canonical": true,
      "event_count": 2,
      "events": [],
      "execution_cost_read_count": 78,
      "execution_cost_read_length": 117597,
      "execution_cost_runtime": 133657000,
      "execution_cost_write_count": 5,
      "execution_cost_write_length": 299,
      "tx_type": "contract_call",
      "contract_call": {
        "contract_id": "SP2C2YFP12AJZB4MABJBAJ55XECVS7E4PMMZ89YZR.arkadiko-stake-registry-v1-1",
        "function_name": "claim-pending-rewards",
        "function_signature": "(define-public (claim-pending-rewards (registry-trait trait_reference) (pool-trait trait_reference)))",
        "function_args": [
          {
            "hex": "0x0616982f3ec112a5f5928a5c96a914bd733793b896a51c61726b6164696b6f2d7374616b652d72656769737472792d76312d31",
            "repr": "SP2C2YFP12AJZB4MABJBAJ55XECVS7E4PMMZ89YZR.arkadiko-stake-registry-v1-1",
            "name": "registry-trait",
            "type": "trait_reference"
          },
          {
            "hex": "0x0616982f3ec112a5f5928a5c96a914bd733793b896a52261726b6164696b6f2d7374616b652d706f6f6c2d777374782d64696b6f2d76312d31",
            "repr": "SP2C2YFP12AJZB4MABJBAJ55XECVS7E4PMMZ89YZR.arkadiko-stake-pool-wstx-diko-v1-1",
            "name": "pool-trait",
            "type": "trait_reference"
          }
        ]
      }
    },
    {
      "tx_id": "0x60d02b3d6b214f062dd0cea1881a571888dd716c97ac3653a5fb700fea72a408",
      "nonce": 3311,
      "fee_rate": "1355271",
      "sender_address": "SP2NQ9HTTQFKW5GXDDDWZ99MNH2JTRSJN8MG7ATP0",
      "sponsored": false,
      "post_condition_mode": "deny",
      "post_conditions": [
        {
          "type": "stx",
          "condition_code": "sent_equal_to",
          "amount": "17737500000",
          "principal": {
            "type_id": "principal_standard",
            "address": "SP2NQ9HTTQFKW5GXDDDWZ99MNH2JTRSJN8MG7ATP0"
          }
        }
      ],
      "anchor_mode": "any",
      "is_unanchored": false,
      "block_hash": "0xeae541b09caa3d57fa3c5581fa5e8ed995dff8e1fc0b1646d8d249902c656943",
      "parent_block_hash": "0xa80328e36b7b0d127d1c0a129eff649ec2ddb6d551e98a38219490fcf2116e59",
      "block_height": 39610,
      "burn_block_time": 1638174864,
      "burn_block_time_iso": "2021-11-29T08:34:24.000Z",
      "parent_burn_block_time": 1638173957,
      "parent_burn_block_time_iso": "2021-11-29T08:19:17.000Z",
      "canonical": true,
      "tx_index": 5,
      "tx_status": "success",
      "tx_result": {
        "hex": "0x0703",
        "repr": "(ok true)"
      },
      "microblock_hash": "",
      "microblock_sequence": 2147483647,
      "microblock_canonical": true,
      "event_count": 2,
      "events": [],
      "execution_cost_read_count": 4,
      "execution_cost_read_length": 735,
      "execution_cost_runtime": 50580000,
      "execution_cost_write_count": 1,
      "execution_cost_write_length": 1,
      "tx_type": "contract_call",
      "contract_call": {
        "contract_id": "SP3FBR2AGK5H9QBDH3EEN6DF8EK8JY7RX8QJ5SVTE.send-many-memo",
        "function_name": "send-many",
        "function_signature": "(define-public (send-many (recipients (list 200 (tuple (memo (buff 34)) (to principal) (ustx uint))))))",
        "function_args": [
          {
            "hex": "0x0b000000010c00000003046d656d6f020000000631313631393802746f0516f0f57e9989bca0cf5269db54a4ea809b0291c3fa047573747801000000000000000000000004213cc560",
            "repr": "(list (tuple (memo 0x313136313938) (to SP3RFAZMSH6YA1KTJD7DN997AG2DG54E3Z9ZJWYN8) (ustx u17737500000)))",
            "name": "recipients",
            "type": "(list 200 (tuple (memo (buff 34)) (to principal) (ustx uint)))"
          }
        ]
      }
    },
    {
      "tx_id": "0x6e9bfbb9f47092ea23efc95b704762cd69fa75c849643b5225420afef7a79e75",
      "nonce": 3366,
      "fee_rate": "1325265",
      "sender_address": "SP2J6HSSDYSTM71S0K0KK4YWRKX59JN1AD52M4B59",
      "sponsored": false,
      "post_condition_mode": "deny",
      "post_conditions": [
        {
          "type": "stx",
          "condition_code": "sent_equal_to",
          "amount": "103743300",
          "principal": {
            "type_id": "principal_standard",
            "address": "SP2J6HSSDYSTM71S0K0KK4YWRKX59JN1AD52M4B59"
          }
        }
      ],
      "anchor_mode": "any",
      "is_unanchored": false,
      "block_hash": "0xeae541b09caa3d57fa3c5581fa5e8ed995dff8e1fc0b1646d8d249902c656943",
      "parent_block_hash": "0xa80328e36b7b0d127d1c0a129eff649ec2ddb6d551e98a38219490fcf2116e59",
      "block_height": 39610,
      "burn_block_time": 1638174864,
      "burn_block_time_iso": "2021-11-29T08:34:24.000Z",
      "parent_burn_block_time": 1638173957,
      "parent_burn_block_time_iso": "2021-11-29T08:19:17.000Z",
      "canonical": true,
      "tx_index": 6,
      "tx_status": "success",
      "tx_result": {
        "hex": "0x0703",
        "repr": "(ok true)"
      },
      "microblock_hash": "",
      "microblock_sequence": 2147483647,
      "microblock_canonical": true,
      "event_count": 2,
      "events": [],
      "execution_cost_read_count": 4,
      "execution_cost_read_length": 735,
      "execution_cost_runtime": 50544000,
      "execution_cost_write_count": 1,
      "execution_cost_write_length": 1,
      "tx_type": "contract_call",
      "contract_call": {
        "contract_id": "SP3FBR2AGK5H9QBDH3EEN6DF8EK8JY7RX8QJ5SVTE.send-many-memo",
        "function_name": "send-many",
        "function_signature": "(define-public (send-many (recipients (list 200 (tuple (memo (buff 34)) (to principal) (ustx uint))))))",
        "function_args": [
          {
            "hex": "0x0b000000010c00000003046d656d6f020000000002746f0516f3ecf93639e8b954448830edc300631e32f97d6a047573747801000000000000000000000000062eff44",
            "repr": "(list (tuple (memo 0x) (to SP3SYSY9P77MBJN24H0REVGR0CCF35YBXDBFWTSDH) (ustx u103743300)))",
            "name": "recipients",
            "type": "(list 200 (tuple (memo (buff 34)) (to principal) (ustx uint)))"
          }
        ]
      }
    },
    {
      "tx_id": "0xe19bced19632e48bc234b56cba0b3363afe0654f11d780541447cd6580b719af",
      "nonce": 13678,
      "fee_rate": "1325265",
      "sender_address": "SP3WV3VC6GM1WF215SDHP0MESQ3BNXHB1N6TPB70S",
      "sponsored": false,
      "post_condition_mode": "deny",
      "post_conditions": [
        {
          "type": "stx",
          "condition_code": "sent_equal_to",
          "amount": "3500000",
          "principal": {
            "type_id": "principal_standard",
            "address": "SP3WV3VC6GM1WF215SDHP0MESQ3BNXHB1N6TPB70S"
          }
        }
      ],
      "anchor_mode": "any",
      "is_unanchored": false,
      "block_hash": "0xeae541b09caa3d57fa3c5581fa5e8ed995dff8e1fc0b1646d8d249902c656943",
      "parent_block_hash": "0xa80328e36b7b0d127d1c0a129eff649ec2ddb6d551e98a38219490fcf2116e59",
      "block_height": 39610,
      "burn_block_time": 1638174864,
      "burn_block_time_iso": "2021-11-29T08:34:24.000Z",
      "parent_burn_block_time": 1638173957,
      "parent_burn_block_time_iso": "2021-11-29T08:19:17.000Z",
      "canonical": true,
      "tx_index": 7,
      "tx_status": "success",
      "tx_result": {
        "hex": "0x0703",
        "repr": "(ok true)"
      },
      "microblock_hash": "",
      "microblock_sequence": 2147483647,
      "microblock_canonical": true,
      "event_count": 2,
      "events": [],
      "execution_cost_read_count": 4,
      "execution_cost_read_length": 735,
      "execution_cost_runtime": 50544000,
      "execution_cost_write_count": 1,
      "execution_cost_write_length": 1,
      "tx_type": "contract_call",
      "contract_call": {
        "contract_id": "SP3FBR2AGK5H9QBDH3EEN6DF8EK8JY7RX8QJ5SVTE.send-many-memo",
        "function_name": "send-many",
        "function_signature": "(define-public (send-many (recipients (list 200 (tuple (memo (buff 34)) (to principal) (ustx uint))))))",
        "function_args": [
          {
            "hex": "0x0b000000010c00000003046d656d6f020000000002746f051634420d008a81ecd3d834fad61faa7d6a2e21d365047573747801000000000000000000000000003567e0",
            "repr": "(list (tuple (memo 0x) (to SPT44380HA0YSMYR6KXDC7XAFNN2W8EKCP5KEPW0) (ustx u3500000)))",
            "name": "recipients",
            "type": "(list 200 (tuple (memo (buff 34)) (to principal) (ustx uint)))"
          }
        ]
      }
    },
    {
      "tx_id": "0xca991b5591edbe6635136f865e37a6bbb2d7b46d8e455328a72cf681706c6a2e",
      "nonce": 50,
      "fee_rate": "2000000",
      "sender_address": "SP3MR0WGR46ZJEFH0YKKY55Q6X9EA1RPET57XF7VV",
      "sponsored": false,
      "post_condition_mode": "deny",
      "post_conditions": [
        {
          "type": "non_fungible",
          "condition_code": "sent",
          "principal": {
            "type_id": "principal_standard",
            "address": "SP3MR0WGR46ZJEFH0YKKY55Q6X9EA1RPET57XF7VV"
          },
          "asset": {
            "contract_name": "bitcoin-monkeys",
            "asset_name": "bitcoin-monkeys",
            "contract_address": "SP2KAF9RF86PVX3NEE27DFV1CQX0T4WGR41X3S45C"
          },
          "asset_value": {
            "hex": "0x01000000000000000000000000000001f3",
            "repr": "u499"
          }
        }
      ],
      "anchor_mode": "any",
      "is_unanchored": false,
      "block_hash": "0xeae541b09caa3d57fa3c5581fa5e8ed995dff8e1fc0b1646d8d249902c656943",
      "parent_block_hash": "0xa80328e36b7b0d127d1c0a129eff649ec2ddb6d551e98a38219490fcf2116e59",
      "block_height": 39610,
      "burn_block_time": 1638174864,
      "burn_block_time_iso": "2021-11-29T08:34:24.000Z",
      "parent_burn_block_time": 1638173957,
      "parent_burn_block_time_iso": "2021-11-29T08:19:17.000Z",
      "canonical": true,
      "tx_index": 8,
      "tx_status": "success",
      "tx_result": {
        "hex": "0x0703",
        "repr": "(ok true)"
      },
      "microblock_hash": "",
      "microblock_sequence": 2147483647,
      "microblock_canonical": true,
      "event_count": 1,
      "events": [],
      "execution_cost_read_count": 17,
      "execution_cost_read_length": 66480,
      "execution_cost_runtime": 70564000,
      "execution_cost_write_count": 2,
      "execution_cost_write_length": 685,
      "tx_type": "contract_call",
      "contract_call": {
        "contract_id": "SPNWZ5V2TPWGQGVDR6T7B6RQ4XMGZ4PXTEE0VQ0S.marketplace-v4",
        "function_name": "list-asset",
        "function_signature": "(define-public (list-asset (tradables trait_reference) (tradable-id uint) (price uint) (commission uint)))",
        "function_args": [
          {
            "hex": "0x0616a6a7a70f41adbe8eae708ed7ec2cbf41a27218200f626974636f696e2d6d6f6e6b657973",
            "repr": "SP2KAF9RF86PVX3NEE27DFV1CQX0T4WGR41X3S45C.bitcoin-monkeys",
            "name": "tradables",
            "type": "trait_reference"
          },
          {
            "hex": "0x01000000000000000000000000000001f3",
            "repr": "u499",
            "name": "tradable-id",
            "type": "uint"
          },
          {
            "hex": "0x010000000000000000000000037e11d600",
            "repr": "u15000000000",
            "name": "price",
            "type": "uint"
          },
          {
            "hex": "0x0100000000000000000000000000000064",
            "repr": "u100",
            "name": "commission",
            "type": "uint"
          }
        ]
      }
    },
    {
      "tx_id": "0x684e808a47969bd8a4bcb5de41544639ba670f429d16f681bc697303926b40af",
      "nonce": 42,
      "fee_rate": "750000",
      "sender_address": "SP2DRM5DKDJX6ECFJH9XDT66DZV8FK2H1A27JZHCA",
      "sponsored": false,
      "post_condition_mode": "deny",
      "post_conditions": [
        {
          "type": "non_fungible",
          "condition_code": "sent",
          "principal": {
            "type_id": "principal_standard",
            "address": "SP2DRM5DKDJX6ECFJH9XDT66DZV8FK2H1A27JZHCA"
          },
          "asset": {
            "contract_name": "bitcoin-monkeys",
            "asset_name": "bitcoin-monkeys",
            "contract_address": "SP2KAF9RF86PVX3NEE27DFV1CQX0T4WGR41X3S45C"
          },
          "asset_value": {
            "hex": "0x010000000000000000000000000000019b",
            "repr": "u411"
          }
        }
      ],
      "anchor_mode": "any",
      "is_unanchored": false,
      "block_hash": "0xeae541b09caa3d57fa3c5581fa5e8ed995dff8e1fc0b1646d8d249902c656943",
      "parent_block_hash": "0xa80328e36b7b0d127d1c0a129eff649ec2ddb6d551e98a38219490fcf2116e59",
      "block_height": 39610,
      "burn_block_time": 1638174864,
      "burn_block_time_iso": "2021-11-29T08:34:24.000Z",
      "parent_burn_block_time": 1638173957,
      "parent_burn_block_time_iso": "2021-11-29T08:19:17.000Z",
      "canonical": true,
      "tx_index": 9,
      "tx_status": "success",
      "tx_result": {
        "hex": "0x0703",
        "repr": "(ok true)"
      },
      "microblock_hash": "",
      "microblock_sequence": 2147483647,
      "microblock_canonical": true,
      "event_count": 1,
      "events": [],
      "execution_cost_read_count": 17,
      "execution_cost_read_length": 66480,
      "execution_cost_runtime": 70564000,
      "execution_cost_write_count": 2,
      "execution_cost_write_length": 685,
      "tx_type": "contract_call",
      "contract_call": {
        "contract_id": "SPNWZ5V2TPWGQGVDR6T7B6RQ4XMGZ4PXTEE0VQ0S.marketplace-v4",
        "function_name": "list-asset",
        "function_signature": "(define-public (list-asset (tradables trait_reference) (tradable-id uint) (price uint) (commission uint)))",
        "function_args": [
          {
            "hex": "0x0616a6a7a70f41adbe8eae708ed7ec2cbf41a27218200f626974636f696e2d6d6f6e6b657973",
            "repr": "SP2KAF9RF86PVX3NEE27DFV1CQX0T4WGR41X3S45C.bitcoin-monkeys",
            "name": "tradables",
            "type": "trait_reference"
          },
          {
            "hex": "0x010000000000000000000000000000019b",
            "repr": "u411",
            "name": "tradable-id",
            "type": "uint"
          },
          {
            "hex": "0x0100000000000000000000000083215600",
            "repr": "u2200000000",
            "name": "price",
            "type": "uint"
          },
          {
            "hex": "0x0100000000000000000000000000000064",
            "repr": "u100",
            "name": "commission",
            "type": "uint"
          }
        ]
      }
    },
    {
      "tx_id": "0x62c8263c0514b071fd1fb9c70c7ca74fac81cff4fb62db546c5e22bbf5493194",
      "nonce": 142,
      "fee_rate": "1000000",
      "sender_address": "SPAFPBD7M89973WDEN68FKYW761RQVYNHSEFQZB9",
      "sponsored": false,
      "post_condition_mode": "deny",
      "post_conditions": [
        {
          "type": "stx",
          "condition_code": "sent_equal_to",
          "amount": "10000000",
          "principal": {
            "type_id": "principal_standard",
            "address": "SPAFPBD7M89973WDEN68FKYW761RQVYNHSEFQZB9"
          }
        },
        {
          "type": "fungible",
          "condition_code": "sent_greater_than_or_equal_to",
          "amount": "2383192570",
          "principal": {
            "type_id": "principal_contract",
            "contract_name": "liquidity-token-v5k9jvzokmy",
            "address": "SP1Z92MPDQEWZXW36VX71Q25HKF5K2EPCJ304F275"
          },
          "asset": {
            "contract_name": "tokensoft-token-v4ka1lgcc8y",
            "asset_name": "tokensoft-token",
            "contract_address": "SP1Z92MPDQEWZXW36VX71Q25HKF5K2EPCJ304F275"
          }
        }
      ],
      "anchor_mode": "any",
      "is_unanchored": false,
      "block_hash": "0xeae541b09caa3d57fa3c5581fa5e8ed995dff8e1fc0b1646d8d249902c656943",
      "parent_block_hash": "0xa80328e36b7b0d127d1c0a129eff649ec2ddb6d551e98a38219490fcf2116e59",
      "block_height": 39610,
      "burn_block_time": 1638174864,
      "burn_block_time_iso": "2021-11-29T08:34:24.000Z",
      "parent_burn_block_time": 1638173957,
      "parent_burn_block_time_iso": "2021-11-29T08:19:17.000Z",
      "canonical": true,
      "tx_index": 11,
      "tx_status": "success",
      "tx_result": {
        "hex": "0x070b000000020100000000000000000000000000989680010000000000000000000000009dd525bf",
        "repr": "(ok (list u10000000 u2647991743))"
      },
      "microblock_hash": "",
      "microblock_sequence": 2147483647,
      "microblock_canonical": true,
      "event_count": 3,
      "events": [],
      "execution_cost_read_count": 80,
      "execution_cost_read_length": 101962,
      "execution_cost_runtime": 122143000,
      "execution_cost_write_count": 9,
      "execution_cost_write_length": 236,
      "tx_type": "contract_call",
      "contract_call": {
        "contract_id": "SP1Z92MPDQEWZXW36VX71Q25HKF5K2EPCJ304F275.stackswap-swap-v5k",
        "function_name": "swap-x-for-y",
        "function_signature": "(define-public (swap-x-for-y (token-x-trait trait_reference) (token-y-trait trait_reference) (token-liquidity-trait trait_reference) (dx uint) (min-dy uint)))",
        "function_args": [
          {
            "hex": "0x06167e9152cdbbb9fef066df4e1b88b19bcb313acc900e777374782d746f6b656e2d763461",
            "repr": "SP1Z92MPDQEWZXW36VX71Q25HKF5K2EPCJ304F275.wstx-token-v4a",
            "name": "token-x-trait",
            "type": "trait_reference"
          },
          {
            "hex": "0x06167e9152cdbbb9fef066df4e1b88b19bcb313acc901b746f6b656e736f66742d746f6b656e2d76346b61316c6763633879",
            "repr": "SP1Z92MPDQEWZXW36VX71Q25HKF5K2EPCJ304F275.tokensoft-token-v4ka1lgcc8y",
            "name": "token-y-trait",
            "type": "trait_reference"
          },
          {
            "hex": "0x06167e9152cdbbb9fef066df4e1b88b19bcb313acc901b6c69717569646974792d746f6b656e2d76356b396a767a6f6b6d79",
            "repr": "SP1Z92MPDQEWZXW36VX71Q25HKF5K2EPCJ304F275.liquidity-token-v5k9jvzokmy",
            "name": "token-liquidity-trait",
            "type": "trait_reference"
          },
          {
            "hex": "0x0100000000000000000000000000989680",
            "repr": "u10000000",
            "name": "dx",
            "type": "uint"
          },
          {
            "hex": "0x010000000000000000000000008e0ca1fa",
            "repr": "u2383192570",
            "name": "min-dy",
            "type": "uint"
          }
        ]
      }
    },
    {
      "tx_id": "0x7546c7cbeab560ae8e42947a9df5f6f5ac55fb3233a3725ee9d21964790698a4",
      "nonce": 373,
      "fee_rate": "100000",
      "sender_address": "SPRE2B9P0Z1P5EV2Y37Y70GY35R56PJS54GBJCNY",
      "sponsored": false,
      "post_condition_mode": "deny",
      "post_conditions": [
        {
          "type": "fungible",
          "condition_code": "sent_less_than_or_equal_to",
          "amount": "34300000000",
          "principal": {
            "type_id": "principal_standard",
            "address": "SPRE2B9P0Z1P5EV2Y37Y70GY35R56PJS54GBJCNY"
          },
          "asset": {
            "contract_name": "board-points",
            "asset_name": "points",
            "contract_address": "SPASZ0VJQTS22YR4HCCAGR05GGRF9V8TCM219YQ8"
          }
        }
      ],
      "anchor_mode": "any",
      "is_unanchored": false,
      "block_hash": "0xeae541b09caa3d57fa3c5581fa5e8ed995dff8e1fc0b1646d8d249902c656943",
      "parent_block_hash": "0xa80328e36b7b0d127d1c0a129eff649ec2ddb6d551e98a38219490fcf2116e59",
      "block_height": 39610,
      "burn_block_time": 1638174864,
      "burn_block_time_iso": "2021-11-29T08:34:24.000Z",
      "parent_burn_block_time": 1638173957,
      "parent_burn_block_time_iso": "2021-11-29T08:19:17.000Z",
      "canonical": true,
      "tx_index": 12,
      "tx_status": "success",
      "tx_result": {
        "hex": "0x0703",
        "repr": "(ok true)"
      },
      "microblock_hash": "",
      "microblock_sequence": 2147483647,
      "microblock_canonical": true,
      "event_count": 1,
      "events": [],
      "execution_cost_read_count": 32,
      "execution_cost_read_length": 51853,
      "execution_cost_runtime": 54201000,
      "execution_cost_write_count": 3,
      "execution_cost_write_length": 70,
      "tx_type": "contract_call",
      "contract_call": {
        "contract_id": "SPASZ0VJQTS22YR4HCCAGR05GGRF9V8TCM219YQ8.board-tiles-manager",
        "function_name": "upgrade-token",
        "function_signature": "(define-public (upgrade-token (token-id uint)))",
        "function_args": [
          {
            "hex": "0x01000000000000000000000000000001e0",
            "repr": "u480",
            "name": "token-id",
            "type": "uint"
          }
        ]
      }
    },
    {
      "tx_id": "0xb2c95a85e9d59322193706a49a34fe7c53ee949699dfa10ec5028e48365c1992",
      "nonce": 63,
      "fee_rate": "750000",
      "sender_address": "SP3W00ZZE6PN11NHFH5KVEY6Q4P7YCYPTAWM7M9DX",
      "sponsored": false,
      "post_condition_mode": "deny",
      "post_conditions": [
        {
          "type": "non_fungible",
          "condition_code": "sent",
          "principal": {
            "type_id": "principal_contract",
            "contract_name": "stacks-art-market-v2",
            "address": "SPJW1XE278YMCEYMXB8ZFGJMH8ZVAAEDP2S2PJYG"
          },
          "asset": {
            "contract_name": "stx-youth",
            "asset_name": "stx-youth",
            "contract_address": "SPJW1XE278YMCEYMXB8ZFGJMH8ZVAAEDP2S2PJYG"
          },
          "asset_value": {
            "hex": "0x0100000000000000000000000000000218",
            "repr": "u536"
          }
        }
      ],
      "anchor_mode": "any",
      "is_unanchored": false,
      "block_hash": "0xeae541b09caa3d57fa3c5581fa5e8ed995dff8e1fc0b1646d8d249902c656943",
      "parent_block_hash": "0xa80328e36b7b0d127d1c0a129eff649ec2ddb6d551e98a38219490fcf2116e59",
      "block_height": 39610,
      "burn_block_time": 1638174864,
      "burn_block_time_iso": "2021-11-29T08:34:24.000Z",
      "parent_burn_block_time": 1638173957,
      "parent_burn_block_time_iso": "2021-11-29T08:19:17.000Z",
      "canonical": true,
      "tx_index": 13,
      "tx_status": "success",
      "tx_result": {
        "hex": "0x0703",
        "repr": "(ok true)"
      },
      "microblock_hash": "",
      "microblock_sequence": 2147483647,
      "microblock_canonical": true,
      "event_count": 2,
      "events": [],
      "execution_cost_read_count": 13,
      "execution_cost_read_length": 21081,
      "execution_cost_runtime": 25776000,
      "execution_cost_write_count": 2,
      "execution_cost_write_length": 84,
      "tx_type": "contract_call",
      "contract_call": {
        "contract_id": "SPJW1XE278YMCEYMXB8ZFGJMH8ZVAAEDP2S2PJYG.stacks-art-market-v2",
        "function_name": "unlist-item",
        "function_signature": "(define-public (unlist-item (collection trait_reference) (collection-id uint) (item-id uint)))",
        "function_args": [
          {
            "hex": "0x061625c0f5c23a3d463bd4ead1f7c2548a3fb529cdb0097374782d796f757468",
            "repr": "SPJW1XE278YMCEYMXB8ZFGJMH8ZVAAEDP2S2PJYG.stx-youth",
            "name": "collection",
            "type": "trait_reference"
          },
          {
            "hex": "0x010000000000000000000000000000000e",
            "repr": "u14",
            "name": "collection-id",
            "type": "uint"
          },
          {
            "hex": "0x0100000000000000000000000000000218",
            "repr": "u536",
            "name": "item-id",
            "type": "uint"
          }
        ]
      }
    },
    {
      "tx_id": "0xd31e0c404bad0f93c1d6803f251657119ac6f8d0b93ce37bc016ffeddd7f97af",
      "nonce": 2,
      "fee_rate": "608664",
      "sender_address": "SP3X6QG6ZHB7HNP3RMQFXYRMF2TWBHN0CWG3GYZ5N",
      "sponsored": false,
      "post_condition_mode": "deny",
      "post_conditions": [
        {
          "type": "stx",
          "condition_code": "sent_less_than_or_equal_to",
          "amount": "20000000",
          "principal": {
            "type_id": "principal_standard",
            "address": "SP3X6QG6ZHB7HNP3RMQFXYRMF2TWBHN0CWG3GYZ5N"
          }
        },
        {
          "type": "non_fungible",
          "condition_code": "not_sent",
          "principal": {
            "type_id": "principal_contract",
            "contract_name": "belles-witches",
            "address": "SPJW1XE278YMCEYMXB8ZFGJMH8ZVAAEDP2S2PJYG"
          },
          "asset": {
            "contract_name": "belles-witches",
            "asset_name": "belles-witches",
            "contract_address": "SPJW1XE278YMCEYMXB8ZFGJMH8ZVAAEDP2S2PJYG"
          },
          "asset_value": {
            "hex": "0x0100000000000000000000000000000000",
            "repr": "u0"
          }
        },
        {
          "type": "stx",
          "condition_code": "sent_less_than_or_equal_to",
          "amount": "15000000",
          "principal": {
            "type_id": "principal_contract",
            "contract_name": "belles-witches",
            "address": "SPJW1XE278YMCEYMXB8ZFGJMH8ZVAAEDP2S2PJYG"
          }
        }
      ],
      "anchor_mode": "any",
      "is_unanchored": false,
      "block_hash": "0xeae541b09caa3d57fa3c5581fa5e8ed995dff8e1fc0b1646d8d249902c656943",
      "parent_block_hash": "0xa80328e36b7b0d127d1c0a129eff649ec2ddb6d551e98a38219490fcf2116e59",
      "block_height": 39610,
      "burn_block_time": 1638174864,
      "burn_block_time_iso": "2021-11-29T08:34:24.000Z",
      "parent_burn_block_time": 1638173957,
      "parent_burn_block_time_iso": "2021-11-29T08:19:17.000Z",
      "canonical": true,
      "tx_index": 14,
      "tx_status": "success",
      "tx_result": {
        "hex": "0x0703",
        "repr": "(ok true)"
      },
      "microblock_hash": "",
      "microblock_sequence": 2147483647,
      "microblock_canonical": true,
      "event_count": 3,
      "events": [],
      "execution_cost_read_count": 20,
      "execution_cost_read_length": 46241,
      "execution_cost_runtime": 127400000,
      "execution_cost_write_count": 8,
      "execution_cost_write_length": 40284,
      "tx_type": "contract_call",
      "contract_call": {
        "contract_id": "SPJW1XE278YMCEYMXB8ZFGJMH8ZVAAEDP2S2PJYG.belles-witches",
        "function_name": "mint",
        "function_signature": "(define-public (mint ))"
      }
    },
    {
      "tx_id": "0xab13bb11c57ee5b283423dc9129d9669d27f5d10ca6fe36870ca9b6354fd0955",
      "nonce": 29,
      "fee_rate": "750000",
      "sender_address": "SP294R64T069ND9YZERN4EF7XHKCG00W64KM4QDNR",
      "sponsored": false,
      "post_condition_mode": "deny",
      "post_conditions": [
        {
          "type": "non_fungible",
          "condition_code": "sent",
          "principal": {
            "type_id": "principal_standard",
            "address": "SP294R64T069ND9YZERN4EF7XHKCG00W64KM4QDNR"
          },
          "asset": {
            "contract_name": "stacculents",
            "asset_name": "stacculents",
            "contract_address": "SPNWZ5V2TPWGQGVDR6T7B6RQ4XMGZ4PXTEE0VQ0S"
          },
          "asset_value": {
            "hex": "0x01000000000000000000000000000002cc",
            "repr": "u716"
          }
        }
      ],
      "anchor_mode": "any",
      "is_unanchored": false,
      "block_hash": "0xeae541b09caa3d57fa3c5581fa5e8ed995dff8e1fc0b1646d8d249902c656943",
      "parent_block_hash": "0xa80328e36b7b0d127d1c0a129eff649ec2ddb6d551e98a38219490fcf2116e59",
      "block_height": 39610,
      "burn_block_time": 1638174864,
      "burn_block_time_iso": "2021-11-29T08:34:24.000Z",
      "parent_burn_block_time": 1638173957,
      "parent_burn_block_time_iso": "2021-11-29T08:19:17.000Z",
      "canonical": true,
      "tx_index": 15,
      "tx_status": "success",
      "tx_result": {
        "hex": "0x0703",
        "repr": "(ok true)"
      },
      "microblock_hash": "",
      "microblock_sequence": 2147483647,
      "microblock_canonical": true,
      "event_count": 1,
      "events": [],
      "execution_cost_read_count": 17,
      "execution_cost_read_length": 35112,
      "execution_cost_runtime": 39196000,
      "execution_cost_write_count": 2,
      "execution_cost_write_length": 685,
      "tx_type": "contract_call",
      "contract_call": {
        "contract_id": "SPNWZ5V2TPWGQGVDR6T7B6RQ4XMGZ4PXTEE0VQ0S.marketplace-v4",
        "function_name": "list-asset",
        "function_signature": "(define-public (list-asset (tradables trait_reference) (tradable-id uint) (price uint) (commission uint)))",
        "function_args": [
          {
            "hex": "0x06162bcf9762d5b90bc36dc1b4759b1727690f92ddd30b7374616363756c656e7473",
            "repr": "SPNWZ5V2TPWGQGVDR6T7B6RQ4XMGZ4PXTEE0VQ0S.stacculents",
            "name": "tradables",
            "type": "trait_reference"
          },
          {
            "hex": "0x01000000000000000000000000000002cc",
            "repr": "u716",
            "name": "tradable-id",
            "type": "uint"
          },
          {
            "hex": "0x0100000000000000000000000000e4e1c0",
            "repr": "u15000000",
            "name": "price",
            "type": "uint"
          },
          {
            "hex": "0x0100000000000000000000000000000064",
            "repr": "u100",
            "name": "commission",
            "type": "uint"
          }
        ]
      }
    },
    {
      "tx_id": "0xeb6ed78169b5229261e93bb5ae20930bcae058fd0f3d15133dd95e527dcc59b7",
      "nonce": 145,
      "fee_rate": "750000",
      "sender_address": "SP3TZF64TY080GVMZRT4Z87E383Q8EAKZ5W67FCNY",
      "sponsored": false,
      "post_condition_mode": "allow",
      "post_conditions": [],
      "anchor_mode": "any",
      "is_unanchored": false,
      "block_hash": "0xeae541b09caa3d57fa3c5581fa5e8ed995dff8e1fc0b1646d8d249902c656943",
      "parent_block_hash": "0xa80328e36b7b0d127d1c0a129eff649ec2ddb6d551e98a38219490fcf2116e59",
      "block_height": 39610,
      "burn_block_time": 1638174864,
      "burn_block_time_iso": "2021-11-29T08:34:24.000Z",
      "parent_burn_block_time": 1638173957,
      "parent_burn_block_time_iso": "2021-11-29T08:19:17.000Z",
      "canonical": true,
      "tx_index": 16,
      "tx_status": "success",
      "tx_result": {
        "hex": "0x07010000000000000000000000000fd06af0",
        "repr": "(ok u265317104)"
      },
      "microblock_hash": "",
      "microblock_sequence": 2147483647,
      "microblock_canonical": true,
      "event_count": 7,
      "events": [],
      "execution_cost_read_count": 98,
      "execution_cost_read_length": 148657,
      "execution_cost_runtime": 168864000,
      "execution_cost_write_count": 7,
      "execution_cost_write_length": 20,
      "tx_type": "contract_call",
      "contract_call": {
        "contract_id": "SP2C2YFP12AJZB4MABJBAJ55XECVS7E4PMMZ89YZR.arkadiko-stake-registry-v1-1",
        "function_name": "unstake",
        "function_signature": "(define-public (unstake (registry-trait trait_reference) (pool-trait trait_reference) (token-trait trait_reference) (amount uint)))",
        "function_args": [
          {
            "hex": "0x0616982f3ec112a5f5928a5c96a914bd733793b896a51c61726b6164696b6f2d7374616b652d72656769737472792d76312d31",
            "repr": "SP2C2YFP12AJZB4MABJBAJ55XECVS7E4PMMZ89YZR.arkadiko-stake-registry-v1-1",
            "name": "registry-trait",
            "type": "trait_reference"
          },
          {
            "hex": "0x0616982f3ec112a5f5928a5c96a914bd733793b896a51d61726b6164696b6f2d7374616b652d706f6f6c2d64696b6f2d76312d31",
            "repr": "SP2C2YFP12AJZB4MABJBAJ55XECVS7E4PMMZ89YZR.arkadiko-stake-pool-diko-v1-1",
            "name": "pool-trait",
            "type": "trait_reference"
          },
          {
            "hex": "0x0616982f3ec112a5f5928a5c96a914bd733793b896a50e61726b6164696b6f2d746f6b656e",
            "repr": "SP2C2YFP12AJZB4MABJBAJ55XECVS7E4PMMZ89YZR.arkadiko-token",
            "name": "token-trait",
            "type": "trait_reference"
          },
          {
            "hex": "0x010000000000000000000000000bcd3d80",
            "repr": "u198000000",
            "name": "amount",
            "type": "uint"
          }
        ]
      }
    },
    {
      "tx_id": "0xb17bb78f9ca1b9e5afbcb80d6339d76e1ef30b1d2913ce66c2ed8323ccaafc58",
      "nonce": 267,
      "fee_rate": "165373",
      "sender_address": "SPXGFH9JTKPF2TQZJ2AH7NSMMMXJ72VMGH8PR654",
      "sponsored": false,
      "post_condition_mode": "deny",
      "post_conditions": [
        {
          "type": "non_fungible",
          "condition_code": "sent",
          "principal": {
            "type_id": "principal_standard",
            "address": "SPXGFH9JTKPF2TQZJ2AH7NSMMMXJ72VMGH8PR654"
          },
          "asset": {
            "contract_name": "boom-nfts",
            "asset_name": "boom",
            "contract_address": "SP497E7RX3233ATBS2AB9G4WTHB63X5PBSP5VGAQ"
          },
          "asset_value": {
            "hex": "0x0100000000000000000000000000002254",
            "repr": "u8788"
          }
        }
      ],
      "anchor_mode": "any",
      "is_unanchored": false,
      "block_hash": "0xeae541b09caa3d57fa3c5581fa5e8ed995dff8e1fc0b1646d8d249902c656943",
      "parent_block_hash": "0xa80328e36b7b0d127d1c0a129eff649ec2ddb6d551e98a38219490fcf2116e59",
      "block_height": 39610,
      "burn_block_time": 1638174864,
      "burn_block_time_iso": "2021-11-29T08:34:24.000Z",
      "parent_burn_block_time": 1638173957,
      "parent_burn_block_time_iso": "2021-11-29T08:19:17.000Z",
      "canonical": true,
      "tx_index": 17,
      "tx_status": "success",
      "tx_result": {
        "hex": "0x0703",
        "repr": "(ok true)"
      },
      "microblock_hash": "",
      "microblock_sequence": 2147483647,
      "microblock_canonical": true,
      "event_count": 1,
      "events": [],
      "execution_cost_read_count": 15,
      "execution_cost_read_length": 21007,
      "execution_cost_runtime": 23865000,
      "execution_cost_write_count": 2,
      "execution_cost_write_length": 451,
      "tx_type": "contract_call",
      "contract_call": {
        "contract_id": "SPNWZ5V2TPWGQGVDR6T7B6RQ4XMGZ4PXTEE0VQ0S.marketplace-v2-alt",
        "function_name": "list-asset",
        "function_signature": "(define-public (list-asset (tradables principal) (tradable-id uint) (price uint) (commission uint)))",
        "function_args": [
          {
            "hex": "0x06160893b8f8e8c431ab4bc894b4c09cd45661f4b65e09626f6f6d2d6e667473",
            "repr": "SP497E7RX3233ATBS2AB9G4WTHB63X5PBSP5VGAQ.boom-nfts",
            "name": "tradables",
            "type": "principal"
          },
          {
            "hex": "0x0100000000000000000000000000002254",
            "repr": "u8788",
            "name": "tradable-id",
            "type": "uint"
          },
          {
            "hex": "0x01000000000000000000000000042c1d80",
            "repr": "u70000000",
            "name": "price",
            "type": "uint"
          },
          {
            "hex": "0x0100000000000000000000000000000064",
            "repr": "u100",
            "name": "commission",
            "type": "uint"
          }
        ]
      }
    },
    {
      "tx_id": "0xd73df76e9530f5e724b87e3cd20ce4046b386a049e5ee4e7ed0f9e2796009933",
      "nonce": 27,
      "fee_rate": "577303",
      "sender_address": "SP3T2S33TT0DYVYH5KCCBWZT8Q6HQH3SGRGKSBCRQ",
      "sponsored": false,
      "post_condition_mode": "deny",
      "post_conditions": [],
      "anchor_mode": "any",
      "is_unanchored": false,
      "block_hash": "0xeae541b09caa3d57fa3c5581fa5e8ed995dff8e1fc0b1646d8d249902c656943",
      "parent_block_hash": "0xa80328e36b7b0d127d1c0a129eff649ec2ddb6d551e98a38219490fcf2116e59",
      "block_height": 39610,
      "burn_block_time": 1638174864,
      "burn_block_time_iso": "2021-11-29T08:34:24.000Z",
      "parent_burn_block_time": 1638173957,
      "parent_burn_block_time_iso": "2021-11-29T08:19:17.000Z",
      "canonical": true,
      "tx_index": 18,
      "tx_status": "success",
      "tx_result": {
        "hex": "0x0703",
        "repr": "(ok true)"
      },
      "microblock_hash": "",
      "microblock_sequence": 2147483647,
      "microblock_canonical": true,
      "event_count": 1,
      "events": [],
      "execution_cost_read_count": 0,
      "execution_cost_read_length": 0,
      "execution_cost_runtime": 0,
      "execution_cost_write_count": 0,
      "execution_cost_write_length": 0,
      "tx_type": "token_transfer",
      "token_transfer": {
        "recipient_address": "SPX8T06E8FJQ33CX8YVR9CC6D9DSTF6JE0Y8R7DS",
        "amount": "1000000000",
        "memo": "0x31383936303437323637000000000000000000000000000000000000000000000000"
      }
    },
    {
      "tx_id": "0x96529b9cff77080d7aa847b58c2b9d7132ee9245b40b3fdd1185289c93080be9",
      "nonce": 188,
      "fee_rate": "1000000",
      "sender_address": "SP59YR7W1J8MRD1D21TE2YJCSXQ9FBT7SFARXFVB",
      "sponsored": false,
      "post_condition_mode": "allow",
      "post_conditions": [],
      "anchor_mode": "any",
      "is_unanchored": false,
      "block_hash": "0xeae541b09caa3d57fa3c5581fa5e8ed995dff8e1fc0b1646d8d249902c656943",
      "parent_block_hash": "0xa80328e36b7b0d127d1c0a129eff649ec2ddb6d551e98a38219490fcf2116e59",
      "block_height": 39610,
      "burn_block_time": 1638174864,
      "burn_block_time_iso": "2021-11-29T08:34:24.000Z",
      "parent_burn_block_time": 1638173957,
      "parent_burn_block_time_iso": "2021-11-29T08:19:17.000Z",
      "canonical": true,
      "tx_index": 19,
      "tx_status": "abort_by_response",
      "tx_result": {
        "hex": "0x080100000000000000000000000000000001",
        "repr": "(err u1)"
      },
      "microblock_hash": "",
      "microblock_sequence": 2147483647,
      "microblock_canonical": true,
      "event_count": 0,
      "events": [],
      "execution_cost_read_count": 77,
      "execution_cost_read_length": 122064,
      "execution_cost_runtime": 138049000,
      "execution_cost_write_count": 2,
      "execution_cost_write_length": 1,
      "tx_type": "contract_call",
      "contract_call": {
        "contract_id": "SP2C2YFP12AJZB4MABJBAJ55XECVS7E4PMMZ89YZR.arkadiko-stake-registry-v1-1",
        "function_name": "unstake",
        "function_signature": "(define-public (unstake (registry-trait trait_reference) (pool-trait trait_reference) (token-trait trait_reference) (amount uint)))",
        "function_args": [
          {
            "hex": "0x0616982f3ec112a5f5928a5c96a914bd733793b896a51c61726b6164696b6f2d7374616b652d72656769737472792d76312d31",
            "repr": "SP2C2YFP12AJZB4MABJBAJ55XECVS7E4PMMZ89YZR.arkadiko-stake-registry-v1-1",
            "name": "registry-trait",
            "type": "trait_reference"
          },
          {
            "hex": "0x0616982f3ec112a5f5928a5c96a914bd733793b896a51d61726b6164696b6f2d7374616b652d706f6f6c2d64696b6f2d76312d31",
            "repr": "SP2C2YFP12AJZB4MABJBAJ55XECVS7E4PMMZ89YZR.arkadiko-stake-pool-diko-v1-1",
            "name": "pool-trait",
            "type": "trait_reference"
          },
          {
            "hex": "0x0616982f3ec112a5f5928a5c96a914bd733793b896a50e61726b6164696b6f2d746f6b656e",
            "repr": "SP2C2YFP12AJZB4MABJBAJ55XECVS7E4PMMZ89YZR.arkadiko-token",
            "name": "token-trait",
            "type": "trait_reference"
          },
          {
            "hex": "0x0100000000000000000000000014dfaeae",
            "repr": "u350203566",
            "name": "amount",
            "type": "uint"
          }
        ]
      }
    },
    {
      "tx_id": "0x94d65af97515cfb1b77af8a5788009d3e517d79374972a4a523665ce88c0d7fa",
      "nonce": 730,
      "fee_rate": "2060273",
      "sender_address": "SP28KM60ZBE7SPYGHNBCJQHYMPB7DEYYTX7R9H1T4",
      "sponsored": false,
      "post_condition_mode": "deny",
      "post_conditions": [
        {
          "type": "non_fungible",
          "condition_code": "sent",
          "principal": {
            "type_id": "principal_standard",
            "address": "SP28KM60ZBE7SPYGHNBCJQHYMPB7DEYYTX7R9H1T4"
          },
          "asset": {
            "contract_name": "bitcoin-monkeys",
            "asset_name": "bitcoin-monkeys",
            "contract_address": "SP2KAF9RF86PVX3NEE27DFV1CQX0T4WGR41X3S45C"
          },
          "asset_value": {
            "hex": "0x01000000000000000000000000000005e2",
            "repr": "u1506"
          }
        }
      ],
      "anchor_mode": "any",
      "is_unanchored": false,
      "block_hash": "0xeae541b09caa3d57fa3c5581fa5e8ed995dff8e1fc0b1646d8d249902c656943",
      "parent_block_hash": "0xa80328e36b7b0d127d1c0a129eff649ec2ddb6d551e98a38219490fcf2116e59",
      "block_height": 39610,
      "burn_block_time": 1638174864,
      "burn_block_time_iso": "2021-11-29T08:34:24.000Z",
      "parent_burn_block_time": 1638173957,
      "parent_burn_block_time_iso": "2021-11-29T08:19:17.000Z",
      "canonical": true,
      "tx_index": 20,
      "tx_status": "success",
      "tx_result": {
        "hex": "0x0703",
        "repr": "(ok true)"
      },
      "microblock_hash": "",
      "microblock_sequence": 2147483647,
      "microblock_canonical": true,
      "event_count": 1,
      "events": [],
      "execution_cost_read_count": 17,
      "execution_cost_read_length": 66480,
      "execution_cost_runtime": 70564000,
      "execution_cost_write_count": 2,
      "execution_cost_write_length": 685,
      "tx_type": "contract_call",
      "contract_call": {
        "contract_id": "SPNWZ5V2TPWGQGVDR6T7B6RQ4XMGZ4PXTEE0VQ0S.marketplace-v4",
        "function_name": "list-asset",
        "function_signature": "(define-public (list-asset (tradables trait_reference) (tradable-id uint) (price uint) (commission uint)))",
        "function_args": [
          {
            "hex": "0x0616a6a7a70f41adbe8eae708ed7ec2cbf41a27218200f626974636f696e2d6d6f6e6b657973",
            "repr": "SP2KAF9RF86PVX3NEE27DFV1CQX0T4WGR41X3S45C.bitcoin-monkeys",
            "name": "tradables",
            "type": "trait_reference"
          },
          {
            "hex": "0x01000000000000000000000000000005e2",
            "repr": "u1506",
            "name": "tradable-id",
            "type": "uint"
          },
          {
            "hex": "0x0100000000000000000000000003dfd240",
            "repr": "u65000000",
            "name": "price",
            "type": "uint"
          },
          {
            "hex": "0x0100000000000000000000000000000064",
            "repr": "u100",
            "name": "commission",
            "type": "uint"
          }
        ]
      }
    },
    {
      "tx_id": "0x5008a61cbf2f0da77d3a3b951023d5464d809b605abb3accb9b0799ee562c2a3",
      "nonce": 73,
      "fee_rate": "400000",
      "sender_address": "SP1EF1B1SWC2PWBG3PWECRX2114VZPA7NB7MRCM2D",
      "sponsored": false,
      "post_condition_mode": "allow",
      "post_conditions": [],
      "anchor_mode": "any",
      "is_unanchored": false,
      "block_hash": "0xeae541b09caa3d57fa3c5581fa5e8ed995dff8e1fc0b1646d8d249902c656943",
      "parent_block_hash": "0xa80328e36b7b0d127d1c0a129eff649ec2ddb6d551e98a38219490fcf2116e59",
      "block_height": 39610,
      "burn_block_time": 1638174864,
      "burn_block_time_iso": "2021-11-29T08:34:24.000Z",
      "parent_burn_block_time": 1638173957,
      "parent_burn_block_time_iso": "2021-11-29T08:19:17.000Z",
      "canonical": true,
      "tx_index": 21,
      "tx_status": "abort_by_response",
      "tx_result": {
        "hex": "0x080100000000000000000000000000001042",
        "repr": "(err u4162)"
      },
      "microblock_hash": "",
      "microblock_sequence": 2147483647,
      "microblock_canonical": true,
      "event_count": 0,
      "events": [],
      "execution_cost_read_count": 55,
      "execution_cost_read_length": 90442,
      "execution_cost_runtime": 110584000,
      "execution_cost_write_count": 8,
      "execution_cost_write_length": 985,
      "tx_type": "contract_call",
      "contract_call": {
        "contract_id": "SP1EF1B1SWC2PWBG3PWECRX2114VZPA7NB7MRCM2D.pair-v1",
        "function_name": "swap-ark-ss-x",
        "function_signature": "(define-public (swap-ark-ss-x (ss-token1 trait_reference) (ss-token2 trait_reference) (ss-liquidity-token trait_reference) (ark-token1 trait_reference) (ark-token2 trait_reference) (token1-amount uint)))",
        "function_args": [
          {
            "hex": "0x06167e9152cdbbb9fef066df4e1b88b19bcb313acc900e777374782d746f6b656e2d763461",
            "repr": "SP1Z92MPDQEWZXW36VX71Q25HKF5K2EPCJ304F275.wstx-token-v4a",
            "name": "ss-token1",
            "type": "trait_reference"
          },
          {
            "hex": "0x0616982f3ec112a5f5928a5c96a914bd733793b896a50a757364612d746f6b656e",
            "repr": "SP2C2YFP12AJZB4MABJBAJ55XECVS7E4PMMZ89YZR.usda-token",
            "name": "ss-token2",
            "type": "trait_reference"
          },
          {
            "hex": "0x06167e9152cdbbb9fef066df4e1b88b19bcb313acc901b6c69717569646974792d746f6b656e2d76356b30796c356f74386c",
            "repr": "SP1Z92MPDQEWZXW36VX71Q25HKF5K2EPCJ304F275.liquidity-token-v5k0yl5ot8l",
            "name": "ss-liquidity-token",
            "type": "trait_reference"
          },
          {
            "hex": "0x0616982f3ec112a5f5928a5c96a914bd733793b896a511777261707065642d7374782d746f6b656e",
            "repr": "SP2C2YFP12AJZB4MABJBAJ55XECVS7E4PMMZ89YZR.wrapped-stx-token",
            "name": "ark-token1",
            "type": "trait_reference"
          },
          {
            "hex": "0x0616982f3ec112a5f5928a5c96a914bd733793b896a50a757364612d746f6b656e",
            "repr": "SP2C2YFP12AJZB4MABJBAJ55XECVS7E4PMMZ89YZR.usda-token",
            "name": "ark-token2",
            "type": "trait_reference"
          },
          {
            "hex": "0x0100000000000000000000000000000b54",
            "repr": "u2900",
            "name": "token1-amount",
            "type": "uint"
          }
        ]
      }
    },
    {
      "tx_id": "0x91d96e24d1f7f90b1f4cde0e62239db455018b1668e77bacb6007b2f2a304038",
      "nonce": 1,
      "fee_rate": "390000",
      "sender_address": "SP8REEG00CRS5WEE87YF55RZC7ERXXHNS4NHTXPY",
      "sponsored": false,
      "post_condition_mode": "deny",
      "post_conditions": [],
      "anchor_mode": "any",
      "is_unanchored": false,
      "block_hash": "0xeae541b09caa3d57fa3c5581fa5e8ed995dff8e1fc0b1646d8d249902c656943",
      "parent_block_hash": "0xa80328e36b7b0d127d1c0a129eff649ec2ddb6d551e98a38219490fcf2116e59",
      "block_height": 39610,
      "burn_block_time": 1638174864,
      "burn_block_time_iso": "2021-11-29T08:34:24.000Z",
      "parent_burn_block_time": 1638173957,
      "parent_burn_block_time_iso": "2021-11-29T08:19:17.000Z",
      "canonical": true,
      "tx_index": 22,
      "tx_status": "success",
      "tx_result": {
        "hex": "0x0703",
        "repr": "(ok true)"
      },
      "microblock_hash": "",
      "microblock_sequence": 2147483647,
      "microblock_canonical": true,
      "event_count": 2,
      "events": [],
      "execution_cost_read_count": 17,
      "execution_cost_read_length": 44630,
      "execution_cost_runtime": 56669000,
      "execution_cost_write_count": 4,
      "execution_cost_write_length": 604,
      "tx_type": "contract_call",
      "contract_call": {
        "contract_id": "SP000000000000000000002Q6VF78.bns",
        "function_name": "name-register",
        "function_signature": "(define-public (name-register (namespace (buff 20)) (name (buff 48)) (salt (buff 20)) (zonefile-hash (buff 20))))",
        "function_args": [
          {
            "hex": "0x0200000003627463",
            "repr": "0x627463",
            "name": "namespace",
            "type": "(buff 20)"
          },
          {
            "hex": "0x020000000564756d626f",
            "repr": "0x64756d626f",
            "name": "name",
            "type": "(buff 48)"
          },
          {
            "hex": "0x020000001491064a7ccdf232e5206bef53177868de2ecac936",
            "repr": "0x91064a7ccdf232e5206bef53177868de2ecac936",
            "name": "salt",
            "type": "(buff 20)"
          },
          {
            "hex": "0x020000001468b0c4b5d3c5ba971bfb84c22604e95617574f1d",
            "repr": "0x68b0c4b5d3c5ba971bfb84c22604e95617574f1d",
            "name": "zonefile-hash",
            "type": "(buff 20)"
          }
        ]
      }
    },
    {
      "tx_id": "0x872e9fa7a0eeb50006a11317de801adfd25f21fbae3be4eaf3a46dda460021ac",
      "nonce": 12,
      "fee_rate": "750000",
      "sender_address": "SP23J0R6S3QBMMZ9HY0785W93MCY5WNV0TRPJ08CQ",
      "sponsored": false,
      "post_condition_mode": "deny",
      "post_conditions": [
        {
          "type": "non_fungible",
          "condition_code": "sent",
          "principal": {
            "type_id": "principal_contract",
            "contract_name": "stacks-art-market-v2",
            "address": "SPJW1XE278YMCEYMXB8ZFGJMH8ZVAAEDP2S2PJYG"
          },
          "asset": {
            "contract_name": "bitcoin-monkeys",
            "asset_name": "bitcoin-monkeys",
            "contract_address": "SP2KAF9RF86PVX3NEE27DFV1CQX0T4WGR41X3S45C"
          },
          "asset_value": {
            "hex": "0x0100000000000000000000000000000886",
            "repr": "u2182"
          }
        }
      ],
      "anchor_mode": "any",
      "is_unanchored": false,
      "block_hash": "0xeae541b09caa3d57fa3c5581fa5e8ed995dff8e1fc0b1646d8d249902c656943",
      "parent_block_hash": "0xa80328e36b7b0d127d1c0a129eff649ec2ddb6d551e98a38219490fcf2116e59",
      "block_height": 39610,
      "burn_block_time": 1638174864,
      "burn_block_time_iso": "2021-11-29T08:34:24.000Z",
      "parent_burn_block_time": 1638173957,
      "parent_burn_block_time_iso": "2021-11-29T08:19:17.000Z",
      "canonical": true,
      "tx_index": 23,
      "tx_status": "success",
      "tx_result": {
        "hex": "0x0703",
        "repr": "(ok true)"
      },
      "microblock_hash": "",
      "microblock_sequence": 2147483647,
      "microblock_canonical": true,
      "event_count": 2,
      "events": [],
      "execution_cost_read_count": 11,
      "execution_cost_read_length": 35877,
      "execution_cost_runtime": 39826000,
      "execution_cost_write_count": 2,
      "execution_cost_write_length": 84,
      "tx_type": "contract_call",
      "contract_call": {
        "contract_id": "SPJW1XE278YMCEYMXB8ZFGJMH8ZVAAEDP2S2PJYG.stacks-art-market-v2",
        "function_name": "unlist-item",
        "function_signature": "(define-public (unlist-item (collection trait_reference) (collection-id uint) (item-id uint)))",
        "function_args": [
          {
            "hex": "0x0616a6a7a70f41adbe8eae708ed7ec2cbf41a27218200f626974636f696e2d6d6f6e6b657973",
            "repr": "SP2KAF9RF86PVX3NEE27DFV1CQX0T4WGR41X3S45C.bitcoin-monkeys",
            "name": "collection",
            "type": "trait_reference"
          },
          {
            "hex": "0x0100000000000000000000000000000017",
            "repr": "u23",
            "name": "collection-id",
            "type": "uint"
          },
          {
            "hex": "0x0100000000000000000000000000000886",
            "repr": "u2182",
            "name": "item-id",
            "type": "uint"
          }
        ]
      }
    },
    {
      "tx_id": "0x20a63a5c20381fce5d1c63dac2e289ef137f606cc82c295fdb5792ca62ebf151",
      "nonce": 96,
      "fee_rate": "13781",
      "sender_address": "SPWE6JW213WW1NJZC3YY8ANG42NC81P5EYQ3GF58",
      "sponsored": false,
      "post_condition_mode": "deny",
      "post_conditions": [],
      "anchor_mode": "any",
      "is_unanchored": false,
      "block_hash": "0xeae541b09caa3d57fa3c5581fa5e8ed995dff8e1fc0b1646d8d249902c656943",
      "parent_block_hash": "0xa80328e36b7b0d127d1c0a129eff649ec2ddb6d551e98a38219490fcf2116e59",
      "block_height": 39610,
      "burn_block_time": 1638174864,
      "burn_block_time_iso": "2021-11-29T08:34:24.000Z",
      "parent_burn_block_time": 1638173957,
      "parent_burn_block_time_iso": "2021-11-29T08:19:17.000Z",
      "canonical": true,
      "tx_index": 24,
      "tx_status": "success",
      "tx_result": {
        "hex": "0x0703",
        "repr": "(ok true)"
      },
      "microblock_hash": "",
      "microblock_sequence": 2147483647,
      "microblock_canonical": true,
      "event_count": 1,
      "events": [],
      "execution_cost_read_count": 0,
      "execution_cost_read_length": 0,
      "execution_cost_runtime": 0,
      "execution_cost_write_count": 0,
      "execution_cost_write_length": 0,
      "tx_type": "token_transfer",
      "token_transfer": {
        "recipient_address": "SPNBYP1MY456K29804XHT4PY5QKMSXNRBHGADTDY",
        "amount": "150000000",
        "memo": "0x36653237616263613934000000000000000000000000000000000000000000000000"
      }
    },
    {
      "tx_id": "0xc97599158f060cdd446ea2b3f97260a92a75d9ffd5349aac29802e78f094d97c",
      "nonce": 6,
      "fee_rate": "252283",
      "sender_address": "SP1KD8C73DTFSZKYARGRXWMZ0AZW64PMFH519G1V2",
      "sponsored": false,
      "post_condition_mode": "deny",
      "post_conditions": [],
      "anchor_mode": "any",
      "is_unanchored": false,
      "block_hash": "0xeae541b09caa3d57fa3c5581fa5e8ed995dff8e1fc0b1646d8d249902c656943",
      "parent_block_hash": "0xa80328e36b7b0d127d1c0a129eff649ec2ddb6d551e98a38219490fcf2116e59",
      "block_height": 39610,
      "burn_block_time": 1638174864,
      "burn_block_time_iso": "2021-11-29T08:34:24.000Z",
      "parent_burn_block_time": 1638173957,
      "parent_burn_block_time_iso": "2021-11-29T08:19:17.000Z",
      "canonical": true,
      "tx_index": 25,
      "tx_status": "success",
      "tx_result": {
        "hex": "0x070c0000000305636f756e740100000000000000000000000000000001036964730b00000001010000000000000000000000000000225b097365726965732d69640100000000000000000000000000000ae8",
        "repr": "(ok (tuple (count u1) (ids (list u8795)) (series-id u2792)))"
      },
      "microblock_hash": "",
      "microblock_sequence": 2147483647,
      "microblock_canonical": true,
      "event_count": 1,
      "events": [],
      "execution_cost_read_count": 12,
      "execution_cost_read_length": 10365,
      "execution_cost_runtime": 65645000,
      "execution_cost_write_count": 6,
      "execution_cost_write_length": 5840,
      "tx_type": "contract_call",
      "contract_call": {
        "contract_id": "SP497E7RX3233ATBS2AB9G4WTHB63X5PBSP5VGAQ.boom-nfts",
        "function_name": "mint-series",
        "function_signature": "(define-public (mint-series (creator principal) (creator-name (optional (tuple (name (buff 48)) (namespace (buff 20))))) (existing-series-id (optional uint)) (series-name (string-utf8 80)) (series-uri (string-ascii 2048)) (series-mime-type (string-ascii 129)) (copies (list 10 (tuple (hash (buff 64)) (mime-type (string-ascii 129)) (name (string-utf8 80)) (number uint) (uri (string-ascii 2048)))))))",
        "function_args": [
          {
            "hex": "0x051666d430e36e9f9fcfcac431de53e057f8625a8f89",
            "repr": "SP1KD8C73DTFSZKYARGRXWMZ0AZW64PMFH519G1V2",
            "name": "creator",
            "type": "principal"
          },
          {
            "hex": "0x09",
            "repr": "none",
            "name": "creator-name",
            "type": "(optional (tuple (name (buff 48)) (namespace (buff 20))))"
          },
          {
            "hex": "0x09",
            "repr": "none",
            "name": "existing-series-id",
            "type": "(optional uint)"
          },
          {
            "hex": "0x0e0000000b4172746965202333343039",
            "repr": "u\"Artie #3409\"",
            "name": "series-name",
            "type": "(string-utf8 80)"
          },
          {
            "hex": "0x0d0000007068747470733a2f2f626f6f6d2d6e66742d34313336396236362d333664612d343434322d626536302d6666663664373535623036352e73332e616d617a6f6e6177732e636f6d2f66316631326331642d326638622d343930612d613866362d3035313137316266373163342e6a706567",
            "repr": "\"https://boom-nft-41369b66-36da-4442-be60-fff6d755b065.s3.amazonaws.com/f1f12c1d-2f8b-490a-a8f6-051171bf71c4.jpeg\"",
            "name": "series-uri",
            "type": "(string-ascii 2048)"
          },
          {
            "hex": "0x0d0000000a696d6167652f6a706567",
            "repr": "\"image/jpeg\"",
            "name": "series-mime-type",
            "type": "(string-ascii 129)"
          },
          {
            "hex": "0x0b000000010c00000005046861736802000000204eafac91853b72de78034632f6baff584a97e2fbe95e505cb51b5446a63cb7b6096d696d652d747970650d0000000a696d6167652f6a706567046e616d650e0000000e4172746965202333343039202331066e756d6265720100000000000000000000000000000001037572690d0000007068747470733a2f2f626f6f6d2d6e66742d34313336396236362d333664612d343434322d626536302d6666663664373535623036352e73332e616d617a6f6e6177732e636f6d2f66316631326331642d326638622d343930612d613866362d3035313137316266373163342e6a706567",
            "repr": "(list (tuple (hash 0x4eafac91853b72de78034632f6baff584a97e2fbe95e505cb51b5446a63cb7b6) (mime-type \"image/jpeg\") (name u\"Artie #3409 #1\") (number u1) (uri \"https://boom-nft-41369b66-36da-4442-be60-fff6d755b065.s3.amazonaws.com/f1f12c1d-2f8b-490a-a8f6-051171bf71c4.jpeg\")))",
            "name": "copies",
            "type": "(list 10 (tuple (hash (buff 64)) (mime-type (string-ascii 129)) (name (string-utf8 80)) (number uint) (uri (string-ascii 2048))))"
          }
        ]
      }
    },
    {
      "tx_id": "0xb4d607e90d0d52483173e9ce5c603b39cd49f87c5f14cdb63085d87a0ac9e4cd",
      "nonce": 0,
      "fee_rate": "300000",
      "sender_address": "SPAGFQH34888PM547MK4X5AYJJVB11KF1RRAB7EZ",
      "sponsored": false,
      "post_condition_mode": "deny",
      "post_conditions": [
        {
          "type": "stx",
          "condition_code": "sent_equal_to",
          "amount": "2000000",
          "principal": {
            "type_id": "principal_standard",
            "address": "SPAGFQH34888PM547MK4X5AYJJVB11KF1RRAB7EZ"
          }
        }
      ],
      "anchor_mode": "any",
      "is_unanchored": false,
      "block_hash": "0xeae541b09caa3d57fa3c5581fa5e8ed995dff8e1fc0b1646d8d249902c656943",
      "parent_block_hash": "0xa80328e36b7b0d127d1c0a129eff649ec2ddb6d551e98a38219490fcf2116e59",
      "block_height": 39610,
      "burn_block_time": 1638174864,
      "burn_block_time_iso": "2021-11-29T08:34:24.000Z",
      "parent_burn_block_time": 1638173957,
      "parent_burn_block_time_iso": "2021-11-29T08:19:17.000Z",
      "canonical": true,
      "tx_index": 26,
      "tx_status": "success",
      "tx_result": {
        "hex": "0x070100000000000000000000000000009b4a",
        "repr": "(ok u39754)"
      },
      "microblock_hash": "",
      "microblock_sequence": 2147483647,
      "microblock_canonical": true,
      "event_count": 1,
      "events": [],
      "execution_cost_read_count": 8,
      "execution_cost_read_length": 42127,
      "execution_cost_runtime": 42746000,
      "execution_cost_write_count": 2,
      "execution_cost_write_length": 334,
      "tx_type": "contract_call",
      "contract_call": {
        "contract_id": "SP000000000000000000002Q6VF78.bns",
        "function_name": "name-preorder",
        "function_signature": "(define-public (name-preorder (hashed-salted-fqn (buff 20)) (stx-to-burn uint)))",
        "function_args": [
          {
            "hex": "0x0200000014e613818dbed0a5e9cb5489d772980084b32b6002",
            "repr": "0xe613818dbed0a5e9cb5489d772980084b32b6002",
            "name": "hashed-salted-fqn",
            "type": "(buff 20)"
          },
          {
            "hex": "0x01000000000000000000000000001e8480",
            "repr": "u2000000",
            "name": "stx-to-burn",
            "type": "uint"
          }
        ]
      }
    },
    {
      "tx_id": "0x2c6a9d6af52e701afbce239e70affc0c82db3fa68e83d9060875e5bd0f979d7b",
      "nonce": 91,
      "fee_rate": "431570",
      "sender_address": "SP1GPBP8NBRXDRJBFQBV7KMAZX1Z7W2RFWJEH0V10",
      "sponsored": false,
      "post_condition_mode": "allow",
      "post_conditions": [],
      "anchor_mode": "any",
      "is_unanchored": false,
      "block_hash": "0xeae541b09caa3d57fa3c5581fa5e8ed995dff8e1fc0b1646d8d249902c656943",
      "parent_block_hash": "0xa80328e36b7b0d127d1c0a129eff649ec2ddb6d551e98a38219490fcf2116e59",
      "block_height": 39610,
      "burn_block_time": 1638174864,
      "burn_block_time_iso": "2021-11-29T08:34:24.000Z",
      "parent_burn_block_time": 1638173957,
      "parent_burn_block_time_iso": "2021-11-29T08:19:17.000Z",
      "canonical": true,
      "tx_index": 27,
      "tx_status": "success",
      "tx_result": {
        "hex": "0x070b00000002010000000000000000000000000204ba2a0100000000000000000000000003ef1480",
        "repr": "(ok (list u33864234 u66000000))"
      },
      "microblock_hash": "",
      "microblock_sequence": 2147483647,
      "microblock_canonical": true,
      "event_count": 8,
      "events": [],
      "execution_cost_read_count": 30,
      "execution_cost_read_length": 58745,
      "execution_cost_runtime": 71676000,
      "execution_cost_write_count": 8,
      "execution_cost_write_length": 985,
      "tx_type": "contract_call",
      "contract_call": {
        "contract_id": "SP2C2YFP12AJZB4MABJBAJ55XECVS7E4PMMZ89YZR.arkadiko-swap-v2-1",
        "function_name": "swap-y-for-x",
        "function_signature": "(define-public (swap-y-for-x (token-x-trait trait_reference) (token-y-trait trait_reference) (dy uint) (min-dx uint)))",
        "function_args": [
          {
            "hex": "0x0616982f3ec112a5f5928a5c96a914bd733793b896a511777261707065642d7374782d746f6b656e",
            "repr": "SP2C2YFP12AJZB4MABJBAJ55XECVS7E4PMMZ89YZR.wrapped-stx-token",
            "name": "token-x-trait",
            "type": "trait_reference"
          },
          {
            "hex": "0x0616982f3ec112a5f5928a5c96a914bd733793b896a50e61726b6164696b6f2d746f6b656e",
            "repr": "SP2C2YFP12AJZB4MABJBAJ55XECVS7E4PMMZ89YZR.arkadiko-token",
            "name": "token-y-trait",
            "type": "trait_reference"
          },
          {
            "hex": "0x0100000000000000000000000003ef1480",
            "repr": "u66000000",
            "name": "dy",
            "type": "uint"
          },
          {
            "hex": "0x01000000000000000000000000019d981b",
            "repr": "u27105307",
            "name": "min-dx",
            "type": "uint"
          }
        ]
      }
    },
    {
      "tx_id": "0x72742be40fb89eb60a1eb4ade1159785f8f773d5f55d037b3f06498ebf2fbec3",
      "nonce": 51,
      "fee_rate": "29874",
      "sender_address": "SPN20PH9CN7T88ZXNHR10PZ5R1GW78B5FVRR8WFY",
      "sponsored": false,
      "post_condition_mode": "allow",
      "post_conditions": [],
      "anchor_mode": "any",
      "is_unanchored": false,
      "block_hash": "0xeae541b09caa3d57fa3c5581fa5e8ed995dff8e1fc0b1646d8d249902c656943",
      "parent_block_hash": "0xa80328e36b7b0d127d1c0a129eff649ec2ddb6d551e98a38219490fcf2116e59",
      "block_height": 39610,
      "burn_block_time": 1638174864,
      "burn_block_time_iso": "2021-11-29T08:34:24.000Z",
      "parent_burn_block_time": 1638173957,
      "parent_burn_block_time_iso": "2021-11-29T08:19:17.000Z",
      "canonical": true,
      "tx_index": 28,
      "tx_status": "success",
      "tx_result": {
        "hex": "0x070b00000002010000000000000000000000000065c5a00100000000000000000000000000c65d40",
        "repr": "(ok (list u6669728 u13000000))"
      },
      "microblock_hash": "",
      "microblock_sequence": 2147483647,
      "microblock_canonical": true,
      "event_count": 8,
      "events": [],
      "execution_cost_read_count": 30,
      "execution_cost_read_length": 58745,
      "execution_cost_runtime": 71676000,
      "execution_cost_write_count": 8,
      "execution_cost_write_length": 985,
      "tx_type": "contract_call",
      "contract_call": {
        "contract_id": "SP2C2YFP12AJZB4MABJBAJ55XECVS7E4PMMZ89YZR.arkadiko-swap-v2-1",
        "function_name": "swap-y-for-x",
        "function_signature": "(define-public (swap-y-for-x (token-x-trait trait_reference) (token-y-trait trait_reference) (dy uint) (min-dx uint)))",
        "function_args": [
          {
            "hex": "0x0616982f3ec112a5f5928a5c96a914bd733793b896a511777261707065642d7374782d746f6b656e",
            "repr": "SP2C2YFP12AJZB4MABJBAJ55XECVS7E4PMMZ89YZR.wrapped-stx-token",
            "name": "token-x-trait",
            "type": "trait_reference"
          },
          {
            "hex": "0x0616982f3ec112a5f5928a5c96a914bd733793b896a50e61726b6164696b6f2d746f6b656e",
            "repr": "SP2C2YFP12AJZB4MABJBAJ55XECVS7E4PMMZ89YZR.arkadiko-token",
            "name": "token-y-trait",
            "type": "trait_reference"
          },
          {
            "hex": "0x0100000000000000000000000000c65d40",
            "repr": "u13000000",
            "name": "dy",
            "type": "uint"
          },
          {
            "hex": "0x0100000000000000000000000000517838",
            "repr": "u5339192",
            "name": "min-dx",
            "type": "uint"
          }
        ]
      }
    },
    {
      "tx_id": "0x8a71723c23ea64b419e2cf9770163c9f7fde39f95ac10904b776dbd9cde53c25",
      "nonce": 64,
      "fee_rate": "103777",
      "sender_address": "SPXEXQ0ZESWZK9ZK4S5KEZ2EHS48NZ4F241X2FZS",
      "sponsored": false,
      "post_condition_mode": "deny",
      "post_conditions": [],
      "anchor_mode": "any",
      "is_unanchored": false,
      "block_hash": "0xeae541b09caa3d57fa3c5581fa5e8ed995dff8e1fc0b1646d8d249902c656943",
      "parent_block_hash": "0xa80328e36b7b0d127d1c0a129eff649ec2ddb6d551e98a38219490fcf2116e59",
      "block_height": 39610,
      "burn_block_time": 1638174864,
      "burn_block_time_iso": "2021-11-29T08:34:24.000Z",
      "parent_burn_block_time": 1638173957,
      "parent_burn_block_time_iso": "2021-11-29T08:19:17.000Z",
      "canonical": true,
      "tx_index": 29,
      "tx_status": "success",
      "tx_result": {
        "hex": "0x07010000000000000000000000000062b8ab",
        "repr": "(ok u6469803)"
      },
      "microblock_hash": "",
      "microblock_sequence": 2147483647,
      "microblock_canonical": true,
      "event_count": 2,
      "events": [],
      "execution_cost_read_count": 46,
      "execution_cost_read_length": 32310,
      "execution_cost_runtime": 37880000,
      "execution_cost_write_count": 5,
      "execution_cost_write_length": 311,
      "tx_type": "contract_call",
      "contract_call": {
        "contract_id": "SP2C2YFP12AJZB4MABJBAJ55XECVS7E4PMMZ89YZR.arkadiko-vault-rewards-v1-1",
        "function_name": "claim-pending-rewards",
        "function_signature": "(define-public (claim-pending-rewards ))"
      }
    },
    {
      "tx_id": "0x0020545c39a9c027fdbf30405206dd1a6670941f8dde9691179c17589312fa49",
      "nonce": 41,
      "fee_rate": "750000",
      "sender_address": "SP1P5XD9HWPH7YGFTVWVT1JH8V7BXG6RGTGHQ7R7T",
      "sponsored": false,
      "post_condition_mode": "deny",
      "post_conditions": [
        {
          "type": "fungible",
          "condition_code": "sent_less_than_or_equal_to",
          "amount": "252792000",
          "principal": {
            "type_id": "principal_standard",
            "address": "SP1P5XD9HWPH7YGFTVWVT1JH8V7BXG6RGTGHQ7R7T"
          },
          "asset": {
            "contract_name": "stsw-token-v4a",
            "asset_name": "stsw",
            "contract_address": "SP1Z92MPDQEWZXW36VX71Q25HKF5K2EPCJ304F275"
          }
        },
        {
          "type": "stx",
          "condition_code": "sent_less_than_or_equal_to",
          "amount": "57288218",
          "principal": {
            "type_id": "principal_standard",
            "address": "SP1P5XD9HWPH7YGFTVWVT1JH8V7BXG6RGTGHQ7R7T"
          }
        }
      ],
      "anchor_mode": "any",
      "is_unanchored": false,
      "block_hash": "0xeae541b09caa3d57fa3c5581fa5e8ed995dff8e1fc0b1646d8d249902c656943",
      "parent_block_hash": "0xa80328e36b7b0d127d1c0a129eff649ec2ddb6d551e98a38219490fcf2116e59",
      "block_height": 39610,
      "burn_block_time": 1638174864,
      "burn_block_time_iso": "2021-11-29T08:34:24.000Z",
      "parent_burn_block_time": 1638173957,
      "parent_burn_block_time_iso": "2021-11-29T08:19:17.000Z",
      "canonical": true,
      "tx_index": 30,
      "tx_status": "abort_by_response",
      "tx_result": {
        "hex": "0x080100000000000000000000000000000001",
        "repr": "(err u1)"
      },
      "microblock_hash": "",
      "microblock_sequence": 2147483647,
      "microblock_canonical": true,
      "event_count": 0,
      "events": [],
      "execution_cost_read_count": 37,
      "execution_cost_read_length": 35496,
      "execution_cost_runtime": 44473000,
      "execution_cost_write_count": 1,
      "execution_cost_write_length": 1,
      "tx_type": "contract_call",
      "contract_call": {
        "contract_id": "SP1Z92MPDQEWZXW36VX71Q25HKF5K2EPCJ304F275.stackswap-swap-v5k",
        "function_name": "add-to-position",
        "function_signature": "(define-public (add-to-position (token-x-trait trait_reference) (token-y-trait trait_reference) (token-liquidity-trait trait_reference) (x uint) (y uint)))",
        "function_args": [
          {
            "hex": "0x06167e9152cdbbb9fef066df4e1b88b19bcb313acc900e777374782d746f6b656e2d763461",
            "repr": "SP1Z92MPDQEWZXW36VX71Q25HKF5K2EPCJ304F275.wstx-token-v4a",
            "name": "token-x-trait",
            "type": "trait_reference"
          },
          {
            "hex": "0x06167e9152cdbbb9fef066df4e1b88b19bcb313acc900e737473772d746f6b656e2d763461",
            "repr": "SP1Z92MPDQEWZXW36VX71Q25HKF5K2EPCJ304F275.stsw-token-v4a",
            "name": "token-y-trait",
            "type": "trait_reference"
          },
          {
            "hex": "0x06167e9152cdbbb9fef066df4e1b88b19bcb313acc90186c69717569646974792d746f6b656e2d7374782d73747377",
            "repr": "SP1Z92MPDQEWZXW36VX71Q25HKF5K2EPCJ304F275.liquidity-token-stx-stsw",
            "name": "token-liquidity-trait",
            "type": "trait_reference"
          },
          {
            "hex": "0x0100000000000000000000000002d87516",
            "repr": "u47740182",
            "name": "x",
            "type": "uint"
          },
          {
            "hex": "0x010000000000000000000000000c8e6aa0",
            "repr": "u210660000",
            "name": "y",
            "type": "uint"
          }
        ]
      }
    },
    {
      "tx_id": "0xe21e75c6e1cc224d65ccd1792f47adfbd254fbe329cb6ae344df65baa80a2106",
      "nonce": 0,
      "fee_rate": "236575",
      "sender_address": "SP8R1HZS39P4DJYAYPZ915EP5T0WH4YZG2T1FN0W",
      "sponsored": false,
      "post_condition_mode": "deny",
      "post_conditions": [
        {
          "type": "stx",
          "condition_code": "sent_equal_to",
          "amount": "2000000",
          "principal": {
            "type_id": "principal_standard",
            "address": "SP8R1HZS39P4DJYAYPZ915EP5T0WH4YZG2T1FN0W"
          }
        }
      ],
      "anchor_mode": "any",
      "is_unanchored": false,
      "block_hash": "0xeae541b09caa3d57fa3c5581fa5e8ed995dff8e1fc0b1646d8d249902c656943",
      "parent_block_hash": "0xa80328e36b7b0d127d1c0a129eff649ec2ddb6d551e98a38219490fcf2116e59",
      "block_height": 39610,
      "burn_block_time": 1638174864,
      "burn_block_time_iso": "2021-11-29T08:34:24.000Z",
      "parent_burn_block_time": 1638173957,
      "parent_burn_block_time_iso": "2021-11-29T08:19:17.000Z",
      "canonical": true,
      "tx_index": 31,
      "tx_status": "success",
      "tx_result": {
        "hex": "0x070100000000000000000000000000009b4a",
        "repr": "(ok u39754)"
      },
      "microblock_hash": "",
      "microblock_sequence": 2147483647,
      "microblock_canonical": true,
      "event_count": 1,
      "events": [],
      "execution_cost_read_count": 8,
      "execution_cost_read_length": 42127,
      "execution_cost_runtime": 42746000,
      "execution_cost_write_count": 2,
      "execution_cost_write_length": 334,
      "tx_type": "contract_call",
      "contract_call": {
        "contract_id": "SP000000000000000000002Q6VF78.bns",
        "function_name": "name-preorder",
        "function_signature": "(define-public (name-preorder (hashed-salted-fqn (buff 20)) (stx-to-burn uint)))",
        "function_args": [
          {
            "hex": "0x020000001499388228fc38625d0e7e474aeecd095bda756f11",
            "repr": "0x99388228fc38625d0e7e474aeecd095bda756f11",
            "name": "hashed-salted-fqn",
            "type": "(buff 20)"
          },
          {
            "hex": "0x01000000000000000000000000001e8480",
            "repr": "u2000000",
            "name": "stx-to-burn",
            "type": "uint"
          }
        ]
      }
    },
    {
      "tx_id": "0x06f8f1fe740cc9b008fbf3c44afcca33153abf9a3ba341f8bf76fd598250de78",
      "nonce": 41,
      "fee_rate": "100000",
      "sender_address": "SP3MJSNG2DPSBPPCCBFKJF6MFFPH0M8HCVKMVGPXF",
      "sponsored": false,
      "post_condition_mode": "deny",
      "post_conditions": [],
      "anchor_mode": "any",
      "is_unanchored": false,
      "block_hash": "0xeae541b09caa3d57fa3c5581fa5e8ed995dff8e1fc0b1646d8d249902c656943",
      "parent_block_hash": "0xa80328e36b7b0d127d1c0a129eff649ec2ddb6d551e98a38219490fcf2116e59",
      "block_height": 39610,
      "burn_block_time": 1638174864,
      "burn_block_time_iso": "2021-11-29T08:34:24.000Z",
      "parent_burn_block_time": 1638173957,
      "parent_burn_block_time_iso": "2021-11-29T08:19:17.000Z",
      "canonical": true,
      "tx_index": 32,
      "tx_status": "success",
      "tx_result": {
        "hex": "0x0703",
        "repr": "(ok true)"
      },
      "microblock_hash": "",
      "microblock_sequence": 2147483647,
      "microblock_canonical": true,
      "event_count": 1,
      "events": [],
      "execution_cost_read_count": 0,
      "execution_cost_read_length": 0,
      "execution_cost_runtime": 0,
      "execution_cost_write_count": 0,
      "execution_cost_write_length": 0,
      "tx_type": "token_transfer",
      "token_transfer": {
        "recipient_address": "SP13EQ51XJ03GN1AB16VV1P708BY3XP5MD4ASR3M1",
        "amount": "500000000",
        "memo": "0x00000000000000000000000000000000000000000000000000000000000000000000"
      }
    },
    {
      "tx_id": "0x837cd6086a4189fea56f8526d89d7c7492fa963e9e5a2d5a74b8d9e261990fc8",
      "nonce": 0,
      "fee_rate": "147434",
      "sender_address": "SP1K123YQ0RTJWEK786D1Z4RBGBE0S3CN3EYRAVKD",
      "sponsored": false,
      "post_condition_mode": "deny",
      "post_conditions": [
        {
          "type": "stx",
          "condition_code": "sent_equal_to",
          "amount": "2000000",
          "principal": {
            "type_id": "principal_standard",
            "address": "SP1K123YQ0RTJWEK786D1Z4RBGBE0S3CN3EYRAVKD"
          }
        }
      ],
      "anchor_mode": "any",
      "is_unanchored": false,
      "block_hash": "0xeae541b09caa3d57fa3c5581fa5e8ed995dff8e1fc0b1646d8d249902c656943",
      "parent_block_hash": "0xa80328e36b7b0d127d1c0a129eff649ec2ddb6d551e98a38219490fcf2116e59",
      "block_height": 39610,
      "burn_block_time": 1638174864,
      "burn_block_time_iso": "2021-11-29T08:34:24.000Z",
      "parent_burn_block_time": 1638173957,
      "parent_burn_block_time_iso": "2021-11-29T08:19:17.000Z",
      "canonical": true,
      "tx_index": 33,
      "tx_status": "success",
      "tx_result": {
        "hex": "0x070100000000000000000000000000009b4a",
        "repr": "(ok u39754)"
      },
      "microblock_hash": "",
      "microblock_sequence": 2147483647,
      "microblock_canonical": true,
      "event_count": 1,
      "events": [],
      "execution_cost_read_count": 8,
      "execution_cost_read_length": 42127,
      "execution_cost_runtime": 42746000,
      "execution_cost_write_count": 2,
      "execution_cost_write_length": 334,
      "tx_type": "contract_call",
      "contract_call": {
        "contract_id": "SP000000000000000000002Q6VF78.bns",
        "function_name": "name-preorder",
        "function_signature": "(define-public (name-preorder (hashed-salted-fqn (buff 20)) (stx-to-burn uint)))",
        "function_args": [
          {
            "hex": "0x02000000149140c45a69653e033ae310cbfbdb7f94234df42f",
            "repr": "0x9140c45a69653e033ae310cbfbdb7f94234df42f",
            "name": "hashed-salted-fqn",
            "type": "(buff 20)"
          },
          {
            "hex": "0x01000000000000000000000000001e8480",
            "repr": "u2000000",
            "name": "stx-to-burn",
            "type": "uint"
          }
        ]
      }
    },
    {
      "tx_id": "0x8aa9838d3c765bb99960a5fcce1c1fcc9d83f7d0af9fc8ac90c8c022f6768022",
      "nonce": 69,
      "fee_rate": "72000",
      "sender_address": "SP2N1P4Q462VT14Q8NXJT6ABK8NHXHHVPJEVN4WR7",
      "sponsored": false,
      "post_condition_mode": "deny",
      "post_conditions": [],
      "anchor_mode": "any",
      "is_unanchored": false,
      "block_hash": "0xeae541b09caa3d57fa3c5581fa5e8ed995dff8e1fc0b1646d8d249902c656943",
      "parent_block_hash": "0xa80328e36b7b0d127d1c0a129eff649ec2ddb6d551e98a38219490fcf2116e59",
      "block_height": 39610,
      "burn_block_time": 1638174864,
      "burn_block_time_iso": "2021-11-29T08:34:24.000Z",
      "parent_burn_block_time": 1638173957,
      "parent_burn_block_time_iso": "2021-11-29T08:19:17.000Z",
      "canonical": true,
      "tx_index": 34,
      "tx_status": "success",
      "tx_result": {
        "hex": "0x0703",
        "repr": "(ok true)"
      },
      "microblock_hash": "",
      "microblock_sequence": 2147483647,
      "microblock_canonical": true,
      "event_count": 1,
      "events": [],
      "execution_cost_read_count": 0,
      "execution_cost_read_length": 0,
      "execution_cost_runtime": 0,
      "execution_cost_write_count": 0,
      "execution_cost_write_length": 0,
      "tx_type": "token_transfer",
      "token_transfer": {
        "recipient_address": "SPX8T06E8FJQ33CX8YVR9CC6D9DSTF6JE0Y8R7DS",
        "amount": "363800000",
        "memo": "0x31383637363535393837000000000000000000000000000000000000000000000000"
      }
    },
    {
      "tx_id": "0x4afc0602ffaf95aada32cee7a914a046957ea1f401127e1583ee67dc48baf4d0",
      "nonce": 0,
      "fee_rate": "100000",
      "sender_address": "SP3WVRA993MBD0DR3XWNG1W9XST0VSJD5BZNEBCJG",
      "sponsored": false,
      "post_condition_mode": "deny",
      "post_conditions": [
        {
          "type": "stx",
          "condition_code": "sent_equal_to",
          "amount": "2000000",
          "principal": {
            "type_id": "principal_standard",
            "address": "SP3WVRA993MBD0DR3XWNG1W9XST0VSJD5BZNEBCJG"
          }
        }
      ],
      "anchor_mode": "any",
      "is_unanchored": false,
      "block_hash": "0xeae541b09caa3d57fa3c5581fa5e8ed995dff8e1fc0b1646d8d249902c656943",
      "parent_block_hash": "0xa80328e36b7b0d127d1c0a129eff649ec2ddb6d551e98a38219490fcf2116e59",
      "block_height": 39610,
      "burn_block_time": 1638174864,
      "burn_block_time_iso": "2021-11-29T08:34:24.000Z",
      "parent_burn_block_time": 1638173957,
      "parent_burn_block_time_iso": "2021-11-29T08:19:17.000Z",
      "canonical": true,
      "tx_index": 35,
      "tx_status": "success",
      "tx_result": {
        "hex": "0x070100000000000000000000000000009b4a",
        "repr": "(ok u39754)"
      },
      "microblock_hash": "",
      "microblock_sequence": 2147483647,
      "microblock_canonical": true,
      "event_count": 1,
      "events": [],
      "execution_cost_read_count": 8,
      "execution_cost_read_length": 42127,
      "execution_cost_runtime": 42746000,
      "execution_cost_write_count": 2,
      "execution_cost_write_length": 334,
      "tx_type": "contract_call",
      "contract_call": {
        "contract_id": "SP000000000000000000002Q6VF78.bns",
        "function_name": "name-preorder",
        "function_signature": "(define-public (name-preorder (hashed-salted-fqn (buff 20)) (stx-to-burn uint)))",
        "function_args": [
          {
            "hex": "0x0200000014386087914f501e5a8b8cfc28b975fb28a082959d",
            "repr": "0x386087914f501e5a8b8cfc28b975fb28a082959d",
            "name": "hashed-salted-fqn",
            "type": "(buff 20)"
          },
          {
            "hex": "0x01000000000000000000000000001e8480",
            "repr": "u2000000",
            "name": "stx-to-burn",
            "type": "uint"
          }
        ]
      }
    },
    {
      "tx_id": "0x8e2ef0873711b3773ebe2d47af9f2525452b5028dd488c920011bf401815e01c",
      "nonce": 10,
      "fee_rate": "53677",
      "sender_address": "SP3X3WQYNT3T020D19CSGSV61MY7FCJE7QTFXVA3C",
      "sponsored": false,
      "post_condition_mode": "deny",
      "post_conditions": [],
      "anchor_mode": "any",
      "is_unanchored": false,
      "block_hash": "0xeae541b09caa3d57fa3c5581fa5e8ed995dff8e1fc0b1646d8d249902c656943",
      "parent_block_hash": "0xa80328e36b7b0d127d1c0a129eff649ec2ddb6d551e98a38219490fcf2116e59",
      "block_height": 39610,
      "burn_block_time": 1638174864,
      "burn_block_time_iso": "2021-11-29T08:34:24.000Z",
      "parent_burn_block_time": 1638173957,
      "parent_burn_block_time_iso": "2021-11-29T08:19:17.000Z",
      "canonical": true,
      "tx_index": 36,
      "tx_status": "success",
      "tx_result": {
        "hex": "0x0703",
        "repr": "(ok true)"
      },
      "microblock_hash": "",
      "microblock_sequence": 2147483647,
      "microblock_canonical": true,
      "event_count": 0,
      "events": [],
      "execution_cost_read_count": 4,
      "execution_cost_read_length": 31643,
      "execution_cost_runtime": 32380000,
      "execution_cost_write_count": 1,
      "execution_cost_write_length": 398,
      "tx_type": "contract_call",
      "contract_call": {
        "contract_id": "SP000000000000000000002Q6VF78.pox",
        "function_name": "allow-contract-caller",
        "function_signature": "(define-public (allow-contract-caller (caller principal) (until-burn-ht (optional uint))))",
        "function_args": [
          {
            "hex": "0x06166f30abe2260231300d411ceba3c29362ac37054612626f6f6d626f7865732d6379636c652d3232",
            "repr": "SP1QK1AZ24R132C0D84EEQ8Y2JDHARDR58R72E1ZW.boomboxes-cycle-22",
            "name": "caller",
            "type": "principal"
          },
          {
            "hex": "0x09",
            "repr": "none",
            "name": "until-burn-ht",
            "type": "(optional uint)"
          }
        ]
      }
    }
  ],
  "total": 37
}
