{
  "limit": 96,
  "offset": 0,
  "results": [
    {
      "tx_id": "0xfbc3164a2b7316372706e9b35386da60a885520b4ea050e37feb2c91475ab6fc",
      "nonce": 2022,
      "fee_rate": "0",
      "sender_address": "SP11SERAP17NV2F1PGHX6S9RGPE3CSZAE3B6Z9JW7",
      "sponsored": false,
      "post_condition_mode": "deny",
      "post_conditions": [],
      "anchor_mode": "on_chain_only",
      "is_unanchored": false,
      "block_hash": "0xb287a21633224ad05ea83d769302d794311da3be48a0eb0c616d02059909b645",
      "parent_block_hash": "0x501d2f28cca2e2b01aa3e343c56287abf9b35512b2895397579153c8e3775a28",
      "block_height": 39496,
      "burn_block_time": 1638096211,
      "burn_block_time_iso": "2021-11-28T10:43:31.000Z",
      "parent_burn_block_time": 1638095878,
      "parent_burn_block_time_iso": "2021-11-28T10:37:58.000Z",
      "canonical": true,
      "tx_index": 0,
      "tx_status": "success",
      "tx_result": {
        "hex": "0x0703",
        "repr": "(ok true)"
      },
      "microblock_hash": "",
      "microblock_sequence": 2147483647,
      "microblock_canonical": true,
      "event_count": 0,
      "events": [],
      "execution_cost_read_count": 0,
      "execution_cost_read_length": 0,
      "execution_cost_runtime": 0,
      "execution_cost_write_count": 0,
      "execution_cost_write_length": 0,
      "tx_type": "coinbase",
      "coinbase_payload": {
        "data": "0x0000000000000000000000000000000000000000000000000000000000000000"
      }
    },
    {
      "tx_id": "0x3aced3135aae39f676ac99e07682906f1c1a3923bdad92b35ef0cb2903192010",
      "nonce": 203,
      "fee_rate": "1000000",
      "sender_address": "SP3TF26QFS3YMYHC9N3ZZTZQKCM4AFYMVW1WMFRTT",
      "sponsored": false,
      "post_condition_mode": "deny",
      "post_conditions": [],
      "anchor_mode": "any",
      "is_unanchored": false,
      "block_hash": "0xb287a21633224ad05ea83d769302d794311da3be48a0eb0c616d02059909b645",
      "parent_block_hash": "0x501d2f28cca2e2b01aa3e343c56287abf9b35512b2895397579153c8e3775a28",
      "block_height": 39496,
      "burn_block_time": 1638096211,
      "burn_block_time_iso": "2021-11-28T10:43:31.000Z",
      "parent_burn_block_time": 1638095878,
      "parent_burn_block_time_iso": "2021-11-28T10:37:58.000Z",
      "canonical": true,
      "tx_index": 1,
      "tx_status": "success",
      "tx_result": {
        "hex": "0x0701000000000000000000000000a8c34de1",
        "repr": "(ok u2831371745)"
      },
      "microblock_hash": "",
      "microblock_sequence": 2147483647,
      "microblock_canonical": true,
      "event_count": 2,
      "events": [],
      "execution_cost_read_count": 78,
      "execution_cost_read_length": 117597,
      "execution_cost_runtime": 133657000,
      "execution_cost_write_count": 5,
      "execution_cost_write_length": 299,
      "tx_type": "contract_call",
      "contract_call": {
        "contract_id": "SP2C2YFP12AJZB4MABJBAJ55XECVS7E4PMMZ89YZR.arkadiko-stake-registry-v1-1",
        "function_name": "claim-pending-rewards",
        "function_signature": "(define-public (claim-pending-rewards (registry-trait trait_reference) (pool-trait trait_reference)))",
        "function_args": [
          {
            "hex": "0x0616982f3ec112a5f5928a5c96a914bd733793b896a51c61726b6164696b6f2d7374616b652d72656769737472792d76312d31",
            "repr": "SP2C2YFP12AJZB4MABJBAJ55XECVS7E4PMMZ89YZR.arkadiko-stake-registry-v1-1",
            "name": "registry-trait",
            "type": "trait_reference"
          },
          {
            "hex": "0x0616982f3ec112a5f5928a5c96a914bd733793b896a52261726b6164696b6f2d7374616b652d706f6f6c2d777374782d757364612d76312d31",
            "repr": "SP2C2YFP12AJZB4MABJBAJ55XECVS7E4PMMZ89YZR.arkadiko-stake-pool-wstx-usda-v1-1",
            "name": "pool-trait",
            "type": "trait_reference"
          }
        ]
      }
    },
    {
      "tx_id": "0x5cfc912d689778f40a1b8d53f916f48fd1dc23acf888eaa2bb1f3bfaf0cd834f",
      "nonce": 130,
      "fee_rate": "50000",
      "sender_address": "SPFVR8J8X0R4B4GTW5C5N3ZVJZ15BKDEWNXKSQT1",
      "sponsored": false,
      "post_condition_mode": "allow",
      "post_conditions": [],
      "anchor_mode": "any",
      "is_unanchored": false,
      "block_hash": "0xb287a21633224ad05ea83d769302d794311da3be48a0eb0c616d02059909b645",
      "parent_block_hash": "0x501d2f28cca2e2b01aa3e343c56287abf9b35512b2895397579153c8e3775a28",
      "block_height": 39496,
      "burn_block_time": 1638096211,
      "burn_block_time_iso": "2021-11-28T10:43:31.000Z",
      "parent_burn_block_time": 1638095878,
      "parent_burn_block_time_iso": "2021-11-28T10:37:58.000Z",
      "canonical": true,
      "tx_index": 18,
      "tx_status": "success",
      "tx_result": {
        "hex": "0x070b000000020100000000000000000000000001bce5000100000000000000000000000003473bc0",
        "repr": "(ok (list u29156608 u55000000))"
      },
      "microblock_hash": "",
      "microblock_sequence": 2147483647,
      "microblock_canonical": true,
      "event_count": 8,
      "events": [],
      "execution_cost_read_count": 30,
      "execution_cost_read_length": 58745,
      "execution_cost_runtime": 71676000,
      "execution_cost_write_count": 8,
      "execution_cost_write_length": 985,
      "tx_type": "contract_call",
      "contract_call": {
        "contract_id": "SP2C2YFP12AJZB4MABJBAJ55XECVS7E4PMMZ89YZR.arkadiko-swap-v2-1",
        "function_name": "swap-y-for-x",
        "function_signature": "(define-public (swap-y-for-x (token-x-trait trait_reference) (token-y-trait trait_reference) (dy uint) (min-dx uint)))",
        "function_args": [
          {
            "hex": "0x0616982f3ec112a5f5928a5c96a914bd733793b896a511777261707065642d7374782d746f6b656e",
            "repr": "SP2C2YFP12AJZB4MABJBAJ55XECVS7E4PMMZ89YZR.wrapped-stx-token",
            "name": "token-x-trait",
            "type": "trait_reference"
          },
          {
            "hex": "0x0616982f3ec112a5f5928a5c96a914bd733793b896a50e61726b6164696b6f2d746f6b656e",
            "repr": "SP2C2YFP12AJZB4MABJBAJ55XECVS7E4PMMZ89YZR.arkadiko-token",
            "name": "token-y-trait",
            "type": "trait_reference"
          },
          {
            "hex": "0x0100000000000000000000000003473bc0",
            "repr": "u55000000",
            "name": "dy",
            "type": "uint"
          },
          {
            "hex": "0x0100000000000000000000000001ab0b19",
            "repr": "u27986713",
            "name": "min-dx",
            "type": "uint"
          }
        ]
      }
    },
    {
      "tx_id": "0x5d7dc4aa3a27d294b78f15121b0b25d9289c5f94bde386c9584ec06df47d9766",
      "nonce": 11,
      "fee_rate": "704697",
      "sender_address": "SPGMTQN3MR9RXGP4WGJ49KMJXFG87FPMCJ3VAX1X",
      "sponsored": false,
      "post_condition_mode": "allow",
      "post_conditions": [],
      "anchor_mode": "any",
      "is_unanchored": false,
      "block_hash": "0xb287a21633224ad05ea83d769302d794311da3be48a0eb0c616d02059909b645",
      "parent_block_hash": "0x501d2f28cca2e2b01aa3e343c56287abf9b35512b2895397579153c8e3775a28",
      "block_height": 39496,
      "burn_block_time": 1638096211,
      "burn_block_time_iso": "2021-11-28T10:43:31.000Z",
      "parent_burn_block_time": 1638095878,
      "parent_burn_block_time_iso": "2021-11-28T10:37:58.000Z",
      "canonical": true,
      "tx_index": 19,
      "tx_status": "success",
      "tx_result": {
        "hex": "0x070b000000020100000000000000000000000000c5ea5101000000000000000000000000017d7840",
        "repr": "(ok (list u12970577 u25000000))"
      },
      "microblock_hash": "",
      "microblock_sequence": 2147483647,
      "microblock_canonical": true,
      "event_count": 8,
      "events": [],
      "execution_cost_read_count": 30,
      "execution_cost_read_length": 58490,
      "execution_cost_runtime": 71421000,
      "execution_cost_write_count": 8,
      "execution_cost_write_length": 985,
      "tx_type": "contract_call",
      "contract_call": {
        "contract_id": "SP2C2YFP12AJZB4MABJBAJ55XECVS7E4PMMZ89YZR.arkadiko-swap-v2-1",
        "function_name": "swap-y-for-x",
        "function_signature": "(define-public (swap-y-for-x (token-x-trait trait_reference) (token-y-trait trait_reference) (dy uint) (min-dx uint)))",
        "function_args": [
          {
            "hex": "0x0616982f3ec112a5f5928a5c96a914bd733793b896a511777261707065642d7374782d746f6b656e",
            "repr": "SP2C2YFP12AJZB4MABJBAJ55XECVS7E4PMMZ89YZR.wrapped-stx-token",
            "name": "token-x-trait",
            "type": "trait_reference"
          },
          {
            "hex": "0x0616982f3ec112a5f5928a5c96a914bd733793b896a50a757364612d746f6b656e",
            "repr": "SP2C2YFP12AJZB4MABJBAJ55XECVS7E4PMMZ89YZR.usda-token",
            "name": "token-y-trait",
            "type": "trait_reference"
          },
          {
            "hex": "0x01000000000000000000000000017d7840",
            "repr": "u25000000",
            "name": "dy",
            "type": "uint"
          },
          {
            "hex": "0x0100000000000000000000000000bd1e0e",
            "repr": "u12393998",
            "name": "min-dx",
            "type": "uint"
          }
        ]
      }
    },
    {
      "tx_id": "0x142628ab983e4e74a708c1bd6565eb9d9e586bef87d0ce6046d801e3c9c2eaa3",
      "nonce": 1,
      "fee_rate": "15070",
      "sender_address": "SP1ZCJGRBCC73M12K4BCZTN4VM2KNVCY33P3KXZRQ",
      "sponsored": false,
      "post_condition_mode": "deny",
      "post_conditions": [],
      "anchor_mode": "any",
      "is_unanchored": false,
      "block_hash": "0xb287a21633224ad05ea83d769302d794311da3be48a0eb0c616d02059909b645",
      "parent_block_hash": "0x501d2f28cca2e2b01aa3e343c56287abf9b35512b2895397579153c8e3775a28",
      "block_height": 39496,
      "burn_block_time": 1638096211,
      "burn_block_time_iso": "2021-11-28T10:43:31.000Z",
      "parent_burn_block_time": 1638095878,
      "parent_burn_block_time_iso": "2021-11-28T10:37:58.000Z",
      "canonical": true,
      "tx_index": 32,
      "tx_status": "success",
      "tx_result": {
        "hex": "0x0703",
        "repr": "(ok true)"
      },
      "microblock_hash": "",
      "microblock_sequence": 2147483647,
      "microblock_canonical": true,
      "event_count": 2,
      "events": [],
      "execution_cost_read_count": 17,
      "execution_cost_read_length": 44630,
      "execution_cost_runtime": 57243000,
      "execution_cost_write_count": 4,
      "execution_cost_write_length": 604,
      "tx_type": "contract_call",
      "contract_call": {
        "contract_id": "SP000000000000000000002Q6VF78.bns",
        "function_name": "name-register",
        "function_signature": "(define-public (name-register (namespace (buff 20)) (name (buff 48)) (salt (buff 20)) (zonefile-hash (buff 20))))",
        "function_args": [
          {
            "hex": "0x0200000003627463",
            "repr": "0x627463",
            "name": "namespace",
            "type": "(buff 20)"
          },
          {
            "hex": "0x020000000661626378797a",
            "repr": "0x61626378797a",
            "name": "name",
            "type": "(buff 48)"
          },
          {
            "hex": "0x020000001444a1c11ed5bf9ffb7ae584a7c8eab6d87c89b131",
            "repr": "0x44a1c11ed5bf9ffb7ae584a7c8eab6d87c89b131",
            "name": "salt",
            "type": "(buff 20)"
          },
          {
            "hex": "0x02000000140cce08270b7c04790ccc50c30e3752012a4881ac",
            "repr": "0x0cce08270b7c04790ccc50c30e3752012a4881ac",
            "name": "zonefile-hash",
            "type": "(buff 20)"
          }
        ]
      }
    },
    {
      "tx_id": "0xbfce10cbeb2e796b5421205c8e8bfa64d75a94c49053b03e71000aaa7771592b",
      "nonce": 7222,
      "fee_rate": "800",
      "sender_address": "SP3G2DMG5WWCP8XF1QZSEQ1XE73X639ABZC835EZV",
      "sponsored": false,
      "post_condition_mode": "deny",
      "post_conditions": [],
      "anchor_mode": "any",
      "is_unanchored": false,
      "block_hash": "0xb287a21633224ad05ea83d769302d794311da3be48a0eb0c616d02059909b645",
      "parent_block_hash": "0x501d2f28cca2e2b01aa3e343c56287abf9b35512b2895397579153c8e3775a28",
      "block_height": 39496,
      "burn_block_time": 1638096211,
      "burn_block_time_iso": "2021-11-28T10:43:31.000Z",
      "parent_burn_block_time": 1638095878,
      "parent_burn_block_time_iso": "2021-11-28T10:37:58.000Z",
      "canonical": true,
      "tx_index": 33,
      "tx_status": "success",
      "tx_result": {
        "hex": "0x0703",
        "repr": "(ok true)"
      },
      "microblock_hash": "",
      "microblock_sequence": 2147483647,
      "microblock_canonical": true,
      "event_count": 1,
      "events": [],
      "execution_cost_read_count": 0,
      "execution_cost_read_length": 0,
      "execution_cost_runtime": 0,
      "execution_cost_write_count": 0,
      "execution_cost_write_length": 0,
      "tx_type": "token_transfer",
      "token_transfer": {
        "recipient_address": "SP16CNZGZ20Y85GMWG01A9GYJ3ZHN4XFQJMSTEG8",
        "amount": "64859916",
        "memo": "0x676f676f000000000000000000000000000000000000000000000000000000000000"
      }
    },
    {
      "tx_id": "0x49ed0b9dc236a0f43b9a668df294a57f7963a901bf245ade8579a7d11ee2540f",
      "nonce": 7223,
      "fee_rate": "800",
      "sender_address": "SP3G2DMG5WWCP8XF1QZSEQ1XE73X639ABZC835EZV",
      "sponsored": false,
      "post_condition_mode": "deny",
      "post_conditions": [],
      "anchor_mode": "any",
      "is_unanchored": false,
      "block_hash": "0xb287a21633224ad05ea83d769302d794311da3be48a0eb0c616d02059909b645",
      "parent_block_hash": "0x501d2f28cca2e2b01aa3e343c56287abf9b35512b2895397579153c8e3775a28",
      "block_height": 39496,
      "burn_block_time": 1638096211,
      "burn_block_time_iso": "2021-11-28T10:43:31.000Z",
      "parent_burn_block_time": 1638095878,
      "parent_burn_block_time_iso": "2021-11-28T10:37:58.000Z",
      "canonical": true,
      "tx_index": 34,
      "tx_status": "success",
      "tx_result": {
        "hex": "0x0703",
        "repr": "(ok true)"
      },
      "microblock_hash": "",
      "microblock_sequence": 2147483647,
      "microblock_canonical": true,
      "event_count": 1,
      "events": [],
      "execution_cost_read_count": 0,
      "execution_cost_read_length": 0,
      "execution_cost_runtime": 0,
      "execution_cost_write_count": 0,
      "execution_cost_write_length": 0,
      "tx_type": "token_transfer",
      "token_transfer": {
        "recipient_address": "SP151ZN8AJVGVJDDTH2WN46RNM4Q0BC175FECQMAG",
        "amount": "90000000",
        "memo": "0x00000000000000000000000000000000000000000000000000000000000000000000"
      }
    },
    {
      "tx_id": "0x76edafe36833c33adbb4b9deea8ab4dd153d881ffe2241e6db8d7e00ad1d8d69",
      "nonce": 211,
      "fee_rate": "7011",
      "sender_address": "SPF4FR0X9Q4PAF6KENDD3NVAGQTM8A830A4F96YG",
      "sponsored": false,
      "post_condition_mode": "deny",
      "post_conditions": [],
      "anchor_mode": "any",
      "is_unanchored": false,
      "block_hash": "0xb287a21633224ad05ea83d769302d794311da3be48a0eb0c616d02059909b645",
      "parent_block_hash": "0x501d2f28cca2e2b01aa3e343c56287abf9b35512b2895397579153c8e3775a28",
      "block_height": 39496,
      "burn_block_time": 1638096211,
      "burn_block_time_iso": "2021-11-28T10:43:31.000Z",
      "parent_burn_block_time": 1638095878,
      "parent_burn_block_time_iso": "2021-11-28T10:37:58.000Z",
      "canonical": true,
      "tx_index": 30,
      "tx_status": "success",
      "tx_result": {
        "hex": "0x0703",
        "repr": "(ok true)"
      },
      "microblock_hash": "",
      "microblock_sequence": 2147483647,
      "microblock_canonical": true,
      "event_count": 1,
      "events": [],
      "execution_cost_read_count": 0,
      "execution_cost_read_length": 0,
      "execution_cost_runtime": 0,
      "execution_cost_write_count": 0,
      "execution_cost_write_length": 0,
      "tx_type": "token_transfer",
      "token_transfer": {
        "recipient_address": "SP65ZMFESJFB9JCBK9ABWS9VZ0R75RBKH41876Q1",
        "amount": "5000000",
        "memo": "0x00000000000000000000000000000000000000000000000000000000000000000000"
      }
    },
    {
      "tx_id": "0x307fea2f2d1f436e4d6b32ec8796bc89a20d57072f280d5a85e497f13198ebf3",
      "nonce": 0,
      "fee_rate": "10250",
      "sender_address": "SP11R9W3GA4760YFTSFWRV3TYGZ55T9A0Q79H1Y7F",
      "sponsored": false,
      "post_condition_mode": "deny",
      "post_conditions": [],
      "anchor_mode": "any",
      "is_unanchored": false,
      "block_hash": "0xb287a21633224ad05ea83d769302d794311da3be48a0eb0c616d02059909b645",
      "parent_block_hash": "0x501d2f28cca2e2b01aa3e343c56287abf9b35512b2895397579153c8e3775a28",
      "block_height": 39496,
      "burn_block_time": 1638096211,
      "burn_block_time_iso": "2021-11-28T10:43:31.000Z",
      "parent_burn_block_time": 1638095878,
      "parent_burn_block_time_iso": "2021-11-28T10:37:58.000Z",
      "canonical": true,
      "tx_index": 31,
      "tx_status": "success",
      "tx_result": {
        "hex": "0x0703",
        "repr": "(ok true)"
      },
      "microblock_hash": "",
      "microblock_sequence": 2147483647,
      "microblock_canonical": true,
      "event_count": 0,
      "events": [],
      "execution_cost_read_count": 4,
      "execution_cost_read_length": 31643,
      "execution_cost_runtime": 32380000,
      "execution_cost_write_count": 1,
      "execution_cost_write_length": 398,
      "tx_type": "contract_call",
      "contract_call": {
        "contract_id": "SP000000000000000000002Q6VF78.pox",
        "function_name": "allow-contract-caller",
        "function_signature": "(define-public (allow-contract-caller (caller principal) (until-burn-ht (optional uint))))",
        "function_args": [
          {
            "hex": "0x06163bbc65d112e79ea9d2001e15f8a615885695d8b60e7876657273652d706f6f6c2d7632",
            "repr": "SPXVRSEH2BKSXAEJ00F1BY562P45D5ERPSKR4Q33.xverse-pool-v2",
            "name": "caller",
            "type": "principal"
          },
          {
            "hex": "0x09",
            "repr": "none",
            "name": "until-burn-ht",
            "type": "(optional uint)"
          }
        ]
      }
    },
    {
      "tx_id": "0x45465d4ad33ea53ea5c357221fb6032f5120050a7da28aa7d0b4ba980e9cfe29",
      "nonce": 44,
      "fee_rate": "750000",
      "sender_address": "SP20376KVG0J5PXF3209FTDDD5NG6PXQETE3G6485",
      "sponsored": false,
      "post_condition_mode": "deny",
      "post_conditions": [
        {
          "type": "non_fungible",
          "condition_code": "sent",
          "principal": {
            "type_id": "principal_standard",
            "address": "SP20376KVG0J5PXF3209FTDDD5NG6PXQETE3G6485"
          },
          "asset": {
            "contract_name": "bitcoin-monkeys",
            "asset_name": "bitcoin-monkeys",
            "contract_address": "SP2KAF9RF86PVX3NEE27DFV1CQX0T4WGR41X3S45C"
          },
          "asset_value": {
            "hex": "0x0100000000000000000000000000000793",
            "repr": "u1939"
          }
        }
      ],
      "anchor_mode": "any",
      "is_unanchored": false,
      "block_hash": "0xb287a21633224ad05ea83d769302d794311da3be48a0eb0c616d02059909b645",
      "parent_block_hash": "0x501d2f28cca2e2b01aa3e343c56287abf9b35512b2895397579153c8e3775a28",
      "block_height": 39496,
      "burn_block_time": 1638096211,
      "burn_block_time_iso": "2021-11-28T10:43:31.000Z",
      "parent_burn_block_time": 1638095878,
      "parent_burn_block_time_iso": "2021-11-28T10:37:58.000Z",
      "canonical": true,
      "tx_index": 2,
      "tx_status": "success",
      "tx_result": {
        "hex": "0x0703",
        "repr": "(ok true)"
      },
      "microblock_hash": "",
      "microblock_sequence": 2147483647,
      "microblock_canonical": true,
      "event_count": 1,
      "events": [],
      "execution_cost_read_count": 17,
      "execution_cost_read_length": 66480,
      "execution_cost_runtime": 70564000,
      "execution_cost_write_count": 2,
      "execution_cost_write_length": 685,
      "tx_type": "contract_call",
      "contract_call": {
        "contract_id": "SPNWZ5V2TPWGQGVDR6T7B6RQ4XMGZ4PXTEE0VQ0S.marketplace-v4",
        "function_name": "list-asset",
        "function_signature": "(define-public (list-asset (tradables trait_reference) (tradable-id uint) (price uint) (commission uint)))",
        "function_args": [
          {
            "hex": "0x0616a6a7a70f41adbe8eae708ed7ec2cbf41a27218200f626974636f696e2d6d6f6e6b657973",
            "repr": "SP2KAF9RF86PVX3NEE27DFV1CQX0T4WGR41X3S45C.bitcoin-monkeys",
            "name": "tradables",
            "type": "trait_reference"
          },
          {
            "hex": "0x0100000000000000000000000000000793",
            "repr": "u1939",
            "name": "tradable-id",
            "type": "uint"
          },
          {
            "hex": "0x010000000000000000000000003b023380",
            "repr": "u990000000",
            "name": "price",
            "type": "uint"
          },
          {
            "hex": "0x0100000000000000000000000000000064",
            "repr": "u100",
            "name": "commission",
            "type": "uint"
          }
        ]
      }
    },
    {
      "tx_id": "0xf766dc43a9c3632c9133bd4b7db3c07f5ec056581ddc20f013d3fe97d8703c04",
      "nonce": 69,
      "fee_rate": "222526",
      "sender_address": "SP37C0G2ENY48WEMRTAG3NGYY0NRXN9YCWKD2J5ZK",
      "sponsored": false,
      "post_condition_mode": "deny",
      "post_conditions": [
        {
          "type": "non_fungible",
          "condition_code": "sent",
          "principal": {
            "type_id": "principal_contract",
            "contract_name": "stacks-art-market-v2",
            "address": "SPJW1XE278YMCEYMXB8ZFGJMH8ZVAAEDP2S2PJYG"
          },
          "asset": {
            "contract_name": "megapont-ape-club-nft",
            "asset_name": "Megapont-Ape-Club",
            "contract_address": "SP3D6PV2ACBPEKYJTCMH7HEN02KP87QSP8KTEH335"
          },
          "asset_value": {
            "hex": "0x0100000000000000000000000000000564",
            "repr": "u1380"
          }
        }
      ],
      "anchor_mode": "any",
      "is_unanchored": false,
      "block_hash": "0xb287a21633224ad05ea83d769302d794311da3be48a0eb0c616d02059909b645",
      "parent_block_hash": "0x501d2f28cca2e2b01aa3e343c56287abf9b35512b2895397579153c8e3775a28",
      "block_height": 39496,
      "burn_block_time": 1638096211,
      "burn_block_time_iso": "2021-11-28T10:43:31.000Z",
      "parent_burn_block_time": 1638095878,
      "parent_burn_block_time_iso": "2021-11-28T10:37:58.000Z",
      "canonical": true,
      "tx_index": 3,
      "tx_status": "success",
      "tx_result": {
        "hex": "0x0703",
        "repr": "(ok true)"
      },
      "microblock_hash": "",
      "microblock_sequence": 2147483647,
      "microblock_canonical": true,
      "event_count": 2,
      "events": [],
      "execution_cost_read_count": 16,
      "execution_cost_read_length": 23777,
      "execution_cost_runtime": 29977000,
      "execution_cost_write_count": 4,
      "execution_cost_write_length": 414,
      "tx_type": "contract_call",
      "contract_call": {
        "contract_id": "SPJW1XE278YMCEYMXB8ZFGJMH8ZVAAEDP2S2PJYG.stacks-art-market-v2",
        "function_name": "unlist-item",
        "function_signature": "(define-public (unlist-item (collection trait_reference) (collection-id uint) (item-id uint)))",
        "function_args": [
          {
            "hex": "0x0616da6b6c4a62ece9fa5a652278baa014ec83df3644156d656761706f6e742d6170652d636c75622d6e6674",
            "repr": "SP3D6PV2ACBPEKYJTCMH7HEN02KP87QSP8KTEH335.megapont-ape-club-nft",
            "name": "collection",
            "type": "trait_reference"
          },
          {
            "hex": "0x010000000000000000000000000000000f",
            "repr": "u15",
            "name": "collection-id",
            "type": "uint"
          },
          {
            "hex": "0x0100000000000000000000000000000564",
            "repr": "u1380",
            "name": "item-id",
            "type": "uint"
          }
        ]
      }
    },
    {
      "tx_id": "0xbc45062f9e14a9e0cac1f9c2ac966857374ee998886a4c1a2f31c94d1e96008c",
      "nonce": 147,
      "fee_rate": "98157",
      "sender_address": "SP1PMVM8V5ZE4E8CYY9D5Z9X4JWWMFR5MPGE32ECT",
      "sponsored": false,
      "post_condition_mode": "allow",
      "post_conditions": [],
      "anchor_mode": "any",
      "is_unanchored": false,
      "block_hash": "0xb287a21633224ad05ea83d769302d794311da3be48a0eb0c616d02059909b645",
      "parent_block_hash": "0x501d2f28cca2e2b01aa3e343c56287abf9b35512b2895397579153c8e3775a28",
      "block_height": 39496,
      "burn_block_time": 1638096211,
      "burn_block_time_iso": "2021-11-28T10:43:31.000Z",
      "parent_burn_block_time": 1638095878,
      "parent_burn_block_time_iso": "2021-11-28T10:37:58.000Z",
      "canonical": true,
      "tx_index": 4,
      "tx_status": "success",
      "tx_result": {
        "hex": "0x070b000000020100000000000000000000000035a4e9000100000000000000000000000066d370b2",
        "repr": "(ok (list u900000000 u1725132978))"
      },
      "microblock_hash": "",
      "microblock_sequence": 2147483647,
      "microblock_canonical": true,
      "event_count": 8,
      "events": [],
      "execution_cost_read_count": 30,
      "execution_cost_read_length": 58490,
      "execution_cost_runtime": 71269000,
      "execution_cost_write_count": 8,
      "execution_cost_write_length": 985,
      "tx_type": "contract_call",
      "contract_call": {
        "contract_id": "SP2C2YFP12AJZB4MABJBAJ55XECVS7E4PMMZ89YZR.arkadiko-swap-v2-1",
        "function_name": "swap-x-for-y",
        "function_signature": "(define-public (swap-x-for-y (token-x-trait trait_reference) (token-y-trait trait_reference) (dx uint) (min-dy uint)))",
        "function_args": [
          {
            "hex": "0x0616982f3ec112a5f5928a5c96a914bd733793b896a511777261707065642d7374782d746f6b656e",
            "repr": "SP2C2YFP12AJZB4MABJBAJ55XECVS7E4PMMZ89YZR.wrapped-stx-token",
            "name": "token-x-trait",
            "type": "trait_reference"
          },
          {
            "hex": "0x0616982f3ec112a5f5928a5c96a914bd733793b896a50a757364612d746f6b656e",
            "repr": "SP2C2YFP12AJZB4MABJBAJ55XECVS7E4PMMZ89YZR.usda-token",
            "name": "token-y-trait",
            "type": "trait_reference"
          },
          {
            "hex": "0x0100000000000000000000000035a4e900",
            "repr": "u900000000",
            "name": "dx",
            "type": "uint"
          },
          {
            "hex": "0x0100000000000000000000000063137dbd",
            "repr": "u1662221757",
            "name": "min-dy",
            "type": "uint"
          }
        ]
      }
    },
    {
      "tx_id": "0xb10c7e8626154c2b8e235ab6140443404d61352a64a5b94ea50fce2be88dd1d3",
      "nonce": 204,
      "fee_rate": "438267",
      "sender_address": "SP2HSFTNTARNXD6Y0X6A3BYFS9D072Z2VAJND5GZQ",
      "sponsored": false,
      "post_condition_mode": "deny",
      "post_conditions": [],
      "anchor_mode": "any",
      "is_unanchored": false,
      "block_hash": "0xb287a21633224ad05ea83d769302d794311da3be48a0eb0c616d02059909b645",
      "parent_block_hash": "0x501d2f28cca2e2b01aa3e343c56287abf9b35512b2895397579153c8e3775a28",
      "block_height": 39496,
      "burn_block_time": 1638096211,
      "burn_block_time_iso": "2021-11-28T10:43:31.000Z",
      "parent_burn_block_time": 1638095878,
      "parent_burn_block_time_iso": "2021-11-28T10:37:58.000Z",
      "canonical": true,
      "tx_index": 5,
      "tx_status": "success",
      "tx_result": {
        "hex": "0x0701000000000000000000000000086bcc91",
        "repr": "(ok u141282449)"
      },
      "microblock_hash": "",
      "microblock_sequence": 2147483647,
      "microblock_canonical": true,
      "event_count": 2,
      "events": [],
      "execution_cost_read_count": 78,
      "execution_cost_read_length": 117598,
      "execution_cost_runtime": 133658000,
      "execution_cost_write_count": 5,
      "execution_cost_write_length": 299,
      "tx_type": "contract_call",
      "contract_call": {
        "contract_id": "SP2C2YFP12AJZB4MABJBAJ55XECVS7E4PMMZ89YZR.arkadiko-stake-registry-v1-1",
        "function_name": "claim-pending-rewards",
        "function_signature": "(define-public (claim-pending-rewards (registry-trait trait_reference) (pool-trait trait_reference)))",
        "function_args": [
          {
            "hex": "0x0616982f3ec112a5f5928a5c96a914bd733793b896a51c61726b6164696b6f2d7374616b652d72656769737472792d76312d31",
            "repr": "SP2C2YFP12AJZB4MABJBAJ55XECVS7E4PMMZ89YZR.arkadiko-stake-registry-v1-1",
            "name": "registry-trait",
            "type": "trait_reference"
          },
          {
            "hex": "0x0616982f3ec112a5f5928a5c96a914bd733793b896a52261726b6164696b6f2d7374616b652d706f6f6c2d64696b6f2d757364612d76312d31",
            "repr": "SP2C2YFP12AJZB4MABJBAJ55XECVS7E4PMMZ89YZR.arkadiko-stake-pool-diko-usda-v1-1",
            "name": "pool-trait",
            "type": "trait_reference"
          }
        ]
      }
    },
    {
      "tx_id": "0x9f032d191e58c58da2b2a7294f17e583f464a795e5d3a2b0d29a04b3187ec053",
      "nonce": 682,
      "fee_rate": "62078",
      "sender_address": "SP0DTXG873BDXEX7FWGWV586DF0G8SVF4TTB2829",
      "sponsored": false,
      "post_condition_mode": "deny",
      "post_conditions": [
        {
          "type": "fungible",
          "condition_code": "sent_equal_to",
          "amount": "60000000",
          "principal": {
            "type_id": "principal_standard",
            "address": "SP0DTXG873BDXEX7FWGWV586DF0G8SVF4TTB2829"
          },
          "asset": {
            "contract_name": "arkadiko-swap-token-wstx-diko",
            "asset_name": "wstx-diko",
            "contract_address": "SP2C2YFP12AJZB4MABJBAJ55XECVS7E4PMMZ89YZR"
          }
        }
      ],
      "anchor_mode": "any",
      "is_unanchored": false,
      "block_hash": "0xb287a21633224ad05ea83d769302d794311da3be48a0eb0c616d02059909b645",
      "parent_block_hash": "0x501d2f28cca2e2b01aa3e343c56287abf9b35512b2895397579153c8e3775a28",
      "block_height": 39496,
      "burn_block_time": 1638096211,
      "burn_block_time_iso": "2021-11-28T10:43:31.000Z",
      "parent_burn_block_time": 1638095878,
      "parent_burn_block_time_iso": "2021-11-28T10:37:58.000Z",
      "canonical": true,
      "tx_index": 6,
      "tx_status": "abort_by_post_condition",
      "tx_result": {
        "hex": "0x080100000000000000000000000000000001",
        "repr": "(err u1)"
      },
      "microblock_hash": "",
      "microblock_sequence": 2147483647,
      "microblock_canonical": true,
      "event_count": 0,
      "events": [],
      "execution_cost_read_count": 153,
      "execution_cost_read_length": 224734,
      "execution_cost_runtime": 257049000,
      "execution_cost_write_count": 8,
      "execution_cost_write_length": 317,
      "tx_type": "contract_call",
      "contract_call": {
        "contract_id": "SP2C2YFP12AJZB4MABJBAJ55XECVS7E4PMMZ89YZR.arkadiko-stake-registry-v1-1",
        "function_name": "stake",
        "function_signature": "(define-public (stake (registry-trait trait_reference) (pool-trait trait_reference) (token-trait trait_reference) (amount uint)))",
        "function_args": [
          {
            "hex": "0x0616982f3ec112a5f5928a5c96a914bd733793b896a51c61726b6164696b6f2d7374616b652d72656769737472792d76312d31",
            "repr": "SP2C2YFP12AJZB4MABJBAJ55XECVS7E4PMMZ89YZR.arkadiko-stake-registry-v1-1",
            "name": "registry-trait",
            "type": "trait_reference"
          },
          {
            "hex": "0x0616982f3ec112a5f5928a5c96a914bd733793b896a52261726b6164696b6f2d7374616b652d706f6f6c2d777374782d64696b6f2d76312d31",
            "repr": "SP2C2YFP12AJZB4MABJBAJ55XECVS7E4PMMZ89YZR.arkadiko-stake-pool-wstx-diko-v1-1",
            "name": "pool-trait",
            "type": "trait_reference"
          },
          {
            "hex": "0x0616982f3ec112a5f5928a5c96a914bd733793b896a51d61726b6164696b6f2d737761702d746f6b656e2d777374782d64696b6f",
            "repr": "SP2C2YFP12AJZB4MABJBAJ55XECVS7E4PMMZ89YZR.arkadiko-swap-token-wstx-diko",
            "name": "token-trait",
            "type": "trait_reference"
          },
          {
            "hex": "0x0100000000000000000000000003938700",
            "repr": "u60000000",
            "name": "amount",
            "type": "uint"
          }
        ]
      }
    },
    {
      "tx_id": "0x4f6424538d4b8d81c4121fa0fccd394e7b05165855c60c9e2869cdf31a85ac58",
      "nonce": 100,
      "fee_rate": "750000",
      "sender_address": "SP0ESHJJ1FA7KBJ26SE4Z5W4TQR2BWPDX8PX72GK",
      "sponsored": false,
      "post_condition_mode": "deny",
      "post_conditions": [
        {
          "type": "non_fungible",
          "condition_code": "sent",
          "principal": {
            "type_id": "principal_contract",
            "contract_name": "stacks-art-market-v2",
            "address": "SPJW1XE278YMCEYMXB8ZFGJMH8ZVAAEDP2S2PJYG"
          },
          "asset": {
            "contract_name": "byte-fighters",
            "asset_name": "byte-fighters",
            "contract_address": "SPJW1XE278YMCEYMXB8ZFGJMH8ZVAAEDP2S2PJYG"
          },
          "asset_value": {
            "hex": "0x0100000000000000000000000000000198",
            "repr": "u408"
          }
        }
      ],
      "anchor_mode": "any",
      "is_unanchored": false,
      "block_hash": "0xb287a21633224ad05ea83d769302d794311da3be48a0eb0c616d02059909b645",
      "parent_block_hash": "0x501d2f28cca2e2b01aa3e343c56287abf9b35512b2895397579153c8e3775a28",
      "block_height": 39496,
      "burn_block_time": 1638096211,
      "burn_block_time_iso": "2021-11-28T10:43:31.000Z",
      "parent_burn_block_time": 1638095878,
      "parent_burn_block_time_iso": "2021-11-28T10:37:58.000Z",
      "canonical": true,
      "tx_index": 7,
      "tx_status": "success",
      "tx_result": {
        "hex": "0x0703",
        "repr": "(ok true)"
      },
      "microblock_hash": "",
      "microblock_sequence": 2147483647,
      "microblock_canonical": true,
      "event_count": 2,
      "events": [],
      "execution_cost_read_count": 223,
      "execution_cost_read_length": 105610,
      "execution_cost_runtime": 281791000,
      "execution_cost_write_count": 5,
      "execution_cost_write_length": 80473,
      "tx_type": "contract_call",
      "contract_call": {
        "contract_id": "SPJW1XE278YMCEYMXB8ZFGJMH8ZVAAEDP2S2PJYG.stacks-art-market-v2",
        "function_name": "unlist-item",
        "function_signature": "(define-public (unlist-item (collection trait_reference) (collection-id uint) (item-id uint)))",
        "function_args": [
          {
            "hex": "0x061625c0f5c23a3d463bd4ead1f7c2548a3fb529cdb00d627974652d6669676874657273",
            "repr": "SPJW1XE278YMCEYMXB8ZFGJMH8ZVAAEDP2S2PJYG.byte-fighters",
            "name": "collection",
            "type": "trait_reference"
          },
          {
            "hex": "0x0100000000000000000000000000000006",
            "repr": "u6",
            "name": "collection-id",
            "type": "uint"
          },
          {
            "hex": "0x0100000000000000000000000000000198",
            "repr": "u408",
            "name": "item-id",
            "type": "uint"
          }
        ]
      }
    },
    {
      "tx_id": "0x9daeced7657bf276db27e74634de4c334f006f9e9b43a2401eea73cc65d121b4",
      "nonce": 9,
      "fee_rate": "96993",
      "sender_address": "SP17R09N2GTQ7ZY0113BPD23ANHBG530J9ZW2GDG2",
      "sponsored": false,
      "post_condition_mode": "deny",
      "post_conditions": [
        {
          "type": "stx",
          "condition_code": "sent_less_than_or_equal_to",
          "amount": "45000000",
          "principal": {
            "type_id": "principal_standard",
            "address": "SP17R09N2GTQ7ZY0113BPD23ANHBG530J9ZW2GDG2"
          }
        },
        {
          "type": "stx",
          "condition_code": "sent_less_than_or_equal_to",
          "amount": "45000000",
          "principal": {
            "type_id": "principal_contract",
            "contract_name": "bitcoin-monkeys",
            "address": "SP2KAF9RF86PVX3NEE27DFV1CQX0T4WGR41X3S45C"
          }
        }
      ],
      "anchor_mode": "any",
      "is_unanchored": false,
      "block_hash": "0xb287a21633224ad05ea83d769302d794311da3be48a0eb0c616d02059909b645",
      "parent_block_hash": "0x501d2f28cca2e2b01aa3e343c56287abf9b35512b2895397579153c8e3775a28",
      "block_height": 39496,
      "burn_block_time": 1638096211,
      "burn_block_time_iso": "2021-11-28T10:43:31.000Z",
      "parent_burn_block_time": 1638095878,
      "parent_burn_block_time_iso": "2021-11-28T10:37:58.000Z",
      "canonical": true,
      "tx_index": 8,
      "tx_status": "success",
      "tx_result": {
        "hex": "0x0701000000000000000000000000000007e1",
        "repr": "(ok u2017)"
      },
      "microblock_hash": "",
      "microblock_sequence": 2147483647,
      "microblock_canonical": true,
      "event_count": 5,
      "events": [],
      "execution_cost_read_count": 24,
      "execution_cost_read_length": 20432,
      "execution_cost_runtime": 21127000,
      "execution_cost_write_count": 6,
      "execution_cost_write_length": 22,
      "tx_type": "contract_call",
      "contract_call": {
        "contract_id": "SP2KAF9RF86PVX3NEE27DFV1CQX0T4WGR41X3S45C.bitcoin-monkeys",
        "function_name": "claim",
        "function_signature": "(define-public (claim ))"
      }
    },
    {
      "tx_id": "0xea25b4d5ba4842b7bf284650b3fe548383cc7d8535950d3d7695fe2715056d34",
      "nonce": 91,
      "fee_rate": "100000",
      "sender_address": "SP3Z0BHS0SVP5733GDZ2RWJV1G2EW04PFN2NSX3PK",
      "sponsored": false,
      "post_condition_mode": "deny",
      "post_conditions": [
        {
          "type": "stx",
          "condition_code": "sent_less_than_or_equal_to",
          "amount": "45000000",
          "principal": {
            "type_id": "principal_standard",
            "address": "SP3Z0BHS0SVP5733GDZ2RWJV1G2EW04PFN2NSX3PK"
          }
        },
        {
          "type": "stx",
          "condition_code": "sent_less_than_or_equal_to",
          "amount": "45000000",
          "principal": {
            "type_id": "principal_contract",
            "contract_name": "bitcoin-monkeys",
            "address": "SP2KAF9RF86PVX3NEE27DFV1CQX0T4WGR41X3S45C"
          }
        }
      ],
      "anchor_mode": "any",
      "is_unanchored": false,
      "block_hash": "0xb287a21633224ad05ea83d769302d794311da3be48a0eb0c616d02059909b645",
      "parent_block_hash": "0x501d2f28cca2e2b01aa3e343c56287abf9b35512b2895397579153c8e3775a28",
      "block_height": 39496,
      "burn_block_time": 1638096211,
      "burn_block_time_iso": "2021-11-28T10:43:31.000Z",
      "parent_burn_block_time": 1638095878,
      "parent_burn_block_time_iso": "2021-11-28T10:37:58.000Z",
      "canonical": true,
      "tx_index": 9,
      "tx_status": "success",
      "tx_result": {
        "hex": "0x0701000000000000000000000000000007e2",
        "repr": "(ok u2018)"
      },
      "microblock_hash": "",
      "microblock_sequence": 2147483647,
      "microblock_canonical": true,
      "event_count": 5,
      "events": [],
      "execution_cost_read_count": 24,
      "execution_cost_read_length": 20432,
      "execution_cost_runtime": 21127000,
      "execution_cost_write_count": 6,
      "execution_cost_write_length": 22,
      "tx_type": "contract_call",
      "contract_call": {
        "contract_id": "SP2KAF9RF86PVX3NEE27DFV1CQX0T4WGR41X3S45C.bitcoin-monkeys",
        "function_name": "claim",
        "function_signature": "(define-public (claim ))"
      }
    },
    {
      "tx_id": "0x7be7dc7c49f53cce2fce0489e9da2fb9e60112808ae7ae86e1e056e63a13d31d",
      "nonce": 1379,
      "fee_rate": "100000",
      "sender_address": "SP3DW8X8CBPSYWT327120KE5N8DEJTTBMYJ2QH68Y",
      "sponsored": false,
      "post_condition_mode": "deny",
      "post_conditions": [],
      "anchor_mode": "any",
      "is_unanchored": false,
      "block_hash": "0xb287a21633224ad05ea83d769302d794311da3be48a0eb0c616d02059909b645",
      "parent_block_hash": "0x501d2f28cca2e2b01aa3e343c56287abf9b35512b2895397579153c8e3775a28",
      "block_height": 39496,
      "burn_block_time": 1638096211,
      "burn_block_time_iso": "2021-11-28T10:43:31.000Z",
      "parent_burn_block_time": 1638095878,
      "parent_burn_block_time_iso": "2021-11-28T10:37:58.000Z",
      "canonical": true,
      "tx_index": 29,
      "tx_status": "success",
      "tx_result": {
        "hex": "0x0703",
        "repr": "(ok true)"
      },
      "microblock_hash": "",
      "microblock_sequence": 2147483647,
      "microblock_canonical": true,
      "event_count": 1,
      "events": [],
      "execution_cost_read_count": 0,
      "execution_cost_read_length": 0,
      "execution_cost_runtime": 0,
      "execution_cost_write_count": 0,
      "execution_cost_write_length": 0,
      "tx_type": "token_transfer",
      "token_transfer": {
        "recipient_address": "SP3Z0BHS0SVP5733GDZ2RWJV1G2EW04PFN2NSX3PK",
        "amount": "105944000",
        "memo": "0x30303000000000000000000000000000000000000000000000000000000000000000"
      }
    },
    {
      "tx_id": "0xdd3373873483a0b7a5205ac0d1223e9054b98ba449c470d7b2699e72f76a3834",
      "nonce": 72,
      "fee_rate": "284987",
      "sender_address": "SP2T4SJRBCF63HJVZBMXEK1SZTGKHY4NZSXE3TF9Y",
      "sponsored": false,
      "post_condition_mode": "allow",
      "post_conditions": [],
      "anchor_mode": "any",
      "is_unanchored": false,
      "block_hash": "0xb287a21633224ad05ea83d769302d794311da3be48a0eb0c616d02059909b645",
      "parent_block_hash": "0x501d2f28cca2e2b01aa3e343c56287abf9b35512b2895397579153c8e3775a28",
      "block_height": 39496,
      "burn_block_time": 1638096211,
      "burn_block_time_iso": "2021-11-28T10:43:31.000Z",
      "parent_burn_block_time": 1638095878,
      "parent_burn_block_time_iso": "2021-11-28T10:37:58.000Z",
      "canonical": true,
      "tx_index": 10,
      "tx_status": "success",
      "tx_result": {
        "hex": "0x0703",
        "repr": "(ok true)"
      },
      "microblock_hash": "",
      "microblock_sequence": 2147483647,
      "microblock_canonical": true,
      "event_count": 12,
      "events": [],
      "execution_cost_read_count": 39,
      "execution_cost_read_length": 74020,
      "execution_cost_runtime": 89815000,
      "execution_cost_write_count": 10,
      "execution_cost_write_length": 986,
      "tx_type": "contract_call",
      "contract_call": {
        "contract_id": "SP2C2YFP12AJZB4MABJBAJ55XECVS7E4PMMZ89YZR.arkadiko-swap-v2-1",
        "function_name": "add-to-position",
        "function_signature": "(define-public (add-to-position (token-x-trait trait_reference) (token-y-trait trait_reference) (swap-token-trait trait_reference) (x uint) (y uint)))",
        "function_args": [
          {
            "hex": "0x0616982f3ec112a5f5928a5c96a914bd733793b896a511777261707065642d7374782d746f6b656e",
            "repr": "SP2C2YFP12AJZB4MABJBAJ55XECVS7E4PMMZ89YZR.wrapped-stx-token",
            "name": "token-x-trait",
            "type": "trait_reference"
          },
          {
            "hex": "0x0616982f3ec112a5f5928a5c96a914bd733793b896a50a757364612d746f6b656e",
            "repr": "SP2C2YFP12AJZB4MABJBAJ55XECVS7E4PMMZ89YZR.usda-token",
            "name": "token-y-trait",
            "type": "trait_reference"
          },
          {
            "hex": "0x0616982f3ec112a5f5928a5c96a914bd733793b896a51d61726b6164696b6f2d737761702d746f6b656e2d777374782d75736461",
            "repr": "SP2C2YFP12AJZB4MABJBAJ55XECVS7E4PMMZ89YZR.arkadiko-swap-token-wstx-usda",
            "name": "swap-token-trait",
            "type": "trait_reference"
          },
          {
            "hex": "0x010000000000000000000000000bebc200",
            "repr": "u200000000",
            "name": "x",
            "type": "uint"
          },
          {
            "hex": "0x010000000000000000000000001701e480",
            "repr": "u386000000",
            "name": "y",
            "type": "uint"
          }
        ]
      }
    },
    {
      "tx_id": "0x33e3e066627824935fbb941bc799458e3295db311f45e65ae96dcba56cf49447",
      "nonce": 137,
      "fee_rate": "150000",
      "sender_address": "SPJW1XE278YMCEYMXB8ZFGJMH8ZVAAEDP2S2PJYG",
      "sponsored": false,
      "post_condition_mode": "allow",
      "post_conditions": [],
      "anchor_mode": "any",
      "is_unanchored": false,
      "block_hash": "0xb287a21633224ad05ea83d769302d794311da3be48a0eb0c616d02059909b645",
      "parent_block_hash": "0x501d2f28cca2e2b01aa3e343c56287abf9b35512b2895397579153c8e3775a28",
      "block_height": 39496,
      "burn_block_time": 1638096211,
      "burn_block_time_iso": "2021-11-28T10:43:31.000Z",
      "parent_burn_block_time": 1638095878,
      "parent_burn_block_time_iso": "2021-11-28T10:37:58.000Z",
      "canonical": true,
      "tx_index": 11,
      "tx_status": "success",
      "tx_result": {
        "hex": "0x070100000000000000000000000000000002",
        "repr": "(ok u2)"
      },
      "microblock_hash": "",
      "microblock_sequence": 2147483647,
      "microblock_canonical": true,
      "event_count": 1,
      "events": [],
      "execution_cost_read_count": 11,
      "execution_cost_read_length": 10814,
      "execution_cost_runtime": 18390000,
      "execution_cost_write_count": 4,
      "execution_cost_write_length": 2334,
      "tx_type": "contract_call",
      "contract_call": {
        "contract_id": "SPJW1XE278YMCEYMXB8ZFGJMH8ZVAAEDP2S2PJYG.stacks-art-nft",
        "function_name": "mint",
        "function_signature": "(define-public (mint (amount uint) (series-index uint) (creator principal) (name (string-utf8 256)) (image (string-ascii 256)) (uri (string-ascii 256)) (mime-type (string-ascii 256)) (hash (buff 64)) (frozen bool)))",
        "function_args": [
          {
            "hex": "0x0100000000000000000000000000000001",
            "repr": "u1",
            "name": "amount",
            "type": "uint"
          },
          {
            "hex": "0x0100000000000000000000000000000000",
            "repr": "u0",
            "name": "series-index",
            "type": "uint"
          },
          {
            "hex": "0x051625c0f5c23a3d463bd4ead1f7c2548a3fb529cdb0",
            "repr": "SPJW1XE278YMCEYMXB8ZFGJMH8ZVAAEDP2S2PJYG",
            "name": "creator",
            "type": "principal"
          },
          {
            "hex": "0x0e0000000b54696d6520576173746564",
            "repr": "u\"Time Wasted\"",
            "name": "name",
            "type": "(string-utf8 256)"
          },
          {
            "hex": "0x0d00000035697066733a2f2f516d56777634487171354b4b4845694e626341554c5468384833416a4873375162533168786d5a74706448375546",
            "repr": "\"ipfs://QmVwv4Hqq5KKHEiNbcAULTh8H3AjHs7QbS1hxmZtpdH7UF\"",
            "name": "image",
            "type": "(string-ascii 256)"
          },
          {
            "hex": "0x0d00000035697066733a2f2f516d574c69634a357a4641784b36376464636239563341706e7038713131786b737a71363550394e524261386b4b",
            "repr": "\"ipfs://QmWLicJ5zFAxK67ddcb9V3Apnp8q11xkszq65P9NRBa8kK\"",
            "name": "uri",
            "type": "(string-ascii 256)"
          },
          {
            "hex": "0x0d00000009617564696f2f6d7033",
            "repr": "\"audio/mp3\"",
            "name": "mime-type",
            "type": "(string-ascii 256)"
          },
          {
            "hex": "0x020000004062643061623237633265623363666433623561333039376264326562356238653261396434393961643832613632323165303562643230633236356432313737",
            "repr": "0x62643061623237633265623363666433623561333039376264326562356238653261396434393961643832613632323165303562643230633236356432313737",
            "name": "hash",
            "type": "(buff 64)"
          },
          {
            "hex": "0x04",
            "repr": "false",
            "name": "frozen",
            "type": "bool"
          }
        ]
      }
    },
    {
      "tx_id": "0x810f6e94435b7bca890d41ff240d0bfa51b98526565a7eba6ea4b898b937ad05",
      "nonce": 66,
      "fee_rate": "250000",
      "sender_address": "SP16WBJNJ26EVFX8C1Q17SK1ZZ2SFEK04426489JW",
      "sponsored": false,
      "post_condition_mode": "deny",
      "post_conditions": [],
      "anchor_mode": "any",
      "is_unanchored": false,
      "block_hash": "0xb287a21633224ad05ea83d769302d794311da3be48a0eb0c616d02059909b645",
      "parent_block_hash": "0x501d2f28cca2e2b01aa3e343c56287abf9b35512b2895397579153c8e3775a28",
      "block_height": 39496,
      "burn_block_time": 1638096211,
      "burn_block_time_iso": "2021-11-28T10:43:31.000Z",
      "parent_burn_block_time": 1638095878,
      "parent_burn_block_time_iso": "2021-11-28T10:37:58.000Z",
      "canonical": true,
      "tx_index": 12,
      "tx_status": "success",
      "tx_result": {
        "hex": "0x070100000000000000000000000000fc49f0",
        "repr": "(ok u16534000)"
      },
      "microblock_hash": "",
      "microblock_sequence": 2147483647,
      "microblock_canonical": true,
      "event_count": 2,
      "events": [],
      "execution_cost_read_count": 46,
      "execution_cost_read_length": 32310,
      "execution_cost_runtime": 37880000,
      "execution_cost_write_count": 5,
      "execution_cost_write_length": 311,
      "tx_type": "contract_call",
      "contract_call": {
        "contract_id": "SP2C2YFP12AJZB4MABJBAJ55XECVS7E4PMMZ89YZR.arkadiko-vault-rewards-v1-1",
        "function_name": "claim-pending-rewards",
        "function_signature": "(define-public (claim-pending-rewards ))"
      }
    },
    {
      "tx_id": "0xc445d567e1d9a0c5f6e1765dd13db41f2fa8c0858d05b82aad8725c1606ea270",
      "nonce": 298,
      "fee_rate": "200000",
      "sender_address": "SPPKV3KBDQRZ6JJK2VWB2JKTXHVYF40J253TY20B",
      "sponsored": false,
      "post_condition_mode": "deny",
      "post_conditions": [
        {
          "type": "non_fungible",
          "condition_code": "sent",
          "principal": {
            "type_id": "principal_standard",
            "address": "SPPKV3KBDQRZ6JJK2VWB2JKTXHVYF40J253TY20B"
          },
          "asset": {
            "contract_name": "funky-donuts",
            "asset_name": "funky-donuts",
            "contract_address": "SPJW1XE278YMCEYMXB8ZFGJMH8ZVAAEDP2S2PJYG"
          },
          "asset_value": {
            "hex": "0x01000000000000000000000000000004de",
            "repr": "u1246"
          }
        }
      ],
      "anchor_mode": "any",
      "is_unanchored": false,
      "block_hash": "0xb287a21633224ad05ea83d769302d794311da3be48a0eb0c616d02059909b645",
      "parent_block_hash": "0x501d2f28cca2e2b01aa3e343c56287abf9b35512b2895397579153c8e3775a28",
      "block_height": 39496,
      "burn_block_time": 1638096211,
      "burn_block_time_iso": "2021-11-28T10:43:31.000Z",
      "parent_burn_block_time": 1638095878,
      "parent_burn_block_time_iso": "2021-11-28T10:37:58.000Z",
      "canonical": true,
      "tx_index": 13,
      "tx_status": "success",
      "tx_result": {
        "hex": "0x0703",
        "repr": "(ok true)"
      },
      "microblock_hash": "",
      "microblock_sequence": 2147483647,
      "microblock_canonical": true,
      "event_count": 2,
      "events": [],
      "execution_cost_read_count": 16,
      "execution_cost_read_length": 24220,
      "execution_cost_runtime": 28459000,
      "execution_cost_write_count": 3,
      "execution_cost_write_length": 365,
      "tx_type": "contract_call",
      "contract_call": {
        "contract_id": "SPJW1XE278YMCEYMXB8ZFGJMH8ZVAAEDP2S2PJYG.stacks-art-market-v2",
        "function_name": "list-item",
        "function_signature": "(define-public (list-item (collection trait_reference) (collection-id uint) (item-id uint) (price uint)))",
        "function_args": [
          {
            "hex": "0x061625c0f5c23a3d463bd4ead1f7c2548a3fb529cdb00c66756e6b792d646f6e757473",
            "repr": "SPJW1XE278YMCEYMXB8ZFGJMH8ZVAAEDP2S2PJYG.funky-donuts",
            "name": "collection",
            "type": "trait_reference"
          },
          {
            "hex": "0x010000000000000000000000000000000b",
            "repr": "u11",
            "name": "collection-id",
            "type": "uint"
          },
          {
            "hex": "0x01000000000000000000000000000004de",
            "repr": "u1246",
            "name": "item-id",
            "type": "uint"
          },
          {
            "hex": "0x0100000000000000000000000001c6b640",
            "repr": "u29800000",
            "name": "price",
            "type": "uint"
          }
        ]
      }
    },
    {
      "tx_id": "0xf88dd26f9662d2bb7b55e22f83cead50c66573bd3bad8bee3d03d42f4c8baf2b",
      "nonce": 875,
      "fee_rate": "200000",
      "sender_address": "SP23GTEC9CSBCGX9308TXXR2DMD7QA3HDHJHFPXKW",
      "sponsored": false,
      "post_condition_mode": "deny",
      "post_conditions": [
        {
          "type": "non_fungible",
          "condition_code": "sent",
          "principal": {
            "type_id": "principal_standard",
            "address": "SP23GTEC9CSBCGX9308TXXR2DMD7QA3HDHJHFPXKW"
          },
          "asset": {
            "contract_name": "byzantion-matryoshka-dolls",
            "asset_name": "matryoshka-dolls",
            "contract_address": "SP2KAF9RF86PVX3NEE27DFV1CQX0T4WGR41X3S45C"
          },
          "asset_value": {
            "hex": "0x01000000000000000000000000000000cc",
            "repr": "u204"
          }
        }
      ],
      "anchor_mode": "any",
      "is_unanchored": false,
      "block_hash": "0xb287a21633224ad05ea83d769302d794311da3be48a0eb0c616d02059909b645",
      "parent_block_hash": "0x501d2f28cca2e2b01aa3e343c56287abf9b35512b2895397579153c8e3775a28",
      "block_height": 39496,
      "burn_block_time": 1638096211,
      "burn_block_time_iso": "2021-11-28T10:43:31.000Z",
      "parent_burn_block_time": 1638095878,
      "parent_burn_block_time_iso": "2021-11-28T10:37:58.000Z",
      "canonical": true,
      "tx_index": 14,
      "tx_status": "success",
      "tx_result": {
        "hex": "0x0703",
        "repr": "(ok true)"
      },
      "microblock_hash": "",
      "microblock_sequence": 2147483647,
      "microblock_canonical": true,
      "event_count": 1,
      "events": [],
      "execution_cost_read_count": 17,
      "execution_cost_read_length": 33270,
      "execution_cost_runtime": 37354000,
      "execution_cost_write_count": 2,
      "execution_cost_write_length": 685,
      "tx_type": "contract_call",
      "contract_call": {
        "contract_id": "SPNWZ5V2TPWGQGVDR6T7B6RQ4XMGZ4PXTEE0VQ0S.marketplace-v4",
        "function_name": "list-asset",
        "function_signature": "(define-public (list-asset (tradables trait_reference) (tradable-id uint) (price uint) (commission uint)))",
        "function_args": [
          {
            "hex": "0x0616a6a7a70f41adbe8eae708ed7ec2cbf41a27218201a62797a616e74696f6e2d6d617472796f73686b612d646f6c6c73",
            "repr": "SP2KAF9RF86PVX3NEE27DFV1CQX0T4WGR41X3S45C.byzantion-matryoshka-dolls",
            "name": "tradables",
            "type": "trait_reference"
          },
          {
            "hex": "0x01000000000000000000000000000000cc",
            "repr": "u204",
            "name": "tradable-id",
            "type": "uint"
          },
          {
            "hex": "0x01000000000000000000000000004c4b40",
            "repr": "u5000000",
            "name": "price",
            "type": "uint"
          },
          {
            "hex": "0x0100000000000000000000000000000064",
            "repr": "u100",
            "name": "commission",
            "type": "uint"
          }
        ]
      }
    },
    {
      "tx_id": "0xff01d7b8feb95960e06d2b322d5753880ff426f49a3425ef30e36ec080cfce70",
      "nonce": 78,
      "fee_rate": "626745",
      "sender_address": "SP3JYTEYFKCY12WTY7TNRCQ392D1WF0YTPV71P0EM",
      "sponsored": false,
      "post_condition_mode": "deny",
      "post_conditions": [
        {
          "type": "stx",
          "condition_code": "sent_equal_to",
          "amount": "265000000",
          "principal": {
            "type_id": "principal_standard",
            "address": "SP3JYTEYFKCY12WTY7TNRCQ392D1WF0YTPV71P0EM"
          }
        },
        {
          "type": "fungible",
          "condition_code": "sent_greater_than_or_equal_to",
          "amount": "95601116103",
          "principal": {
            "type_id": "principal_contract",
            "contract_name": "liquidity-token-v5kcp63j1up",
            "address": "SP1Z92MPDQEWZXW36VX71Q25HKF5K2EPCJ304F275"
          },
          "asset": {
            "contract_name": "fari-token-mn",
            "asset_name": "fari",
            "contract_address": "SP213KNHB5QD308TEESY1ZMX1BP8EZDPG4JWD0MEA"
          }
        }
      ],
      "anchor_mode": "any",
      "is_unanchored": false,
      "block_hash": "0xb287a21633224ad05ea83d769302d794311da3be48a0eb0c616d02059909b645",
      "parent_block_hash": "0x501d2f28cca2e2b01aa3e343c56287abf9b35512b2895397579153c8e3775a28",
      "block_height": 39496,
      "burn_block_time": 1638096211,
      "burn_block_time_iso": "2021-11-28T10:43:31.000Z",
      "parent_burn_block_time": 1638095878,
      "parent_burn_block_time_iso": "2021-11-28T10:37:58.000Z",
      "canonical": true,
      "tx_index": 15,
      "tx_status": "success",
      "tx_result": {
        "hex": "0x070b00000002010000000000000000000000000fcb9440010000000000000000000000176e2df681",
        "repr": "(ok (list u265000000 u100632753793))"
      },
      "microblock_hash": "",
      "microblock_sequence": 2147483647,
      "microblock_canonical": true,
      "event_count": 4,
      "events": [],
      "execution_cost_read_count": 81,
      "execution_cost_read_length": 76863,
      "execution_cost_runtime": 97045000,
      "execution_cost_write_count": 9,
      "execution_cost_write_length": 236,
      "tx_type": "contract_call",
      "contract_call": {
        "contract_id": "SP1Z92MPDQEWZXW36VX71Q25HKF5K2EPCJ304F275.stackswap-swap-v5k",
        "function_name": "swap-x-for-y",
        "function_signature": "(define-public (swap-x-for-y (token-x-trait trait_reference) (token-y-trait trait_reference) (token-liquidity-trait trait_reference) (dx uint) (min-dy uint)))",
        "function_args": [
          {
            "hex": "0x06167e9152cdbbb9fef066df4e1b88b19bcb313acc900e777374782d746f6b656e2d763461",
            "repr": "SP1Z92MPDQEWZXW36VX71Q25HKF5K2EPCJ304F275.wstx-token-v4a",
            "name": "token-x-trait",
            "type": "trait_reference"
          },
          {
            "hex": "0x06168239d62b2dda30234e767c1fd3a15d90efb6d0240d666172692d746f6b656e2d6d6e",
            "repr": "SP213KNHB5QD308TEESY1ZMX1BP8EZDPG4JWD0MEA.fari-token-mn",
            "name": "token-y-trait",
            "type": "trait_reference"
          },
          {
            "hex": "0x06167e9152cdbbb9fef066df4e1b88b19bcb313acc901b6c69717569646974792d746f6b656e2d76356b637036336a317570",
            "repr": "SP1Z92MPDQEWZXW36VX71Q25HKF5K2EPCJ304F275.liquidity-token-v5kcp63j1up",
            "name": "token-liquidity-trait",
            "type": "trait_reference"
          },
          {
            "hex": "0x010000000000000000000000000fcb9440",
            "repr": "u265000000",
            "name": "dx",
            "type": "uint"
          },
          {
            "hex": "0x01000000000000000000000016424543c7",
            "repr": "u95601116103",
            "name": "min-dy",
            "type": "uint"
          }
        ]
      }
    },
    {
      "tx_id": "0xe346784a1e7ef45ed03a732b3e6435afaa9c42d942ddf02faa3e445b13705c50",
      "nonce": 57,
      "fee_rate": "400000",
      "sender_address": "SP1B6SRJYD3WGWKZW7ZH9XY815QME67QD8DE78MC4",
      "sponsored": false,
      "post_condition_mode": "deny",
      "post_conditions": [
        {
          "type": "stx",
          "condition_code": "sent_equal_to",
          "amount": "180000000",
          "principal": {
            "type_id": "principal_standard",
            "address": "SP1B6SRJYD3WGWKZW7ZH9XY815QME67QD8DE78MC4"
          }
        },
        {
          "type": "fungible",
          "condition_code": "sent_greater_than_or_equal_to",
          "amount": "67593838068",
          "principal": {
            "type_id": "principal_contract",
            "contract_name": "liquidity-token-v5kcp63j1up",
            "address": "SP1Z92MPDQEWZXW36VX71Q25HKF5K2EPCJ304F275"
          },
          "asset": {
            "contract_name": "fari-token-mn",
            "asset_name": "fari",
            "contract_address": "SP213KNHB5QD308TEESY1ZMX1BP8EZDPG4JWD0MEA"
          }
        }
      ],
      "anchor_mode": "any",
      "is_unanchored": false,
      "block_hash": "0xb287a21633224ad05ea83d769302d794311da3be48a0eb0c616d02059909b645",
      "parent_block_hash": "0x501d2f28cca2e2b01aa3e343c56287abf9b35512b2895397579153c8e3775a28",
      "block_height": 39496,
      "burn_block_time": 1638096211,
      "burn_block_time_iso": "2021-11-28T10:43:31.000Z",
      "parent_burn_block_time": 1638095878,
      "parent_burn_block_time_iso": "2021-11-28T10:37:58.000Z",
      "canonical": true,
      "tx_index": 16,
      "tx_status": "abort_by_post_condition",
      "tx_result": {
        "hex": "0x080100000000000000000000000000001045",
        "repr": "(err u4165)"
      },
      "microblock_hash": "",
      "microblock_sequence": 2147483647,
      "microblock_canonical": true,
      "event_count": 0,
      "events": [],
      "execution_cost_read_count": 32,
      "execution_cost_read_length": 35215,
      "execution_cost_runtime": 49056000,
      "execution_cost_write_count": 6,
      "execution_cost_write_length": 234,
      "tx_type": "contract_call",
      "contract_call": {
        "contract_id": "SP1Z92MPDQEWZXW36VX71Q25HKF5K2EPCJ304F275.stackswap-swap-v5k",
        "function_name": "swap-x-for-y",
        "function_signature": "(define-public (swap-x-for-y (token-x-trait trait_reference) (token-y-trait trait_reference) (token-liquidity-trait trait_reference) (dx uint) (min-dy uint)))",
        "function_args": [
          {
            "hex": "0x06167e9152cdbbb9fef066df4e1b88b19bcb313acc900e777374782d746f6b656e2d763461",
            "repr": "SP1Z92MPDQEWZXW36VX71Q25HKF5K2EPCJ304F275.wstx-token-v4a",
            "name": "token-x-trait",
            "type": "trait_reference"
          },
          {
            "hex": "0x06168239d62b2dda30234e767c1fd3a15d90efb6d0240d666172692d746f6b656e2d6d6e",
            "repr": "SP213KNHB5QD308TEESY1ZMX1BP8EZDPG4JWD0MEA.fari-token-mn",
            "name": "token-y-trait",
            "type": "trait_reference"
          },
          {
            "hex": "0x06167e9152cdbbb9fef066df4e1b88b19bcb313acc901b6c69717569646974792d746f6b656e2d76356b637036336a317570",
            "repr": "SP1Z92MPDQEWZXW36VX71Q25HKF5K2EPCJ304F275.liquidity-token-v5kcp63j1up",
            "name": "token-liquidity-trait",
            "type": "trait_reference"
          },
          {
            "hex": "0x010000000000000000000000000aba9500",
            "repr": "u180000000",
            "name": "dx",
            "type": "uint"
          },
          {
            "hex": "0x0100000000000000000000000fbce81df4",
            "repr": "u67593838068",
            "name": "min-dy",
            "type": "uint"
          }
        ]
      }
    },
    {
      "tx_id": "0xbf5133b1b08bd22256614c156e1be1a97c1cefbac8ae3669f8712ec5d01260ff",
      "nonce": 5,
      "fee_rate": "70000",
      "sender_address": "SP322F1TCGFP3SZTV6735R8B0C10SCRXQS39BNTJ2",
      "sponsored": false,
      "post_condition_mode": "deny",
      "post_conditions": [],
      "anchor_mode": "any",
      "is_unanchored": false,
      "block_hash": "0xb287a21633224ad05ea83d769302d794311da3be48a0eb0c616d02059909b645",
      "parent_block_hash": "0x501d2f28cca2e2b01aa3e343c56287abf9b35512b2895397579153c8e3775a28",
      "block_height": 39496,
      "burn_block_time": 1638096211,
      "burn_block_time_iso": "2021-11-28T10:43:31.000Z",
      "parent_burn_block_time": 1638095878,
      "parent_burn_block_time_iso": "2021-11-28T10:37:58.000Z",
      "canonical": true,
      "tx_index": 17,
      "tx_status": "success",
      "tx_result": {
        "hex": "0x0701000000000000000000000000000003f0",
        "repr": "(ok u1008)"
      },
      "microblock_hash": "",
      "microblock_sequence": 2147483647,
      "microblock_canonical": true,
      "event_count": 1,
      "events": [],
      "execution_cost_read_count": 32,
      "execution_cost_read_length": 28091,
      "execution_cost_runtime": 63497000,
      "execution_cost_write_count": 4,
      "execution_cost_write_length": 16248,
      "tx_type": "contract_call",
      "contract_call": {
        "contract_id": "SP32AEEF6WW5Y0NMJ1S8SBSZDAY8R5J32NBZFPKKZ.free-punks-v0",
        "function_name": "mint",
        "function_signature": "(define-public (mint (punk-id uint)))",
        "function_args": [
          {
            "hex": "0x0100000000000000000000000000000000",
            "repr": "u0",
            "name": "punk-id",
            "type": "uint"
          }
        ]
      }
    },
    {
      "tx_id": "0xc4f51af90ab7af2d2e554732dd25d4b82a5cbf22dc2d0cdb60ef206b30beacf7",
      "nonce": 262,
      "fee_rate": "150000",
      "sender_address": "SP7E34QCWBZKMWMAHZJ7GEYYZR10986KAVPPZWYZ",
      "sponsored": false,
      "post_condition_mode": "deny",
      "post_conditions": [
        {
          "type": "non_fungible",
          "condition_code": "sent",
          "principal": {
            "type_id": "principal_contract",
            "contract_name": "stacks-art-market-v2",
            "address": "SPJW1XE278YMCEYMXB8ZFGJMH8ZVAAEDP2S2PJYG"
          },
          "asset": {
            "contract_name": "funky-donuts",
            "asset_name": "funky-donuts",
            "contract_address": "SPJW1XE278YMCEYMXB8ZFGJMH8ZVAAEDP2S2PJYG"
          },
          "asset_value": {
            "hex": "0x010000000000000000000000000000082f",
            "repr": "u2095"
          }
        }
      ],
      "anchor_mode": "any",
      "is_unanchored": false,
      "block_hash": "0xb287a21633224ad05ea83d769302d794311da3be48a0eb0c616d02059909b645",
      "parent_block_hash": "0x501d2f28cca2e2b01aa3e343c56287abf9b35512b2895397579153c8e3775a28",
      "block_height": 39496,
      "burn_block_time": 1638096211,
      "burn_block_time_iso": "2021-11-28T10:43:31.000Z",
      "parent_burn_block_time": 1638095878,
      "parent_burn_block_time_iso": "2021-11-28T10:37:58.000Z",
      "canonical": true,
      "tx_index": 20,
      "tx_status": "abort_by_post_condition",
      "tx_result": {
        "hex": "0x080100000000000000000000000000000065",
        "repr": "(err u101)"
      },
      "microblock_hash": "",
      "microblock_sequence": 2147483647,
      "microblock_canonical": true,
      "event_count": 0,
      "events": [],
      "execution_cost_read_count": 6,
      "execution_cost_read_length": 15938,
      "execution_cost_runtime": 16950000,
      "execution_cost_write_count": 0,
      "execution_cost_write_length": 0,
      "tx_type": "contract_call",
      "contract_call": {
        "contract_id": "SPJW1XE278YMCEYMXB8ZFGJMH8ZVAAEDP2S2PJYG.stacks-art-market-v2",
        "function_name": "unlist-item",
        "function_signature": "(define-public (unlist-item (collection trait_reference) (collection-id uint) (item-id uint)))",
        "function_args": [
          {
            "hex": "0x061625c0f5c23a3d463bd4ead1f7c2548a3fb529cdb00c66756e6b792d646f6e757473",
            "repr": "SPJW1XE278YMCEYMXB8ZFGJMH8ZVAAEDP2S2PJYG.funky-donuts",
            "name": "collection",
            "type": "trait_reference"
          },
          {
            "hex": "0x010000000000000000000000000000000b",
            "repr": "u11",
            "name": "collection-id",
            "type": "uint"
          },
          {
            "hex": "0x010000000000000000000000000000082f",
            "repr": "u2095",
            "name": "item-id",
            "type": "uint"
          }
        ]
      }
    },
    {
      "tx_id": "0xc83023342c5f6dee09e56c4c54665ab4cc6c1a5f85508b334cb0473dd86aa51e",
      "nonce": 361,
      "fee_rate": "110848",
      "sender_address": "SP15W83Y5K9X0H96RGX050GX2YFXVFCZTKAAT00H5",
      "sponsored": false,
      "post_condition_mode": "deny",
      "post_conditions": [
        {
          "type": "non_fungible",
          "condition_code": "sent",
          "principal": {
            "type_id": "principal_contract",
            "contract_name": "marketplace-v4",
            "address": "SPNWZ5V2TPWGQGVDR6T7B6RQ4XMGZ4PXTEE0VQ0S"
          },
          "asset": {
            "contract_name": "btc-badgers",
            "asset_name": "btc-badgers-nft",
            "contract_address": "SP38FN88VZ97GWV0E8THXRM6Z5VMFPHFY4J1JEC5S"
          },
          "asset_value": {
            "hex": "0x01000000000000000000000000000003b3",
            "repr": "u947"
          }
        }
      ],
      "anchor_mode": "any",
      "is_unanchored": false,
      "block_hash": "0xb287a21633224ad05ea83d769302d794311da3be48a0eb0c616d02059909b645",
      "parent_block_hash": "0x501d2f28cca2e2b01aa3e343c56287abf9b35512b2895397579153c8e3775a28",
      "block_height": 39496,
      "burn_block_time": 1638096211,
      "burn_block_time_iso": "2021-11-28T10:43:31.000Z",
      "parent_burn_block_time": 1638095878,
      "parent_burn_block_time_iso": "2021-11-28T10:37:58.000Z",
      "canonical": true,
      "tx_index": 21,
      "tx_status": "success",
      "tx_result": {
        "hex": "0x0703",
        "repr": "(ok true)"
      },
      "microblock_hash": "",
      "microblock_sequence": 2147483647,
      "microblock_canonical": true,
      "event_count": 1,
      "events": [],
      "execution_cost_read_count": 14,
      "execution_cost_read_length": 69689,
      "execution_cost_runtime": 74297000,
      "execution_cost_write_count": 4,
      "execution_cost_write_length": 546,
      "tx_type": "contract_call",
      "contract_call": {
        "contract_id": "SPNWZ5V2TPWGQGVDR6T7B6RQ4XMGZ4PXTEE0VQ0S.marketplace-v4",
        "function_name": "unlist-asset",
        "function_signature": "(define-public (unlist-asset (tradables trait_reference) (tradable-id uint)))",
        "function_args": [
          {
            "hex": "0x0616d0faa11bfa4f0e6c0e46a3dc50df2ee8fb45fe240b6274632d62616467657273",
            "repr": "SP38FN88VZ97GWV0E8THXRM6Z5VMFPHFY4J1JEC5S.btc-badgers",
            "name": "tradables",
            "type": "trait_reference"
          },
          {
            "hex": "0x01000000000000000000000000000003b3",
            "repr": "u947",
            "name": "tradable-id",
            "type": "uint"
          }
        ]
      }
    },
    {
      "tx_id": "0x560f258db12f681c55ec10c1ed80867b5e15ec2ce10c59ad7b574ad401109931",
      "nonce": 266,
      "fee_rate": "127352",
      "sender_address": "SPMH8TX6ZB5RNJC4CHR1K65T2A63NRK17VK717B0",
      "sponsored": false,
      "post_condition_mode": "deny",
      "post_conditions": [
        {
          "type": "non_fungible",
          "condition_code": "sent",
          "principal": {
            "type_id": "principal_standard",
            "address": "SPMH8TX6ZB5RNJC4CHR1K65T2A63NRK17VK717B0"
          },
          "asset": {
            "contract_name": "stacks-pops",
            "asset_name": "stacks-pops",
            "contract_address": "SPJW1XE278YMCEYMXB8ZFGJMH8ZVAAEDP2S2PJYG"
          },
          "asset_value": {
            "hex": "0x01000000000000000000000000000009ce",
            "repr": "u2510"
          }
        }
      ],
      "anchor_mode": "any",
      "is_unanchored": false,
      "block_hash": "0xb287a21633224ad05ea83d769302d794311da3be48a0eb0c616d02059909b645",
      "parent_block_hash": "0x501d2f28cca2e2b01aa3e343c56287abf9b35512b2895397579153c8e3775a28",
      "block_height": 39496,
      "burn_block_time": 1638096211,
      "burn_block_time_iso": "2021-11-28T10:43:31.000Z",
      "parent_burn_block_time": 1638095878,
      "parent_burn_block_time_iso": "2021-11-28T10:37:58.000Z",
      "canonical": true,
      "tx_index": 22,
      "tx_status": "success",
      "tx_result": {
        "hex": "0x0703",
        "repr": "(ok true)"
      },
      "microblock_hash": "",
      "microblock_sequence": 2147483647,
      "microblock_canonical": true,
      "event_count": 2,
      "events": [],
      "execution_cost_read_count": 24,
      "execution_cost_read_length": 106995,
      "execution_cost_runtime": 274034000,
      "execution_cost_write_count": 6,
      "execution_cost_write_length": 80754,
      "tx_type": "contract_call",
      "contract_call": {
        "contract_id": "SPJW1XE278YMCEYMXB8ZFGJMH8ZVAAEDP2S2PJYG.stacks-art-market-v2",
        "function_name": "list-item",
        "function_signature": "(define-public (list-item (collection trait_reference) (collection-id uint) (item-id uint) (price uint)))",
        "function_args": [
          {
            "hex": "0x061625c0f5c23a3d463bd4ead1f7c2548a3fb529cdb00b737461636b732d706f7073",
            "repr": "SPJW1XE278YMCEYMXB8ZFGJMH8ZVAAEDP2S2PJYG.stacks-pops",
            "name": "collection",
            "type": "trait_reference"
          },
          {
            "hex": "0x0100000000000000000000000000000003",
            "repr": "u3",
            "name": "collection-id",
            "type": "uint"
          },
          {
            "hex": "0x01000000000000000000000000000009ce",
            "repr": "u2510",
            "name": "item-id",
            "type": "uint"
          },
          {
            "hex": "0x0100000000000000000000000000e4e1c0",
            "repr": "u15000000",
            "name": "price",
            "type": "uint"
          }
        ]
      }
    },
    {
      "tx_id": "0xd035e2b337ba9b08e70c5e566ce3327f5c1b5ad8335aee06728e93a823caca0c",
      "nonce": 509,
      "fee_rate": "120000",
      "sender_address": "SP26XS066PNXV9M28HP4EZVS7R36JWVGERW58H5KW",
      "sponsored": false,
      "post_condition_mode": "allow",
      "post_conditions": [],
      "anchor_mode": "any",
      "is_unanchored": false,
      "block_hash": "0xb287a21633224ad05ea83d769302d794311da3be48a0eb0c616d02059909b645",
      "parent_block_hash": "0x501d2f28cca2e2b01aa3e343c56287abf9b35512b2895397579153c8e3775a28",
      "block_height": 39496,
      "burn_block_time": 1638096211,
      "burn_block_time_iso": "2021-11-28T10:43:31.000Z",
      "parent_burn_block_time": 1638095878,
      "parent_burn_block_time_iso": "2021-11-28T10:37:58.000Z",
      "canonical": true,
      "tx_index": 23,
      "tx_status": "success",
      "tx_result": {
        "hex": "0x070100000000000000000000000000d09efd",
        "repr": "(ok u13672189)"
      },
      "microblock_hash": "",
      "microblock_sequence": 2147483647,
      "microblock_canonical": true,
      "event_count": 9,
      "events": [],
      "execution_cost_read_count": 148,
      "execution_cost_read_length": 233787,
      "execution_cost_runtime": 263930000,
      "execution_cost_write_count": 10,
      "execution_cost_write_length": 285,
      "tx_type": "contract_call",
      "contract_call": {
        "contract_id": "SP2C2YFP12AJZB4MABJBAJ55XECVS7E4PMMZ89YZR.arkadiko-stake-registry-v1-1",
        "function_name": "stake-pending-rewards",
        "function_signature": "(define-public (stake-pending-rewards (registry-trait trait_reference) (pool-trait trait_reference) (diko-pool-trait trait_reference) (diko-token-trait trait_reference)))",
        "function_args": [
          {
            "hex": "0x0616982f3ec112a5f5928a5c96a914bd733793b896a51c61726b6164696b6f2d7374616b652d72656769737472792d76312d31",
            "repr": "SP2C2YFP12AJZB4MABJBAJ55XECVS7E4PMMZ89YZR.arkadiko-stake-registry-v1-1",
            "name": "registry-trait",
            "type": "trait_reference"
          },
          {
            "hex": "0x0616982f3ec112a5f5928a5c96a914bd733793b896a52261726b6164696b6f2d7374616b652d706f6f6c2d777374782d757364612d76312d31",
            "repr": "SP2C2YFP12AJZB4MABJBAJ55XECVS7E4PMMZ89YZR.arkadiko-stake-pool-wstx-usda-v1-1",
            "name": "pool-trait",
            "type": "trait_reference"
          },
          {
            "hex": "0x0616982f3ec112a5f5928a5c96a914bd733793b896a51d61726b6164696b6f2d7374616b652d706f6f6c2d64696b6f2d76312d31",
            "repr": "SP2C2YFP12AJZB4MABJBAJ55XECVS7E4PMMZ89YZR.arkadiko-stake-pool-diko-v1-1",
            "name": "diko-pool-trait",
            "type": "trait_reference"
          },
          {
            "hex": "0x0616982f3ec112a5f5928a5c96a914bd733793b896a50e61726b6164696b6f2d746f6b656e",
            "repr": "SP2C2YFP12AJZB4MABJBAJ55XECVS7E4PMMZ89YZR.arkadiko-token",
            "name": "diko-token-trait",
            "type": "trait_reference"
          }
        ]
      }
    },
    {
      "tx_id": "0xe6efa11771b9a6875d04abb37c978839d0c5605bf68bcce7df384bf1c5626f00",
      "nonce": 412,
      "fee_rate": "70000",
      "sender_address": "SP1AV2HX27BCGB7S91Q47J0K05NK334YBQ270TJJT",
      "sponsored": false,
      "post_condition_mode": "deny",
      "post_conditions": [],
      "anchor_mode": "any",
      "is_unanchored": false,
      "block_hash": "0xb287a21633224ad05ea83d769302d794311da3be48a0eb0c616d02059909b645",
      "parent_block_hash": "0x501d2f28cca2e2b01aa3e343c56287abf9b35512b2895397579153c8e3775a28",
      "block_height": 39496,
      "burn_block_time": 1638096211,
      "burn_block_time_iso": "2021-11-28T10:43:31.000Z",
      "parent_burn_block_time": 1638095878,
      "parent_burn_block_time_iso": "2021-11-28T10:37:58.000Z",
      "canonical": true,
      "tx_index": 24,
      "tx_status": "abort_by_response",
      "tx_result": {
        "hex": "0x080100000000000000000000000000000066",
        "repr": "(err u102)"
      },
      "microblock_hash": "",
      "microblock_sequence": 2147483647,
      "microblock_canonical": true,
      "event_count": 0,
      "events": [],
      "execution_cost_read_count": 308,
      "execution_cost_read_length": 17799,
      "execution_cost_runtime": 51523000,
      "execution_cost_write_count": 0,
      "execution_cost_write_length": 0,
      "tx_type": "contract_call",
      "contract_call": {
        "contract_id": "SP32AEEF6WW5Y0NMJ1S8SBSZDAY8R5J32NBZFPKKZ.free-punks-v0",
        "function_name": "mint",
        "function_signature": "(define-public (mint (punk-id uint)))",
        "function_args": [
          {
            "hex": "0x0100000000000000000000000000000000",
            "repr": "u0",
            "name": "punk-id",
            "type": "uint"
          }
        ]
      }
    },
    {
      "tx_id": "0x8946eb9f920095e04e830bb720402f15e5886298657d545fee58eca56f350bdb",
      "nonce": 286,
      "fee_rate": "110848",
      "sender_address": "SP3H2TDA41FD8MSVE73MHTEF75M4JDF7KR6XAXSZB",
      "sponsored": false,
      "post_condition_mode": "deny",
      "post_conditions": [
        {
          "type": "non_fungible",
          "condition_code": "sent",
          "principal": {
            "type_id": "principal_contract",
            "contract_name": "marketplace-v4",
            "address": "SPNWZ5V2TPWGQGVDR6T7B6RQ4XMGZ4PXTEE0VQ0S"
          },
          "asset": {
            "contract_name": "btc-badgers",
            "asset_name": "btc-badgers-nft",
            "contract_address": "SP38FN88VZ97GWV0E8THXRM6Z5VMFPHFY4J1JEC5S"
          },
          "asset_value": {
            "hex": "0x0100000000000000000000000000000026",
            "repr": "u38"
          }
        }
      ],
      "anchor_mode": "any",
      "is_unanchored": false,
      "block_hash": "0xb287a21633224ad05ea83d769302d794311da3be48a0eb0c616d02059909b645",
      "parent_block_hash": "0x501d2f28cca2e2b01aa3e343c56287abf9b35512b2895397579153c8e3775a28",
      "block_height": 39496,
      "burn_block_time": 1638096211,
      "burn_block_time_iso": "2021-11-28T10:43:31.000Z",
      "parent_burn_block_time": 1638095878,
      "parent_burn_block_time_iso": "2021-11-28T10:37:58.000Z",
      "canonical": true,
      "tx_index": 25,
      "tx_status": "success",
      "tx_result": {
        "hex": "0x0703",
        "repr": "(ok true)"
      },
      "microblock_hash": "",
      "microblock_sequence": 2147483647,
      "microblock_canonical": true,
      "event_count": 1,
      "events": [],
      "execution_cost_read_count": 14,
      "execution_cost_read_length": 69689,
      "execution_cost_runtime": 74297000,
      "execution_cost_write_count": 4,
      "execution_cost_write_length": 546,
      "tx_type": "contract_call",
      "contract_call": {
        "contract_id": "SPNWZ5V2TPWGQGVDR6T7B6RQ4XMGZ4PXTEE0VQ0S.marketplace-v4",
        "function_name": "unlist-asset",
        "function_signature": "(define-public (unlist-asset (tradables trait_reference) (tradable-id uint)))",
        "function_args": [
          {
            "hex": "0x0616d0faa11bfa4f0e6c0e46a3dc50df2ee8fb45fe240b6274632d62616467657273",
            "repr": "SP38FN88VZ97GWV0E8THXRM6Z5VMFPHFY4J1JEC5S.btc-badgers",
            "name": "tradables",
            "type": "trait_reference"
          },
          {
            "hex": "0x0100000000000000000000000000000026",
            "repr": "u38",
            "name": "tradable-id",
            "type": "uint"
          }
        ]
      }
    },
    {
      "tx_id": "0xe95345564ca72ee2edcd6c88a8d2e2dcfc0d611a598f27fd112603bca061a424",
      "nonce": 40,
      "fee_rate": "140980",
      "sender_address": "SP1Y325P1ZSTVMZBN815ZDN3WR857SA28JNHT57NF",
      "sponsored": false,
      "post_condition_mode": "deny",
      "post_conditions": [
        {
          "type": "fungible",
          "condition_code": "sent_equal_to",
          "amount": "60804539",
          "principal": {
            "type_id": "principal_standard",
            "address": "SP1Y325P1ZSTVMZBN815ZDN3WR857SA28JNHT57NF"
          },
          "asset": {
            "contract_name": "arkadiko-swap-token-wstx-diko",
            "asset_name": "wstx-diko",
            "contract_address": "SP2C2YFP12AJZB4MABJBAJ55XECVS7E4PMMZ89YZR"
          }
        }
      ],
      "anchor_mode": "any",
      "is_unanchored": false,
      "block_hash": "0xb287a21633224ad05ea83d769302d794311da3be48a0eb0c616d02059909b645",
      "parent_block_hash": "0x501d2f28cca2e2b01aa3e343c56287abf9b35512b2895397579153c8e3775a28",
      "block_height": 39496,
      "burn_block_time": 1638096211,
      "burn_block_time_iso": "2021-11-28T10:43:31.000Z",
      "parent_burn_block_time": 1638095878,
      "parent_burn_block_time_iso": "2021-11-28T10:37:58.000Z",
      "canonical": true,
      "tx_index": 26,
      "tx_status": "success",
      "tx_result": {
        "hex": "0x0701000000000000000000000000039fcdbb",
        "repr": "(ok u60804539)"
      },
      "microblock_hash": "",
      "microblock_sequence": 2147483647,
      "microblock_canonical": true,
      "event_count": 5,
      "events": [],
      "execution_cost_read_count": 155,
      "execution_cost_read_length": 224751,
      "execution_cost_runtime": 257522000,
      "execution_cost_write_count": 9,
      "execution_cost_write_length": 581,
      "tx_type": "contract_call",
      "contract_call": {
        "contract_id": "SP2C2YFP12AJZB4MABJBAJ55XECVS7E4PMMZ89YZR.arkadiko-stake-registry-v1-1",
        "function_name": "stake",
        "function_signature": "(define-public (stake (registry-trait trait_reference) (pool-trait trait_reference) (token-trait trait_reference) (amount uint)))",
        "function_args": [
          {
            "hex": "0x0616982f3ec112a5f5928a5c96a914bd733793b896a51c61726b6164696b6f2d7374616b652d72656769737472792d76312d31",
            "repr": "SP2C2YFP12AJZB4MABJBAJ55XECVS7E4PMMZ89YZR.arkadiko-stake-registry-v1-1",
            "name": "registry-trait",
            "type": "trait_reference"
          },
          {
            "hex": "0x0616982f3ec112a5f5928a5c96a914bd733793b896a52261726b6164696b6f2d7374616b652d706f6f6c2d777374782d64696b6f2d76312d31",
            "repr": "SP2C2YFP12AJZB4MABJBAJ55XECVS7E4PMMZ89YZR.arkadiko-stake-pool-wstx-diko-v1-1",
            "name": "pool-trait",
            "type": "trait_reference"
          },
          {
            "hex": "0x0616982f3ec112a5f5928a5c96a914bd733793b896a51d61726b6164696b6f2d737761702d746f6b656e2d777374782d64696b6f",
            "repr": "SP2C2YFP12AJZB4MABJBAJ55XECVS7E4PMMZ89YZR.arkadiko-swap-token-wstx-diko",
            "name": "token-trait",
            "type": "trait_reference"
          },
          {
            "hex": "0x01000000000000000000000000039fcdbb",
            "repr": "u60804539",
            "name": "amount",
            "type": "uint"
          }
        ]
      }
    },
    {
      "tx_id": "0x8a02bd2cc1f0760e8abf8a08199712d7634ca4874243d953f5539bd1e9da2778",
      "nonce": 51,
      "fee_rate": "106911",
      "sender_address": "SP3NDGET2RK5VKRTM47EJ8444MB3PKKJTJR3RPS0X",
      "sponsored": false,
      "post_condition_mode": "deny",
      "post_conditions": [
        {
          "type": "stx",
          "condition_code": "sent_less_than_or_equal_to",
          "amount": "45000000",
          "principal": {
            "type_id": "principal_standard",
            "address": "SP3NDGET2RK5VKRTM47EJ8444MB3PKKJTJR3RPS0X"
          }
        },
        {
          "type": "stx",
          "condition_code": "sent_less_than_or_equal_to",
          "amount": "45000000",
          "principal": {
            "type_id": "principal_contract",
            "contract_name": "bitcoin-monkeys",
            "address": "SP2KAF9RF86PVX3NEE27DFV1CQX0T4WGR41X3S45C"
          }
        }
      ],
      "anchor_mode": "any",
      "is_unanchored": false,
      "block_hash": "0xb287a21633224ad05ea83d769302d794311da3be48a0eb0c616d02059909b645",
      "parent_block_hash": "0x501d2f28cca2e2b01aa3e343c56287abf9b35512b2895397579153c8e3775a28",
      "block_height": 39496,
      "burn_block_time": 1638096211,
      "burn_block_time_iso": "2021-11-28T10:43:31.000Z",
      "parent_burn_block_time": 1638095878,
      "parent_burn_block_time_iso": "2021-11-28T10:37:58.000Z",
      "canonical": true,
      "tx_index": 27,
      "tx_status": "success",
      "tx_result": {
        "hex": "0x0701000000000000000000000000000007e3",
        "repr": "(ok u2019)"
      },
      "microblock_hash": "",
      "microblock_sequence": 2147483647,
      "microblock_canonical": true,
      "event_count": 5,
      "events": [],
      "execution_cost_read_count": 24,
      "execution_cost_read_length": 20432,
      "execution_cost_runtime": 21127000,
      "execution_cost_write_count": 6,
      "execution_cost_write_length": 22,
      "tx_type": "contract_call",
      "contract_call": {
        "contract_id": "SP2KAF9RF86PVX3NEE27DFV1CQX0T4WGR41X3S45C.bitcoin-monkeys",
        "function_name": "claim",
        "function_signature": "(define-public (claim ))"
      }
    },
    {
      "tx_id": "0x786f5f04c5559495e1349a1b74407f5f604a09b76cd6aec219f9c65d59ce0051",
      "nonce": 627,
      "fee_rate": "71200",
      "sender_address": "SPPV8FN67M28FRGAHKR5P2YJKJ41R6CSD55MZE94",
      "sponsored": false,
      "post_condition_mode": "allow",
      "post_conditions": [],
      "anchor_mode": "any",
      "is_unanchored": false,
      "block_hash": "0xb287a21633224ad05ea83d769302d794311da3be48a0eb0c616d02059909b645",
      "parent_block_hash": "0x501d2f28cca2e2b01aa3e343c56287abf9b35512b2895397579153c8e3775a28",
      "block_height": 39496,
      "burn_block_time": 1638096211,
      "burn_block_time_iso": "2021-11-28T10:43:31.000Z",
      "parent_burn_block_time": 1638095878,
      "parent_burn_block_time_iso": "2021-11-28T10:37:58.000Z",
      "canonical": true,
      "tx_index": 28,
      "tx_status": "success",
      "tx_result": {
        "hex": "0x070100000000000000000000000000000064",
        "repr": "(ok u100)"
      },
      "microblock_hash": "",
      "microblock_sequence": 2147483647,
      "microblock_canonical": true,
      "event_count": 2,
      "events": [],
      "execution_cost_read_count": 412,
      "execution_cost_read_length": 269598,
      "execution_cost_runtime": 808606000,
      "execution_cost_write_count": 18,
      "execution_cost_write_length": 169860,
      "tx_type": "contract_call",
      "contract_call": {
        "contract_id": "SPASZ0VJQTS22YR4HCCAGR05GGRF9V8TCM219YQ8.board-stake",
        "function_name": "unstake",
        "function_signature": "(define-public (unstake (token-id uint)))",
        "function_args": [
          {
            "hex": "0x0100000000000000000000000000000064",
            "repr": "u100",
            "name": "token-id",
            "type": "uint"
          }
        ]
      }
    }
  ],
  "total": 35
}
